Workbook

Sheet Nhân sự
B1: Name | C1: Job | D1: Role
A2: 1 | B2: ThanLV | C2: Project Manager | D2: PM
A3: 2 | B3: HieuND97 | C3: Project Manager | D3: PM
A4: 3 | B4: NhutNM5 | C4: Project Manager | D4: PM
A5: 4 | B5: TuyenNH1 | C5: CC | D5: SA
A6: 5 | B6: HienDT25 | C6: PMO | D6: PMO
A7: 6 | B7: ThongNH7 | C7: Solution Architect | D7: SA
A8: 7 | B8: VuCH2 | C8: Solution Architect | D8: SA
A9: 8 | B9: BaoNQ12 | C9: Solution Architect | D9: SA
A10: 9 | B10: AnhHY | C10: Application Developer | D10: BE
A11: 10 | B11: TamVM7 | C11: Application Developer | D11: FE
A12: 11 | B12: AnPD3 | C12: Application Developer | D12: BE
A13: 12 | B13: ToaiND2 | C13: Application Developer | D13: BE
... A50: 49 | B50: MinhNN73 | C50: Application Developer | D50: FE

Sheet Bảng đã đổi tên
A1: employee_id | B1: full_name | C1: account | D1: contract_type | E1: hire_date | F1: job_title | G1: toeic_score | H1: certificates | I1: department | J1: location | K1: parent_department | L1: child_department | M1: main_skill | N1: seniority(main) | O1: current_skiill | P1: seniority(current)
A2: 1 | B2: An NL | C2: user001 | D2: OFF | E2: 44958 | F2: Senior Project Manager | G2: 955 | H2: EnglishScore;Project Management Professional (PMP) | I2: FHM CMS | J2: HCM | K2: FHM | L2: FHM CMS | M2: Project Management | O2: Project Management | P2: Middle
A3: 2 | B3: Binh TT | C3: user002 | D3: OFF | E3: 46082 | F3: Project Manager | I3: FHM CMS | J3: HCM | K3: FHM | L3: FHM CMS | O3: Project Management | P3: Middle
A4: 3 | B4: Cuong HP | C4: user003 | D4: OFF | E4: 44667 | F4: Associate Project Manager | G4: 910 | H4: PROFESSIONAL SCRUM MASTER™ I;EnglishScore;PROFESSIONAL SCRUM MASTER™ II;Oracle Cloud Infrastructure 2023 Certified Foundations Associate;Oracle Cloud Data Management 2023 Certified Foundations Associate;Oracle Cloud Infrastructure 2023 AI Certified Foundations Associate;Core Designer Certificate;Advanced Designer Certificate;Oracle Cloud Infrastructure for Sunbird Ed Specialty;Aptis General - Listening Reading Speaking Writing - Level B2 | I4: FHM CMS | J4: HCM | K4: FHM | L4: FHM CMS | M4: .NET Framework | N4: Junior | O4: Project Management | P4: Junior
A5: 4 | B5: Dung QA | C5: user004 | D5: OFF | E5: 43062 | F5: Project Manager | G5: 620 | H5: C++ Standard Template Library;EnglishScore;FSOFT Foreign Language Proficiency Test - TOEIC Test;PROFESSIONAL SCRUM MASTER™ I;TOEIC (Internal);PMI Agile Certified Practitioner (PMI-ACP)® | I5: FHM CMS | J5: HCM | K5: FHM | L5: FHM CMS | M5: Project Management | O5: Project Management | P5: Junior
A6: 5 | B6: Giang MK | C6: user005 | D6: OFF | E6: 45427 | F6: Senior Software Engineer | G6: 720 | H6: EnglishScore;Azure Fundamentals | I6: FHM CMS | J6: HCM | K6: FHM | L6: FHM CMS | M6: .NET Framework | O6: .NET Framework | P6: Middle
A7: 6 | B7: Hai PL | C7: user006 | D7: OFF | E7: 45870 | F7: Solution Architect | G7: 740 | H7: Google Cloud Certified Professional Cloud Developer;Google Cloud Certified - Associate Cloud Engineer;Microsoft Certified: Azure Fundamentals;Microsoft Certified: Azure Developer Associate;Microsoft Certified: Azure Data Engineer Associate;Microsoft Certified: Azure Solutions Architect Expert;Microsoft Certified: DevOps Engineer Expert;Cloud Architect using Microsoft Azure;EnglishScore;FSOFT Foreign Language Proficiency Test - TOEIC Test;GitHub Copilot;Agile Scrum Foundation;Secure Coding | I7: FHM CMS | J7: HCM | K7: FHM | L7: FHM CMS | M7: .NET Framework | O7: Azure Cloud | P7: Middle
A8: 7 | B8: Hieu DN | C8: user007 | D8: OFF | E8: 43983 | F8: Solution Architect | G8: 755 | H8: Google Cloud Certified Professional Cloud Developer;Core Designer Certificate;Advanced Designer Certificate;Microsoft Certified: Azure Data Engineer Associate;Microsoft Certified: Azure Database Administrator Associate;Microsoft Certified: Azure IoT Developer Specialty;Microsoft Certified: Azure Solutions Architect Expert;Microsoft Certified: DevOps Engineer Expert;Google Cloud Certified - Associate Cloud Engineer;Microsoft Certified: Azure Fundamentals;Microsoft Certified: Azure Developer Associate;FSOFT Foreign Language Proficiency Test - TOEIC Test;EnglishScore;Cloud Architect using Microsoft Azure | I8: FHM CMS | J8: HCM | K8: FHM | L8: FHM CMS | M8: .NET Framework | N8: Middle | O8: Azure Cloud | P8: Senior
A9: 8 | B9: Hung LH | C9: user008 | D9: OFF | E9: 43366 | F9: Associate Solution Architect | G9: 735 | H9: Microsoft Certified: Azure Solutions Architect Expert;Developing ASP.NET MVC Web Applications;Microsoft Certified: Azure Developer Associate;PROFESSIONAL SCRUM MASTER™ I;Microsoft Certified Solutions Associate: Web Applications;Cloud Native Application Architecture;Th?c s? K? thu?t Ph?n m?m (AI MSE);Google Cloud Certified: Cloud Digital Leader;Agile Development;Data Mining Foundations and Practice;Microsoft Certified: Azure DevOps Engineer Expert;Core Designer Certificate;Advanced Designer Certificate;Microsoft Specialist: Programming in C#;Microsoft Certified: Azure Fundamentals;EnglishScore;Microsoft Certified: Azure Architect Technologies;AWS Cloud Architect;FSOFT Foreign Language Proficiency Test - TOEIC Test;Associate Traditional Web Developer O11 | I9: FHM CMS | J9: HCM | K9: FHM | L9: FHM CMS | M9: Azure Cloud | O9: Azure Cloud | P9: Senior
A10: 9 | B10: Khanh BT | C10: user009 | D10: OFF | E10: 44028 | F10: Senior Software Engineer | G10: 955 | H10: Advanced Designer Certificate;Core Designer Certificate;EnglishScore;FSOFT Foreign Language Proficiency Test - TOEIC Test;GitHub Copilot;Google Cloud Certified - Associate Cloud Engineer;AWS Certified Developer - Associate;Microsoft Certified: Azure AI Engineer Associate;PROFESSIONAL SCRUM MASTER™ I;PROFESSIONAL SCRUM MASTER™ II;Enrich skills to succeed - Go Platform;AWS Certified Solutions Architect - Associate;Microsoft Certified: Azure AI Fundamentals;Microsoft Certified: Azure Data Fundamentals | I10: FHM CMS | J10: HCM | K10: FHM | L10: FHM CMS | M10: Java Framework | N10: Middle | O10: Java Framework | P10: Middle
A11: 10 | B11: Lam AK | C11: user010 | D11: OFF | E11: 45084 | F11: Senior Software Engineer | G11: 550 | H11: EnglishScore | I11: FHM CMS | J11: HCM | K11: FHM | L11: FHM CMS | M11: ReactJS Framework | N11: Senior | O11: ReactJS Framework | P11: Senior
A12: 11 | B12: Linh NL | C12: user011 | D12: OFF | E12: 46007 | F12: Senior Software Engineer | I12: FHM CMS | J12: HCM | K12: FHM | L12: FHM CMS | M12: .NET Framework | N12: Middle | O12: Java Framework | P12: Junior
A13: 12 | B13: Long TT | C13: user012 | D13: OFF | E13: 46026 | F13: Application Developer | H13: EnglishScore;Developer Certificate;GitHub Copilot;Microsoft Certified: Azure Fundamentals;Java Programming;Agile Scrum Foundation | I13: F1 JDC | J13: HCM | K13: F1 | L13: F1 JDC | M13: Java Framework | N13: Junior | O13: Java Framework | P13: Junior
A14: 13 | B14: Minh HP | C14: user013 | D14: OFF | E14: 45084 | F14: Senior Software Engineer | G14: 665 | H14: Cloud Developer;EnglishScore;Product Manager | I14: FHM CMS | J14: HCM | K14: FHM | L14: FHM CMS | M14: ReactJS Framework | N14: Middle | O14: Java Framework | P14: Middle
A15: 14 | B15: Nam QA | C15: user014 | D15: OFF | E15: 44005 | F15: Senior Business Analyst | G15: 710 | H15: EnglishScore;Japanese Language Proficiency Test N2;FSOFT Foreign Language Proficiency Test - TOEIC Test;Introduction to Data Science in Python;FSOFT Customer Interview Training;Interview Skill for Interviewer | I15: FHM CMS | J15: HCM | K15: FHM | L15: FHM CMS | M15: BA | N15: Senior | O15: BA | P15: Junior
A16: 15 | B16: Ngoc MK | C16: user015 | D16: OFF | E16: 46023 | F16: Associate Business Analyst | H16: Japanese Language Proficiency Test N3 | I16: FHM CMS | J16: HCM | K16: FHM | L16: FHM CMS | O16: BA | P16: Junior
A17: 16 | B17: Nhat PL | C17: user016 | D17: OFF | E17: 45283 | F17: Business Analyst | G17: 755 | H17: EnglishScore;Business Analytics;Developer Certificate;Generative AI Practitioner Certificate;ML Practitioner Certificate;AI in Office;Core Designer Certificate;Advanced Designer Certificate | I17: FHM CMS | J17: HCM | K17: FHM | L17: FHM CMS | M17: BA | N17: Junior | O17: BA | P17: Junior
A18: 17 | B18: Phong DN | C18: user017 | D18: OFF | E18: 45854 | F18: Business Analyst | H18: Japanese Language Proficiency Test N2 | I18: FHM CMS | J18: HCM | K18: FHM | L18: FHM CMS | O18: BA | P18: Middle
A19: 18 | B19: Phuc LH | C19: user018 | D19: OFF | E19: 45283 | F19: Business Analyst | H19: Japanese Language Proficiency Test N2;Japanese Language Proficiency Test N3;TOEIC Listening & Reading;Professional Scrum Product Owner I;Core Designer Certificate;Business Intelligence Analytics;Programming for Data Science with Python;Introduction to Python;Microsoft Certified: Azure Fundamentals;Professional Scrum Product Owner II;Certification of Capability in Business Analysis (CCBA);Introduction to Version Control | I19: FHM CMS | J19: HCM | K19: FHM | L19: FHM CMS | M19: BA | N19: Junior | O19: BA | P19: Junior
A20: 19 | B20: Quan BT | C20: user019 | D20: OFF | E20: 45283 | F20: Business Analyst | H20: SQL;Japanese Language Proficiency Test N2 | I20: FHM CMS | J20: HCM | K20: FHM | L20: FHM CMS | M20: BA | N20: Junior | O20: BA | P20: Junior
A21: 20 | B21: Thao AK | C21: user020 | D21: OFF | E21: 46014 | F21: Senior Software Engineer | I21: FHM CMS | J21: HCM | K21: FHM | L21: FHM CMS | O21: Java Framework | P21: Junior
A22: 21 | B22: Trang NL | C22: user021 | D22: OFF | E22: 46149 | F22: Senior Software Engineer | I22: FHM CMS | J22: HCM | K22: FHM | L22: FHM CMS | O22: ReactJS Framework | P22: Senior
A23: 22 | B23: Truc TT | C23: user022 | D23: OFF | E23: 45885 | F23: Senior Software Engineer | G23: 690 | H23: Microsoft Certified: Azure Data Fundamentals;PROFESSIONAL SCRUM MASTER™ I | I23: FHM CMS | J23: HCM | K23: FHM | L23: FHM CMS | M23: .NET Framework | O23: .NET Framework | P23: Middle
A24: 23 | B24: Tuan HP | C24: user023 | D24: OFF | E24: 46168 | F24: Application Developer | G24: 710 | H24: EnglishScore;Developer Certificate;GitHub Copilot;Microsoft Certified: Azure Fundamentals;Java Programming;SQL | I24: F1 JDC | J24: HCM | K24: F1 | L24: F1 JDC | M24: Java Framework | N24: Junior | O24: Java Framework | P24: Junior
A25: 24 | B25: Van QA | C25: user024 | D25: OFF | E25: 40929 | F25: Senior Business Analyst | G25: 595 | H25: FSOFT Foreign Language Proficiency Test - TOEIC Test;ISTQB Certified Tester - Foundation Level;EnglishScore | I25: FHM CMS | J25: HCM | K25: FHM | L25: FHM CMS | M25: BA | N25: Senior | O25: DevOps & CI/CD Engineering | P25: Junior
A26: 25 | B26: Vy MK | C26: user025 | D26: OFF | E26: 43182 | F26: Senior Software Engineer | G26: 575 | H26: Effective Problem-Solving and Decision-Making;Developing Web Apps (OutSystems 11);EnglishScore;FSOFT Foreign Language Proficiency Test - TOEIC Test | I26: FHM CMS | J26: HCM | K26: FHM | L26: FHM CMS | M26: .NET Framework | N26: Senior | O26: DevOps & CI/CD Engineering | P26: Junior
A27: 26 | B27: An PL | C27: user026 | D27: OFF | E27: 46174 | F27: Application Developer | G27: 880 | H27: EnglishScore;Developer Certificate;GitHub Copilot;Microsoft Certified: Azure Fundamentals;Agile Scrum Foundation | I27: F1 JDC | J27: HCM | K27: F1 | L27: F1 JDC | M27: Java Framework | N27: Junior | O27: Java Framework | P27: Junior
A28: 27 | B28: Binh DN | C28: user027 | D28: OFF | E28: 46174 | F28: Application Developer | G28: 850 | H28: Cloud Developer;EnglishScore;Product Manager;GitHub Copilot;React Developer;Microsoft Certified: Azure Fundamentals;Agile Scrum Foundation | I28: F1 JDC | J28: HCM | K28: F1 | L28: F1 JDC | M28: ReactJS Framework | N28: Middle | O28: ReactJS Framework | P28: Middle
A29: 28 | B29: Cuong LH | C29: user028 | D29: OFF | E29: 46218 | F29: Application Developer | I29: F1 JDC | J29: HCM | K29: F1 | L29: F1 JDC | M29: Java Framework | N29: Junior | O29: Java Framework | P29: Junior
A30: 29 | B30: Dung BT | C30: user029 | D30: OFF | E30: 45923 | F30: Principal Test Analyst | I30: FHM CMS | J30: HCM | K30: FHM | L30: FHM CMS | O30: Manual Test | P30: Senior
A31: 30 | B31: Giang AK | C31: user030 | D31: OFF | E31: 46168 | F31: Manual Test | I31: FHM CMS | J31: HCM | K31: FHM | L31: FHM CMS | O31: Manual Test | P31: Junior
A32: 31 | B32: Hai NL | C32: user031 | D32: OFF | E32: 45398 | F32: Senior Software Tester | G32: 710 | H32: EnglishScore;ISTQB Certified Tester Advanced Level - Test Analyst | I32: FHM CMS | J32: HCM | K32: FHM | L32: FHM CMS | O32: Manual Test | P32: Middle
A33: 32 | B33: Hieu TT | C33: user032 | D33: OFF | E33: 45937 | F33: Senior Software Tester | I33: FHM CMS | J33: HCM | K33: FHM | L33: FHM CMS | O33: Manual Test | P33: Middle
A34: 33 | B34: Hung HP | C34: user033 | D34: OFF | E34: 43206 | F34: Senior Software Engineer | G34: 620 | H34: EnglishScore;PROFESSIONAL SCRUM MASTER™ I;Developing ASP.NET MVC Web Applications;Microsoft Specialist: Programming in C#;FSOFT Foreign Language Proficiency Test - TOEIC Test;Microsoft Certified: Azure Fundamentals;Microsoft Certified: Azure DevOps Engineer Expert;Microsoft Certified: DevOps Engineer Expert;Microsoft Certified: Azure Administrator Associate;TOEIC (Internal);TOEIC Listening & Reading;Microsoft Certified: Azure Solutions Architect Expert;Microsoft Certified: Identity and Access Administrator Associate;Microsoft Certified: Security, Compliance, and Identity Fundamentals;Microsoft Certified: Azure Data Engineer Associate;Microsoft Certified: Azure Data Fundamentals;Microsoft Certified: Azure Network Engineer Associate;Microsoft Certified: Azure Developer Associate | I34: FHM CMS | J34: HCM | K34: FHM | L34: FHM CMS | M34: .NET Framework | N34: Middle | O34: Azure Cloud | P34: Senior
A35: 34 | B35: Khanh QA | C35: user034 | D35: OFF | E35: 46149 | F35: Associate Business Analyst | H35: Japanese Language Proficiency Test N3 | I35: FHM JFL | J35: HCM | K35: FHM | L35: FHM JFL | O35: BA | P35: Junior
A36: 35 | B36: Lam MK | C36: user035 | D36: OFF | E36: 46244 | F36: Manual Test | H36: ISTQB Foundation;EnglishScore;Automation Testing;API Testing | I36: IVS | J36: HCM | K36: IVS | L36: IVS | O36: Manual Test | P36: Middle
A37: 36 | B37: Linh PL | C37: user036 | D37: OFF | E37: 46237 | F37: Business Analyst | H37: EnglishScore;Business Analytics;Agile Scrum Foundation;Japanese Language Proficiency Test N3;Generative AI Practitioner Certificate | I37: FHM JFL | J37: HCM | K37: FHM | L37: FHM JFL | M37: BA | O37: BA | P37: Middle
A38: 37 | B38: Long DN | C38: user037 | D38: OFF | E38: 46237 | F38: Business Analyst | I38: FHM JFL | J38: HCM | K38: FHM | L38: FHM JFL
A39: 38 | B39: Minh LH | C39: user038 | D39: OFF | E39: 46237 | F39: Application Developer | H39: EnglishScore;Developer Certificate;GitHub Copilot;Microsoft Certified: Azure Fundamentals | I39: FHM CMS | J39: HCM | K39: FHM | L39: FHM CMS
A40: 39 | B40: Nam BT | C40: user039 | E40: 46029 | F40: Intern - DEV | I40: FHM CMS | J40: HCM | K40: FHM | L40: FHM CMS | O40: Java Framework | P40: Intern
A41: 40 | B41: Ngoc AK | C41: user040 | E41: 46029 | F41: Intern - DEV | I41: FHM CMS | J41: HCM | K41: FHM | L41: FHM CMS | O41: Java Framework | P41: Intern
A42: 41 | B42: Nhat NL | C42: user041 | E42: 46029 | F42: Intern - DEV | I42: FHM CMS | J42: HCM | K42: FHM | L42: FHM CMS | O42: Java Framework | P42: Intern
A43: 42 | B43: Phong TT | C43: user042 | E43: 46029 | F43: Intern - DEV | I43: FHM CMS | J43: HCM | K43: FHM | L43: FHM CMS | O43: Java Framework | P43: Intern
A44: 43 | B44: Phuc HP | C44: user043 | E44: 46089 | F44: OJT - DEV | I44: FHM CMS | J44: HCM | K44: FHM | L44: FHM CMS | O44: Java Framework | P44: OJT
A45: 44 | B45: Quan QA | C45: user044 | E45: 46089 | F45: OJT - DEV | I45: FHM CMS | J45: HCM | K45: FHM | L45: FHM CMS | O45: Java Framework | P45: OJT
A46: 45 | B46: Thao MK | C46: user045 | E46: 46089 | F46: OJT - DEV | I46: FHM CMS | J46: HCM | K46: FHM | L46: FHM CMS | O46: Java Framework | P46: OJT
A47: 46 | B47: Trang PL | C47: user046 | E47: 46258 | F47: Intern - Tester | I47: FHM CMS | J47: HCM | K47: FHM | L47: FHM CMS | O47: Manual Test | P47: Intern
A48: 47 | B48: Truc DN | C48: user047 | E48: 46258 | F48: Intern - Tester | I48: FHM CMS | J48: HCM | K48: FHM | L48: FHM CMS | O48: Manual Test | P48: Intern
A49: 48 | B49: Tuan LH | C49: user048 | E49: 46258 | F49: Intern - Tester | I49: FHM CMS | J49: HCM | K49: FHM | L49: FHM CMS | O49: Manual Test | P49: Intern
A50: 49 | B50: Van BT | C50: user049 | D50: PRO | E50: 46250 | F50: Senior Software Engineer | G50: 895 | H50: IELTS 6.5;AWS Cloud Architect;Java Programming;EnglishScore;Data Structures and Algorithms;ML Practitioner Certificate;MLOps Practitioner Certificate;Core Designer Certificate;Advanced Designer Certificate;Developer Certificate;Google Data Analytics | I50: FHM CMS | J50: HCM | K50: FHM | L50: FHM CMS | M50: Java Framework | N50: Junior | O50: Java Framework | P50: Junior

Sheet Bảng nhân sự CMS
A1: No | B1: Full Name | C1: Account | D1: Contract Type | E1: Hire Date | F1: Job Title | G1: Toeic Score | H1: Certificates | I1: Department | J1: Location | K1: Parent Department | L1: Child Department | M1: Main Skill | N1: Seniority(Main) | O1: Current Skill | P1: Seniority(Current) | Q1: Job Rank | R1: Customer Co | S1: Customer code | T1: Project Dept | U1: Project co | V1: Project Co2 | W1: Project Code3 | X1: Project code 2 | Y1: Project Type | Z1: Role
A2: 1 | B2: Chu Chiêu Dủ An | C2: user001 | D2: OFF | E2: 45398 | F2: Senior Software Engineer | G2: 895 | H2: EnglishScore;Developer Certificate;Advanced Designer Certificate;ML Practitioner Certificate;MLOps Practitioner Certificate;Core Designer Certificate;GitHub Copilot;Data Engineering with Microsoft Azure;TOEIC Listening & Reading | I2: FHM CMS | J2: HCM | K2: FHM | L2: FHM CMS | M2: Java Framework | N2: Middle | O2: Java Framework | P2: Senior | Q2: DEVE03 | R2: FR | S2: =VLOOKUP(R2,Customer_Mapping!A:B,2,FALSE) -> Customer_001 | T2: FSO.HCM.FHM.CMS | U2: FRDLO | V2: FMCS3 | W2: =IF(U2="","",IFERROR(_xlfn.XLOOKUP(U2,Mapping!$A:$A,Mapping!$B:$B),"")) -> Project_001 | X2: =IF(V2="","",IFERROR(_xlfn.XLOOKUP(V2,Mapping!$A:$A,Mapping!$B:$B),"")) -> Project_017 | Y2: External | Z2: Java Framework
A3: 2 | B3: Bùi Tuấn Anh | C3: user002 | D3: OFF | E3: 44896 | F3: Software Engineer | G3: 690 | H3: Java Web Developer;EnglishScore | I3: FHM CMS | J3: HCM | K3: FHM | L3: FHM CMS | M3: Java Framework | N3: Junior | O3: IT Service | P3: Junior | Q3: DEVE02 | R3: FR | S3: =VLOOKUP(R3,Customer_Mapping!A:B,2,FALSE) -> Customer_001 | T3: FSO.HCM.FHM.CMS | U3: Portal_EU01 | V3: FRDLO | W3: =IF(U3="","",IFERROR(_xlfn.XLOOKUP(U3,Mapping!$A:$A,Mapping!$B:$B),"")) -> Project_002 | X3: =IF(V3="","",IFERROR(_xlfn.XLOOKUP(V3,Mapping!$A:$A,Mapping!$B:$B),"")) -> Project_001 | Y3: External | Z3: Java Framework
A4: 3 | B4: Huỳnh Ngọc Minh Anh | C4: user003 | D4: OFF | E4: 44902 | F4: Business Analyst | G4: 945 | H4: EnglishScore;PROFESSIONAL SCRUM MASTER™ I | I4: FHM CMS | J4: HCM | K4: FHM | L4: FHM CMS | M4: BA | N4: Junior | O4: BA | P4: Middle | Q4: BANE02 | R4: Casio-Europe | S4: =VLOOKUP(R4,Customer_Mapping!A:B,2,FALSE) -> Customer_002 | T4: FSO.HCM.FHM.CMS | U4: JOCAR_Replace | V4: Portal_EU01 | W4: =IF(U4="","",IFERROR(_xlfn.XLOOKUP(U4,Mapping!$A:$A,Mapping!$B:$B),"")) -> Project_003 | X4: =IF(V4="","",IFERROR(_xlfn.XLOOKUP(V4,Mapping!$A:$A,Mapping!$B:$B),"")) -> Project_002 | Y4: External | Z4: BA
A5: 4 | B5: Hoàng Yến Anh | C5: user004 | D5: OFF | E5: 44028 | F5: Senior Software Engineer | G5: 955 | H5: Advanced Designer Certificate;Core Designer Certificate;EnglishScore;FSOFT Foreign Language Proficiency Test - TOEIC Test;GitHub Copilot;Google Cloud Certified - Associate Cloud Engineer;AWS Certified Developer - Associate;Microsoft Certified: Azure AI Engineer Associate;PROFESSIONAL SCRUM MASTER™ I;PROFESSIONAL SCRUM MASTER™ II;Enrich skills to succeed - Go Platform;AWS Certified Solutions Architect - Associate;Microsoft Certified: Azure AI Fundamentals;Microsoft Certified: Azure Data Fundamentals | I5: FHM CMS | J5: HCM | K5: FHM | L5: FHM CMS | M5: Java Framework | N5: Middle | O5: Java Framework | P5: Middle | Q5: DEVE03 | R5: JJCM | S5: =VLOOKUP(R5,Customer_Mapping!A:B,2,FALSE) -> Customer_003 | T5: FSO.HCM.FHM.CMS | U5: FVD2025 | V5: JOCAR_Replace | W5: =IF(U5="","",IFERROR(_xlfn.XLOOKUP(U5,Mapping!$A:$A,Mapping!$B:$B),"")) -> Project_004 | X5: =IF(V5="","",IFERROR(_xlfn.XLOOKUP(V5,Mapping!$A:$A,Mapping!$B:$B),"")) -> Project_003 | Y5: External | Z5: Java Framework
A6: 5 | B6: Nguyễn Hà Kim Anh | C6: user005 | D6: OFF | E6: 46082 | F6: Associate Project Manager | H6: IELTS 6.5 | I6: FHM CMS | J6: HCM | K6: FHM | L6: FHM CMS | M6: Project Management | N6: Junior | O6: Project Management | P6: Junior | Q6: SPMA01 | R6: FR | S6: =VLOOKUP(R6,Customer_Mapping!A:B,2,FALSE) -> Customer_001 | T6: FSO.HCM.FHM.CMS | U6: SBR_Buhin26 | V6: FVD2025 | W6: =IF(U6="","",IFERROR(_xlfn.XLOOKUP(U6,Mapping!$A:$A,Mapping!$B:$B),"")) -> Project_005 | X6: =IF(V6="","",IFERROR(_xlfn.XLOOKUP(V6,Mapping!$A:$A,Mapping!$B:$B),"")) -> Project_004 | Y6: External | Z6: Project Management
A7: 6 | B7: Nông Minh Anh | C7: user006 | D7: OFF | E7: 45673 | F7: Software Engineer | H7: TOEIC Listening & Reading;Japanese Language Proficiency Test N3;GitHub Copilot | I7: FHM CMS | J7: HCM | K7: FHM | L7: FHM CMS | M7: Java Framework | N7: Junior | O7: Java Framework | P7: Middle | Q7: DEVE02 | R7: SBR | S7: =VLOOKUP(R7,Customer_Mapping!A:B,2,FALSE) -> Customer_004 | T7: FSO.HCM.FHM.CMS | U7: SDX_Y3 | V7: SBR_Buhin26 | W7: =IF(U7="","",IFERROR(_xlfn.XLOOKUP(U7,Mapping!$A:$A,Mapping!$B:$B),"")) -> Project_006 | X7: =IF(V7="","",IFERROR(_xlfn.XLOOKUP(V7,Mapping!$A:$A,Mapping!$B:$B),"")) -> Project_005 | Y7: External | Z7: Java Framework
A8: 7 | B8: Phạm Lê Thế Anh | C8: user007 | D8: OFF | E8: 44667 | F8: Software Engineer | G8: 640 | H8: EnglishScore;Microsoft Certified: Azure Developer Associate;Software Engineer Intern;Advanced Designer Certificate;IELTS 5.5;Microsoft Certified: Azure Fundamentals | I8: FHM CMS | J8: HCM | K8: FHM | L8: FHM CMS | M8: AWS Cloud | O8: DevOps & CI/CD Engineering | P8: Middle | Q8: DEVE02 | R8: Sodexo | S8: =VLOOKUP(R8,Customer_Mapping!A:B,2,FALSE) -> Customer_005 | T8: FSO.HCM.FHM.CMS | U8: CDX_MS | V8: SDX_Y3 | W8: =IF(U8="","",IFERROR(_xlfn.XLOOKUP(U8,Mapping!$A:$A,Mapping!$B:$B),"")) -> Project_007 | X8: =IF(V8="","",IFERROR(_xlfn.XLOOKUP(V8,Mapping!$A:$A,Mapping!$B:$B),"")) -> Project_006 | Y8: External | Z8: AWS Cloud
A9: 8 | B9: Trần Quỳnh Anh | C9: user008 | D9: OFF | E9: 46060 | F9: Associate Project Manager | I9: FHM JFL | J9: HCM | K9: FHM | L9: FHM JFL | M9: Project Management | N9: Junior | O9: Project Management | P9: Junior | Q9: SPMA01 | R9: SonyGS | S9: =VLOOKUP(R9,Customer_Mapping!A:B,2,FALSE) -> Customer_006 | T9: FSO.HCM.FHM.CMS | U9: SF_Link_2026 | V9: CDX_MS | W9: =IF(U9="","",IFERROR(_xlfn.XLOOKUP(U9,Mapping!$A:$A,Mapping!$B:$B),"")) -> Project_008 | X9: =IF(V9="","",IFERROR(_xlfn.XLOOKUP(V9,Mapping!$A:$A,Mapping!$B:$B),"")) -> Project_007 | Y9: External | Z9: Project Management
A10: 9 | B10: Nguyễn Thị Duy An | C10: user009 | D10: OFF | E10: 45200 | F10: Senior Software Tester | G10: 550 | H10: EnglishScore;Model Context Protocol: Advanced Topics;Introduction to Agent Skills;Cluade Code in Action;Introduction to Model Context Protocol;Claude Code 101;Claude with the Anthropic API;Introduction to Claude Cowork;Introduction to subagents;ISTQB Certified Tester - Foundation Level;Agile Software Developer;Oracle Cloud Infrastructure 2023 Certified Foundations Associate;Oracle Cloud Infrastructure for Sunbird Ed Specialty | I10: FHM CMS | J10: HCM | K10: FHM | L10: FHM CMS | M10: Manual Test | N10: Senior | O10: Manual Test | P10: Junior | Q10: TEST04 | R10: SBR | S10: =VLOOKUP(R10,Customer_Mapping!A:B,2,FALSE) -> Customer_004 | T10: FSO.HCM.FHM.CMS | U10: JOCAR_Replace | V10: SF_Link_2026 | W10: =IF(U10="","",IFERROR(_xlfn.XLOOKUP(U10,Mapping!$A:$A,Mapping!$B:$B),"")) -> Project_003 | X10: =IF(V10="","",IFERROR(_xlfn.XLOOKUP(V10,Mapping!$A:$A,Mapping!$B:$B),"")) -> Project_008 | Y10: External | Z10: Manual Test
A11: 10 | B11: Phạm Duy An | C11: user010 | D11: OFF | E11: 46007 | F11: Senior Software Engineer | I11: FHM CMS | J11: HCM | K11: FHM | L11: FHM CMS | M11: .NET Framework | N11: Middle | O11: Java Framework | P11: Junior | Q11: DEVE03 | R11: JJCM | S11: =VLOOKUP(R11,Customer_Mapping!A:B,2,FALSE) -> Customer_003 | T11: FSO.HCM.FHM.CMS | U11: STL_AG_02 | V11: JOCAR_Replace | W11: =IF(U11="","",IFERROR(_xlfn.XLOOKUP(U11,Mapping!$A:$A,Mapping!$B:$B),"")) -> Project_009 | X11: =IF(V11="","",IFERROR(_xlfn.XLOOKUP(V11,Mapping!$A:$A,Mapping!$B:$B),"")) -> Project_003 | Y11: External | Z11: .NET Framework
A12: 11 | B12: Phan Đình Thiên Ân | C12: user011 | D12: OFF | E12: 45114 | F12: Software Engineer | G12: 895 | H12: GitHub Copilot;EnglishScore;Japanese Language Proficiency Test N5;TOEIC Listening & Reading;JUNIOR ANGULAR DEVELOPER;PROFESSIONAL SCRUM MASTER™ I;Oracle Cloud Infrastructure for Sunbird Ed Specialty;Oracle Cloud Infrastructure 2023 AI Certified Foundations Associate;Core Designer Certificate;Advanced Designer Certificate;Microsoft Certified: Azure Fundamentals;NVIDIA Getting Started with AI on Jetson Nano;Oracle Cloud Data Management 2023 Certified Foundations Associate;Oracle Cloud Infrastructure 2023 Certified Foundations Associate;Microsoft Certified: Azure AI Engineer Associate | I12: FHM CMS | J12: HCM | K12: FHM | L12: FHM CMS | M12: ReactJS Framework | O12: ReactJS Framework | P12: Junior | Q12: DEVE02 | R12: ANA | S12: =VLOOKUP(R12,Customer_Mapping!A:B,2,FALSE) -> Customer_007 | T12: FSO.HCM.FHM.CMS | U12: SIQAX3 | V12: STL_AG_02 | W12: =IF(U12="","",IFERROR(_xlfn.XLOOKUP(U12,Mapping!$A:$A,Mapping!$B:$B),"")) -> Project_010 | X12: =IF(V12="","",IFERROR(_xlfn.XLOOKUP(V12,Mapping!$A:$A,Mapping!$B:$B),"")) -> Project_009 | Y12: External | Z12: ReactJS Framework
A13: 12 | B13: Phạm Trường An | C13: user012 | D13: OFF | E13: 44400 | F13: Senior Software Engineer | G13: 690 | H13: Cloud Developer using Microsoft Azure;EnglishScore;Core Designer Certificate;Advanced Designer Certificate;Cloud Architect using Microsoft Azure;IELTS 5.0;Microsoft Certified: Azure Developer Associate;Microsoft Certified: Azure Fundamentals;Microsoft Certified: Azure Data Fundamentals | I13: FHM CMS | J13: HCM | K13: FHM | L13: FHM CMS | M13: .NET Framework | N13: Middle | O13: Azure Cloud | P13: Senior | Q13: DEVE03 | R13: SmartGroup | S13: =VLOOKUP(R13,Customer_Mapping!A:B,2,FALSE) -> Customer_008 | T13: FSO.HCM.FHM.CMS | U13: C99.CMS.AUD.IPDS 2026 | V13: SIQAX3 | W13: =IF(U13="","",IFERROR(_xlfn.XLOOKUP(U13,Mapping!$A:$A,Mapping!$B:$B),"")) -> Project_011 | X13: =IF(V13="","",IFERROR(_xlfn.XLOOKUP(V13,Mapping!$A:$A,Mapping!$B:$B),"")) -> Project_010 | Y13: External | Z13: .NET Framework
A14: 13 | B14: Trần Võ Hoàng Trọng Ân | C14: user013 | D14: OFF | E14: 45754 | F14: Software Engineer | H14: GitHub Copilot | I14: FHM CMS | J14: HCM | K14: FHM | L14: FHM CMS | M14: Java Framework | N14: Junior | O14: Java Framework | P14: Middle | Q14: DEVE02 | R14: COX-AM | S14: =VLOOKUP(R14,Customer_Mapping!A:B,2,FALSE) -> Customer_009 | T14: FSO.HCM.FHM.AKAT | U14: FVD2025 | V14: C99.CMS.AUD.IPDS 2026 | W14: =IF(U14="","",IFERROR(_xlfn.XLOOKUP(U14,Mapping!$A:$A,Mapping!$B:$B),"")) -> Project_004 | X14: =IF(V14="","",IFERROR(_xlfn.XLOOKUP(V14,Mapping!$A:$A,Mapping!$B:$B),"")) -> Project_011 | Y14: External | Z14: Java Framework
A15: 14 | B15: Võ Gia Ân | C15: user014 | D15: OFF | E15: 46060 | F15: Associate Software Engineer | H15: IELTS 6.5 | I15: FHM CMS | J15: HCM | K15: FHM | L15: FHM CMS | M15: Java Framework | N15: Junior | O15: Java Framework | P15: Junior | Q15: DEVE01 | R15: FR | S15: =VLOOKUP(R15,Customer_Mapping!A:B,2,FALSE) -> Customer_001 | T15: FSO.HCM.FHM.CMS | U15: C99.I5.LOG 2026 | V15: FVD2025 | W15: =IF(U15="","",IFERROR(_xlfn.XLOOKUP(U15,Mapping!$A:$A,Mapping!$B:$B),"")) -> Project_012 | X15: =IF(V15="","",IFERROR(_xlfn.XLOOKUP(V15,Mapping!$A:$A,Mapping!$B:$B),"")) -> Project_004 | Y15: External | Z15: Java Framework
A16: 15 | B16: Lương Xuân Bách | C16: user015 | D16: OFF | E16: 45419 | F16: Associate Software Engineer | G16: 895 | H16: EnglishScore | I16: FHM CMS | J16: HCM | K16: FHM | L16: FHM CMS | M16: Java Framework | N16: Junior | O16: .NET Framework | P16: Middle | Q16: DEVE01 | R16: COX-AM | S16: =VLOOKUP(R16,Customer_Mapping!A:B,2,FALSE) -> Customer_009 | T16: FSO.HCM.FHM.AKAT | U16: FRWMS2026 | V16: C99.I5.LOG 2026 | W16: =IF(U16="","",IFERROR(_xlfn.XLOOKUP(U16,Mapping!$A:$A,Mapping!$B:$B),"")) -> Project_013 | X16: =IF(V16="","",IFERROR(_xlfn.XLOOKUP(V16,Mapping!$A:$A,Mapping!$B:$B),"")) -> Project_012 | Y16: External | Z16: Java Framework
A17: 16 | B17: Phạm Công Bằng | C17: user016 | D17: OFF | E17: 45480 | F17: Senior Solution Architect | G17: 800 | H17: TOEFL ITP;EnglishScore | I17: FHM CMS | J17: HCM | K17: FHM | L17: FHM CMS | M17: Software Solution Architecture | O17: Java Framework | P17: Senior | Q17: SARE03 | R17: FR | S17: =VLOOKUP(R17,Customer_Mapping!A:B,2,FALSE) -> Customer_001 | T17: FSO.HCM.FHM.CMS | U17: NEWKONG2 | V17: FRWMS2026 | W17: =IF(U17="","",IFERROR(_xlfn.XLOOKUP(U17,Mapping!$A:$A,Mapping!$B:$B),"")) -> Project_014 | X17: =IF(V17="","",IFERROR(_xlfn.XLOOKUP(V17,Mapping!$A:$A,Mapping!$B:$B),"")) -> Project_013 | Y17: External | Z17: Software Solution Architecture
A18: 17 | B18: Đinh Thái Bảo | C18: user017 | D18: OFF | E18: 44013 | F18: Associate Project Manager | G18: 800 | H18: PROFESSIONAL SCRUM MASTER™ I;Advanced Designer Certificate;MLOps Practitioner Certificate;Core Designer Certificate;ML Practitioner Certificate;Developer Certificate;Oracle Cloud Data Management 2023 Certified Foundations Associate;SQL (Advanced);Google Analytics Certification;Oracle Cloud Infrastructure 2023 AI Certified Foundations Associate;ISTQB Certified Tester Advanced Level - Test Analyst;ISTQB Certified Tester - Foundation Level;FSOFT Foreign Language Proficiency Test - TOEIC Test;Product Manager;EnglishScore | I18: FHM CMS | J18: HCM | K18: FHM | L18: FHM CMS | M18: Manual Test | N18: Senior | O18: Manual Test | P18: Junior | Q18: SPMA01 | R18: FXSS | S18: =VLOOKUP(R18,Customer_Mapping!A:B,2,FALSE) -> Customer_010 | T18: FSO.HCM.FHM.CMS | U18: JOCAR_Replace | V18: NEWKONG2 | W18: =IF(U18="","",IFERROR(_xlfn.XLOOKUP(U18,Mapping!$A:$A,Mapping!$B:$B),"")) -> Project_003 | X18: =IF(V18="","",IFERROR(_xlfn.XLOOKUP(V18,Mapping!$A:$A,Mapping!$B:$B),"")) -> Project_014 | Y18: External | Z18: Manual Test
A19: 18 | B19: Nguyễn Quốc Bảo | C19: user018 | D19: OFF | E19: 43366 | F19: Associate Solution Architect | G19: 735 | H19: Microsoft Certified: Azure Solutions Architect Expert;Developing ASP.NET MVC Web Applications;Microsoft Certified: Azure Developer Associate;PROFESSIONAL SCRUM MASTER™ I;Microsoft Certified Solutions Associate: Web Applications;Cloud Native Application Architecture;Th?c s? K? thu?t Ph?n m?m (AI MSE);Google Cloud Certified: Cloud Digital Leader;Agile Development;Data Mining Foundations and Practice;Microsoft Certified: Azure DevOps Engineer Expert;Core Designer Certificate;Advanced Designer Certificate;Microsoft Specialist: Programming in C#;Microsoft Certified: Azure Fundamentals;EnglishScore;Microsoft Certified: Azure Architect Technologies;AWS Cloud Architect;FSOFT Foreign Language Proficiency Test - TOEIC Test;Associate Traditional Web Developer O11 | I19: FHM CMS | J19: HCM | K19: FHM | L19: FHM CMS | M19: Azure Cloud | O19: Azure Cloud | P19: Senior | Q19: SARE01 | R19: JJCM | S19: =VLOOKUP(R19,Customer_Mapping!A:B,2,FALSE) -> Customer_003 | T19: FSO.HCM.FHM.CMS | U19: SCU100 | V19: JOCAR_Replace | W19: =IF(U19="","",IFERROR(_xlfn.XLOOKUP(U19,Mapping!$A:$A,Mapping!$B:$B),"")) -> Project_015 | X19: =IF(V19="","",IFERROR(_xlfn.XLOOKUP(V19,Mapping!$A:$A,Mapping!$B:$B),"")) -> Project_003 | Y19: External | Z19: Azure Cloud
A20: 19 | B20: Phạm Hoàng Bảo | C20: user019 | D20: OFF | E20: 45154 | F20: Senior Software Engineer | G20: 690 | H20: AWS Certified Solutions Architect - Associate;Oracle Cloud Infrastructure for Sunbird Ed Specialty;Advanced Designer Certificate;Core Designer Certificate;EnglishScore | I20: FHM CMS | J20: HCM | K20: FHM | L20: FHM CMS | M20: .NET Framework | N20: Middle | O20: .NET Framework | P20: Middle | Q20: DEVE03 | R20: ISCUBE | S20: =VLOOKUP(R20,Customer_Mapping!A:B,2,FALSE) -> Customer_011 | T20: FSO.HCM.FHM.CMS | U20: C99.I5.LOG 2026 | V20: SCU100 | W20: =IF(U20="","",IFERROR(_xlfn.XLOOKUP(U20,Mapping!$A:$A,Mapping!$B:$B),"")) -> Project_012 | X20: =IF(V20="","",IFERROR(_xlfn.XLOOKUP(V20,Mapping!$A:$A,Mapping!$B:$B),"")) -> Project_015 | Y20: External | Z20: .NET Framework
A21: 20 | B21: Phạm Trần Huy Bảo | C21: user020 | D21: OFF | E21: 44850 | F21: Software Engineer | G21: 950 | H21: Vietnamese Standardized Test of English Proficiency (VSTEP) - Level 3/CEFR B1;Microsoft Certified: Azure Fundamentals;Full Stack Web Developer;Core Designer Certificate;Advanced Designer Certificate;EnglishScore;Java Fundamentals;Advanced Java Programming Techniques;Intermediate JavaScript;Front End Web Developer | I21: FHM CMS | J21: HCM | K21: FHM | L21: FHM CMS | M21: .NET Framework | N21: Junior | O21: .NET Framework | P21: Junior | Q21: DEVE02 | R21: COX-AM | S21: =VLOOKUP(R21,Customer_Mapping!A:B,2,FALSE) -> Customer_009 | T21: FSO.HCM.FHM.AKAT | U21: STL_AG_02 | V21: C99.I5.LOG 2026 | W21: =IF(U21="","",IFERROR(_xlfn.XLOOKUP(U21,Mapping!$A:$A,Mapping!$B:$B),"")) -> Project_009 | X21: =IF(V21="","",IFERROR(_xlfn.XLOOKUP(V21,Mapping!$A:$A,Mapping!$B:$B),"")) -> Project_012 | Y21: External | Z21: .NET Framework
A22: 21 | B22: Trần Gia Bảo | C22: user021 | D22: OFF | E22: 45642 | F22: Associate Data Engineer | H22: SQL (Basic) | I22: FHM CMS | J22: HCM | K22: FHM | L22: FHM CMS | M22: DE | N22: Junior | O22: DE | P22: Middle | Q22: DSEN01 | R22: ANA | S22: =VLOOKUP(R22,Customer_Mapping!A:B,2,FALSE) -> Customer_007 | T22: FSO.HCM.FHM.CMS | U22: FRWMS2026 | V22: STL_AG_02 | W22: =IF(U22="","",IFERROR(_xlfn.XLOOKUP(U22,Mapping!$A:$A,Mapping!$B:$B),"")) -> Project_013 | X22: =IF(V22="","",IFERROR(_xlfn.XLOOKUP(V22,Mapping!$A:$A,Mapping!$B:$B),"")) -> Project_009 | Y22: External | Z22: DE
A23: 22 | B23: Trần Hoài Bảo | C23: user022 | D23: OFF | E23: 44568 | F23: Senior Software Engineer | G23: 640 | H23: Cloud Architect using Microsoft Azure;EnglishScore;AWS Cloud Architect;Microsoft Certified: Azure Solutions Architect Expert;Microsoft Certified: Azure Administrator Associate;Professional Scrum Product Owner I;Cloud Developer;Cloud Developer using Microsoft Azure;NVIDIA Getting Started with AI on Jetson Nano;Oracle Cloud Data Management 2023 Certified Foundations Associate;Oracle Cloud Infrastructure 2023 Certified Foundations Associate;PROFESSIONAL SCRUM MASTER™ I;Microsoft Certified: Azure Developer Associate;Microsoft Certified: Azure Fundamentals;Microsoft Certified: Azure Data Fundamentals | I23: FHM CMS | J23: HCM | K23: FHM | L23: FHM CMS | M23: Azure Cloud | O23: Azure Cloud | P23: Middle | Q23: DEVE03 | R23: FR | S23: =VLOOKUP(R23,Customer_Mapping!A:B,2,FALSE) -> Customer_001 | T23: FSO.HCM.FHM.CMS | U23: STL_AG_02 | V23: FRWMS2026 | W23: =IF(U23="","",IFERROR(_xlfn.XLOOKUP(U23,Mapping!$A:$A,Mapping!$B:$B),"")) -> Project_009 | X23: =IF(V23="","",IFERROR(_xlfn.XLOOKUP(V23,Mapping!$A:$A,Mapping!$B:$B),"")) -> Project_013 | Y23: External | Z23: Azure Cloud
A24: 23 | B24: Trần Lê Chi Bảo | C24: user023 | D24: OFF | E24: 46113 | F24: Associate Business Analyst | H24: Japanese Language Proficiency Test N2 | I24: FHM CMS | J24: HCM | K24: FHM | L24: FHM CMS | M24: BA | N24: Junior | O24: Project Management | P24: Junior | Q24: BANE01 | R24: ANA | S24: =VLOOKUP(R24,Customer_Mapping!A:B,2,FALSE) -> Customer_007 | T24: FSO.HCM.FHM.CMS | U24: SBR_Buhin26 | V24: STL_AG_02 | W24: =IF(U24="","",IFERROR(_xlfn.XLOOKUP(U24,Mapping!$A:$A,Mapping!$B:$B),"")) -> Project_005 | X24: =IF(V24="","",IFERROR(_xlfn.XLOOKUP(V24,Mapping!$A:$A,Mapping!$B:$B),"")) -> Project_009 | Y24: External | Z24: BA
A25: 24 | B25: Văn Quốc Bảo | C25: user024 | D25: OFF | E25: 44621 | F25: Senior Software Engineer | G25: 880 | H25: EnglishScore;Generative AI Practitioner Certificate;Professional Scrum Developer I;Oracle Cloud Infrastructure for Sunbird Ed Specialty;Core Designer Certificate;Advanced Designer Certificate;NVIDIA Getting Started with AI on Jetson Nano;PROFESSIONAL SCRUM MASTER™ I | I25: FHM CMS | J25: HCM | K25: FHM | L25: FHM CMS | M25: DevOps & CI/CD Engineering | O25: DevOps & CI/CD Engineering | P25: Middle | Q25: DEVE03 | R25: SBR | S25: =VLOOKUP(R25,Customer_Mapping!A:B,2,FALSE) -> Customer_004 | T25: FSO.HCM.FHM.CMS | U25: C99.I5.WM.AA 2026 | V25: SBR_Buhin26 | W25: =IF(U25="","",IFERROR(_xlfn.XLOOKUP(U25,Mapping!$A:$A,Mapping!$B:$B),"")) -> Project_016 | X25: =IF(V25="","",IFERROR(_xlfn.XLOOKUP(V25,Mapping!$A:$A,Mapping!$B:$B),"")) -> Project_005 | Y25: External | Z25: DevOps & CI/CD Engineering
A26: 25 | B26: Lê Thái Bình | C26: user025 | D26: OFF | E26: 46014 | F26: Senior Software Engineer | H26: Microsoft Certified: Azure AI Apps and Agents Developer Associate;Microsoft Certified: Agentic AI Business Solutions Architect;Vietnamese Standardized Test of English Proficiency (VSTEP) - Level 4/CEFR B2;GitHub Copilot | I26: FHM CMS | J26: HCM | K26: FHM | L26: FHM CMS | M26: Java Framework | N26: Middle | O26: Java Framework | P26: Senior | Q26: DEVE03 | R26: COX-AM | S26: =VLOOKUP(R26,Customer_Mapping!A:B,2,FALSE) -> Customer_009 | T26: FSO.HCM.FHM.AKAT | U26: FMCS3 | V26: C99.I5.WM.AA 2026 | W26: =IF(U26="","",IFERROR(_xlfn.XLOOKUP(U26,Mapping!$A:$A,Mapping!$B:$B),"")) -> Project_017 | X26: =IF(V26="","",IFERROR(_xlfn.XLOOKUP(V26,Mapping!$A:$A,Mapping!$B:$B),"")) -> Project_016 | Y26: External | Z26: Java Framework
A27: 26 | B27: Thạch Thanh Bình | C27: user026 | D27: OFF | E27: 43974 | F27: Senior Software Engineer | G27: 800 | H27: Advanced Designer Certificate;Core Designer Certificate;Agile with Atlassian Jira;Communication in the 21st Century Workplace;Project Management: The Basics for Success;Microsoft Certified: Azure Fundamentals;FSOFT Foreign Language Proficiency Test - TOEIC Test;EnglishScore | I27: FHM CMS | J27: HCM | K27: FHM | L27: FHM CMS | M27: Java Framework | N27: Middle | O27: Java Framework | P27: Senior | Q27: DEVE03 | R27: FR | S27: =VLOOKUP(R27,Customer_Mapping!A:B,2,FALSE) -> Customer_001 | T27: FSO.HCM.FHM.CMS | U27: MetalAlpha | V27: FMCS3 | W27: =IF(U27="","",IFERROR(_xlfn.XLOOKUP(U27,Mapping!$A:$A,Mapping!$B:$B),"")) -> Project_018 | X27: =IF(V27="","",IFERROR(_xlfn.XLOOKUP(V27,Mapping!$A:$A,Mapping!$B:$B),"")) -> Project_017 | Y27: External | Z27: Java Framework
A28: 27 | B28: Y In Byă | C28: user027 | D28: OFF | E28: 45123 | F28: Senior Software Engineer | G28: 665 | H28: EnglishScore;Advanced Designer Certificate | I28: FHM CMS | J28: HCM | K28: FHM | L28: FHM CMS | M28: Java Framework | N28: Middle | O28: Java Framework | P28: Junior | Q28: DEVE03 | R28: MOC | S28: =VLOOKUP(R28,Customer_Mapping!A:B,2,FALSE) -> Customer_012 | T28: FSO.HCM.FHM.CMS | U28: J_POLARIS | V28: MetalAlpha | W28: =IF(U28="","",IFERROR(_xlfn.XLOOKUP(U28,Mapping!$A:$A,Mapping!$B:$B),"")) -> Project_019 | X28: =IF(V28="","",IFERROR(_xlfn.XLOOKUP(V28,Mapping!$A:$A,Mapping!$B:$B),"")) -> Project_018 | Y28: External | Z28: Java Framework
A29: 28 | B29: Đỗ Minh Chánh | C29: user028 | D29: OFF | E29: 45496 | F29: Associate Solution Architect | H29: Claude Certified Architect - Foundations;Japanese Language Proficiency Test N2;TOEIC Listening & Reading;AWS Certified Developer - Associate;AWS Certified Solutions Architect - Associate;Salesforce Certified Associate | I29: FHM JFL | J29: HCM | K29: FHM | L29: FHM JFL | M29: AWS Cloud | O29: AWS Cloud | P29: Middle | Q29: SARE01 | R29: JIT | S29: =VLOOKUP(R29,Customer_Mapping!A:B,2,FALSE) -> Customer_013 | T29: FSO.HCM.FHM.JPG | U29: OPNEXT88 | V29: J_POLARIS | W29: =IF(U29="","",IFERROR(_xlfn.XLOOKUP(U29,Mapping!$A:$A,Mapping!$B:$B),"")) -> Project_020 | X29: =IF(V29="","",IFERROR(_xlfn.XLOOKUP(V29,Mapping!$A:$A,Mapping!$B:$B),"")) -> Project_019 | Y29: External | Z29: AWS Cloud
A30: 29 | B30: Nguyễn Ngọc Bảo Chân | C30: user029 | D30: OFF | E30: 44005 | F30: Senior Software Tester | G30: 865 | H30: Data Analysis and Visualization with Microsoft Power BI;EnglishScore;FSOFT Foreign Language Proficiency Test - TOEIC Test;Business Intelligence Analytics;Tiếng Trung;A Life of Happiness and Fulfillment;AI for Everyone | I30: FHM CMS | J30: HCM | K30: FHM | L30: FHM CMS | M30: Manual Test | N30: Senior | O30: Manual Test | P30: Middle | Q30: TEST04 | R30: OddsPark | S30: =VLOOKUP(R30,Customer_Mapping!A:B,2,FALSE) -> Customer_014 | T30: FSO.HCM.FHM.JPG | U30: FR.SF.2025 | V30: OPNEXT88 | W30: =IF(U30="","",IFERROR(_xlfn.XLOOKUP(U30,Mapping!$A:$A,Mapping!$B:$B),"")) -> Project_021 | X30: =IF(V30="","",IFERROR(_xlfn.XLOOKUP(V30,Mapping!$A:$A,Mapping!$B:$B),"")) -> Project_020 | Y30: External | Z30: Manual Test
A31: 30 | B31: Lê Thị Xuân Chi | C31: user030 | D31: OFF | E31: 45246 | F31: Senior Software Tester | G31: 640 | H31: Oracle Cloud Infrastructure for Sunbird Ed Specialty;Advanced Designer Certificate;EnglishScore | I31: FHM CMS | J31: HCM | K31: FHM | L31: FHM CMS | M31: Manual Test | N31: Senior | O31: Low-Code & No-Code Development | P31: Middle | Q31: TEST04 | R31: FR | S31: =VLOOKUP(R31,Customer_Mapping!A:B,2,FALSE) -> Customer_001 | T31: FSO.HCM.FHM.CMS | U31: FR VDMC Operation 2026 | V31: FR.SF.2025 | W31: =IF(U31="","",IFERROR(_xlfn.XLOOKUP(U31,Mapping!$A:$A,Mapping!$B:$B),"")) -> Project_022 | X31: =IF(V31="","",IFERROR(_xlfn.XLOOKUP(V31,Mapping!$A:$A,Mapping!$B:$B),"")) -> Project_021 | Y31: External | Z31: Manual Test
A32: 31 | B32: Đặng Ngọc Chính | C32: user031 | D32: OFF | E32: 44485 | F32: Project Manager | G32: 755 | H32: PMI Agile Certified Practitioner (PMI-ACP)®;Project Management Professional (PMP);Phần cứng máy tính;Excel Skills for Business: Essentials;Developer Certificate;MLOps Practitioner Certificate;Core Designer Certificate;ML Practitioner Certificate;Advanced Designer Certificate;Google Project Management;Project Initiation: Starting a Successful Project;Project Planning: Putting It All Together;Foundations of Project Management;Project Execution: Running the Project;EnglishScore;FSOFT Foreign Language Proficiency Test - TOEIC Test | I32: FHM CMS | J32: HCM | K32: FHM | L32: FHM CMS | M32: Project Management | O32: IT Service | P32: Senior | Q32: SPMA02 | R32: FR | S32: =VLOOKUP(R32,Customer_Mapping!A:B,2,FALSE) -> Customer_001 | T32: FSO.HCM.FHM.CMS | U32: SF_Link_2026 | V32: FR VDMC Operation 2026 | W32: =IF(U32="","",IFERROR(_xlfn.XLOOKUP(U32,Mapping!$A:$A,Mapping!$B:$B),"")) -> Project_008 | X32: =IF(V32="","",IFERROR(_xlfn.XLOOKUP(V32,Mapping!$A:$A,Mapping!$B:$B),"")) -> Project_022 | Y32: External | Z32: Project Management
A33: 32 | B33: Nguyễn Nhân Chính | C33: user032 | D33: OFF | E33: 45992 | F33: Associate Software Engineer | H33: GitHub Copilot | I33: FHM CMS | J33: HCM | K33: FHM | L33: FHM CMS | M33: .NET Framework | N33: Junior | O33: Java Framework | P33: Junior | Q33: DEVE01 | R33: SBR | S33: =VLOOKUP(R33,Customer_Mapping!A:B,2,FALSE) -> Customer_004 | T33: FSO.HCM.FHM.CMS | U33: SBR_Buhin26 | V33: SF_Link_2026 | W33: =IF(U33="","",IFERROR(_xlfn.XLOOKUP(U33,Mapping!$A:$A,Mapping!$B:$B),"")) -> Project_005 | X33: =IF(V33="","",IFERROR(_xlfn.XLOOKUP(V33,Mapping!$A:$A,Mapping!$B:$B),"")) -> Project_008 | Y33: External | Z33: .NET Framework
A34: 33 | B34: Lê Thị Chung | C34: user033 | D34: OFF | E34: 44697 | F34: Senior Software Tester | G34: 575 | H34: EnglishScore;ISTQB Certified Tester Advanced Level - Test Analyst;Oracle Cloud Infrastructure for Sunbird Ed Specialty;Advanced Designer Certificate;Core Designer Certificate;Certified Tester ISTQB Foundation Level | I34: FHM CMS | J34: HCM | K34: FHM | L34: FHM CMS | M34: Manual Test | N34: Junior | O34: Manual Test | P34: Middle | Q34: TEST03 | R34: SBR | S34: =VLOOKUP(R34,Customer_Mapping!A:B,2,FALSE) -> Customer_004 | T34: FSO.HCM.FHM.CMS | U34: FRWMS2026 | V34: SBR_Buhin26 | W34: =IF(U34="","",IFERROR(_xlfn.XLOOKUP(U34,Mapping!$A:$A,Mapping!$B:$B),"")) -> Project_013 | X34: =IF(V34="","",IFERROR(_xlfn.XLOOKUP(V34,Mapping!$A:$A,Mapping!$B:$B),"")) -> Project_005 | Y34: External | Z34: Manual Test
A35: 34 | B35: Đặng Hồ Tuấn Cường | C35: user034 | D35: OFF | E35: 46180 | F35: Associate Software Engineer | I35: FHM CMS | J35: HCM | K35: FHM | L35: FHM CMS | O35: Java Framework | P35: Junior | Q35: DEVE01 | R35: FR | S35: =VLOOKUP(R35,Customer_Mapping!A:B,2,FALSE) -> Customer_001 | T35: FSO.HCM.FHM.CMS | U35: NEWKONG2 | V35: FRWMS2026 | W35: =IF(U35="","",IFERROR(_xlfn.XLOOKUP(U35,Mapping!$A:$A,Mapping!$B:$B),"")) -> Project_014 | X35: =IF(V35="","",IFERROR(_xlfn.XLOOKUP(V35,Mapping!$A:$A,Mapping!$B:$B),"")) -> Project_013 | Y35: External
A36: 35 | B36: Dương Mạnh Cường | C36: user035 | D36: OFF | E36: 41928 | F36: Software Development Head | G36: 960 | H36: Japanese Language Proficiency Test N2;EnglishScore;FSOFT Foreign Language Proficiency Test - TOEIC Test;Project Management Professional (PMP);AWS Certified Solutions Architect - Associate;Microsoft Certified Solutions Associate: Web Applications;Microsoft Specialist: Programming in HTML5 with JavaScript and CSS3;Predix Certified Developer;Self Awareness and the Effective Leader;Leadership Communication for Maximum Impact: Storytelling;Advanced Designer Certificate;Microsoft Certified Professional;Microsoft Certified Solutions Developer: Web Applications;PROFESSIONAL SCRUM MASTER™ I;Microsoft Certified: Azure Architect Technologies;Microsoft Certified: Azure Solutions Architect Expert | I36: FHM CMS | J36: HCM | K36: FHM | L36: FHM CMS | M36: Software Solution Architecture | O36: Software Solution Architecture | P36: Senior | Q36: SGMT01 | R36: FXSS | S36: =VLOOKUP(R36,Customer_Mapping!A:B,2,FALSE) -> Customer_010 | T36: FSO.HCM.FHM.CMS | U36: C99.I5.WM.AA 2026 | V36: NEWKONG2 | W36: =IF(U36="","",IFERROR(_xlfn.XLOOKUP(U36,Mapping!$A:$A,Mapping!$B:$B),"")) -> Project_016 | X36: =IF(V36="","",IFERROR(_xlfn.XLOOKUP(V36,Mapping!$A:$A,Mapping!$B:$B),"")) -> Project_014 | Y36: External | Z36: Software Solution Architecture
A37: 36 | B37: Nguyễn Kiên Cường | C37: user036 | D37: OFF | E37: 45338 | F37: Software Engineer | G37: 865 | H37: Advanced Designer Certificate;Core Designer Certificate;NVIDIA Getting Started with AI on Jetson Nano;MLOps Practitioner Certificate;TOEIC Listening & Reading;Developer Certificate;ML Practitioner Certificate;EnglishScore;AWS Certified Solutions Architect - Associate;GitHub Copilot | I37: FHM CMS | J37: HCM | K37: FHM | L37: FHM CMS | M37: NodeJs Server Implementation | N37: Junior | O37: Java Framework | P37: Middle | Q37: DEVE02 | R37: COX-AM | S37: =VLOOKUP(R37,Customer_Mapping!A:B,2,FALSE) -> Customer_009 | T37: FSO.HCM.FHM.AKAT | U37: C99.I5.SANS 2026 | V37: C99.I5.WM.AA 2026 | W37: =IF(U37="","",IFERROR(_xlfn.XLOOKUP(U37,Mapping!$A:$A,Mapping!$B:$B),"")) -> Project_023 | X37: =IF(V37="","",IFERROR(_xlfn.XLOOKUP(V37,Mapping!$A:$A,Mapping!$B:$B),"")) -> Project_016 | Y37: External | Z37: NodeJs Server Implementation
A38: 37 | B38: Nguyễn Công Đắc | C38: user037 | D38: OFF | E38: 44348 | F38: Senior Software Engineer | G38: 755 | H38: GitHub Copilot;EnglishScore;Cloud Developer;AWS Cloud Architect;PROFESSIONAL SCRUM MASTER™ I | I38: FHM CMS | J38: HCM | K38: FHM | L38: FHM CMS | M38: CAD Engineering | O38: IT Service | P38: Expert | Q38: DEVE04 | R38: COX-AM | S38: =VLOOKUP(R38,Customer_Mapping!A:B,2,FALSE) -> Customer_009 | T38: FSO.HCM.FHM.AKAT | U38: FMCS3 | V38: C99.I5.SANS 2026 | W38: =IF(U38="","",IFERROR(_xlfn.XLOOKUP(U38,Mapping!$A:$A,Mapping!$B:$B),"")) -> Project_017 | X38: =IF(V38="","",IFERROR(_xlfn.XLOOKUP(V38,Mapping!$A:$A,Mapping!$B:$B),"")) -> Project_023 | Y38: External | Z38: CAD Engineering
A39: 38 | B39: Mai Thanh Đại | C39: user038 | D39: OFF | E39: 45192 | F39: Solution Architect | G39: 785 | H39: Google Cloud Certified Generative AI Leader;EnglishScore;AWS Certified Solutions Architect - Associate | I39: FHM CMS | J39: HCM | K39: FHM | L39: FHM CMS | M39: Java Framework | N39: Senior | O39: AWS Cloud | P39: Senior | Q39: SARE02 | R39: FR | S39: =VLOOKUP(R39,Customer_Mapping!A:B,2,FALSE) -> Customer_001 | T39: FSO.HCM.FHM.CMS | U39: FRDLO | V39: FMCS3 | W39: =IF(U39="","",IFERROR(_xlfn.XLOOKUP(U39,Mapping!$A:$A,Mapping!$B:$B),"")) -> Project_001 | X39: =IF(V39="","",IFERROR(_xlfn.XLOOKUP(V39,Mapping!$A:$A,Mapping!$B:$B),"")) -> Project_017 | Y39: Hien | Z39: Java Framework
A40: 39 | B40: Ngô Minh Đại | C40: user039 | D40: OFF | E40: 46135 | F40: Senior Auto Test Engineer | I40: FHM CMS | J40: HCM | K40: FHM | L40: FHM CMS | O40: Manual Test | P40: Senior | Q40: ATES04 | R40: FR | S40: =VLOOKUP(R40,Customer_Mapping!A:B,2,FALSE) -> Customer_001 | T40: FSO.HCM.FHM.CMS | U40: SBR_Buhin26 | V40: FRDLO | W40: =IF(U40="","",IFERROR(_xlfn.XLOOKUP(U40,Mapping!$A:$A,Mapping!$B:$B),"")) -> Project_005 | X40: =IF(V40="","",IFERROR(_xlfn.XLOOKUP(V40,Mapping!$A:$A,Mapping!$B:$B),"")) -> Project_001 | Y40: External
A41: 40 | B41: Phan Văn Đại | C41: user040 | D41: OFF | E41: 46180 | F41: Associate Software Engineer | I41: FHM CMS | J41: HCM | K41: FHM | L41: FHM CMS | O41: Java Framework | P41: Junior | Q41: DEVE01 | R41: SBR | S41: =VLOOKUP(R41,Customer_Mapping!A:B,2,FALSE) -> Customer_004 | T41: FSO.HCM.FHM.CMS | U41: SBR_Buhin26 | V41: SBR_Buhin26 | W41: =IF(U41="","",IFERROR(_xlfn.XLOOKUP(U41,Mapping!$A:$A,Mapping!$B:$B),"")) -> Project_005 | X41: =IF(V41="","",IFERROR(_xlfn.XLOOKUP(V41,Mapping!$A:$A,Mapping!$B:$B),"")) -> Project_005 | Y41: External
A42: 41 | B42: Lý Công Đăng | C42: user041 | D42: OFF | E42: 46189 | F42: Associate Software Engineer | I42: FHM CMS | J42: HCM | K42: FHM | L42: FHM CMS | O42: Java Framework | P42: Junior | Q42: DEVE01 | R42: SBR | S42: =VLOOKUP(R42,Customer_Mapping!A:B,2,FALSE) -> Customer_004 | T42: FSO.HCM.FHM.CMS | U42: SBR_Buhin26 | V42: SBR_Buhin26 | W42: =IF(U42="","",IFERROR(_xlfn.XLOOKUP(U42,Mapping!$A:$A,Mapping!$B:$B),"")) -> Project_005 | X42: =IF(V42="","",IFERROR(_xlfn.XLOOKUP(V42,Mapping!$A:$A,Mapping!$B:$B),"")) -> Project_005 | Y42: External
A43: 42 | B43: Nguyễn Hoàng Hải Đăng | C43: user042 | D43: OFF | E43: 43617 | F43: Principal Software Engineer | G43: 710 | H43: EnglishScore;FSOFT Foreign Language Proficiency Test - TOEIC Test;Advanced Designer Certificate;Core Designer Certificate;Google Cloud Certified - Associate Cloud Engineer;AWS Certified Solutions Architect - Associate;Google Cloud Certified Generative AI Leader;Microsoft Certified: Azure Fundamentals;Oracle Certified Associate, Java SE 8 Programmer;Microsoft Certified: Azure Data Fundamentals | I43: FHM CMS | J43: HCM | K43: FHM | L43: FHM CMS | M43: Java Framework | N43: Senior | O43: Artificial Intelligence (AI) | P43: Senior | Q43: DEVE05 | R43: SBR | S43: =VLOOKUP(R43,Customer_Mapping!A:B,2,FALSE) -> Customer_004 | T43: FSO.HCM.FHM.CMS | U43: C99.I5.VS 2026 | V43: SBR_Buhin26 | W43: =IF(U43="","",IFERROR(_xlfn.XLOOKUP(U43,Mapping!$A:$A,Mapping!$B:$B),"")) -> Project_024 | X43: =IF(V43="","",IFERROR(_xlfn.XLOOKUP(V43,Mapping!$A:$A,Mapping!$B:$B),"")) -> Project_005 | Y43: External | Z43: Java Framework
A44: 43 | B44: Phan Hải Đăng | C44: user043 | D44: OFF | E44: 42354 | F44: Senior Software Engineer | G44: 665 | H44: FSOFT Foreign Language Proficiency Test - TOEIC Test;Certified HIPAA Privacy Associate (CHPA);SQL;EnglishScore;Predix Certified Developer;GitHub Copilot;PROFESSIONAL SCRUM MASTER™ I;Enrich skills to succeed - .NET Technology;Enrich skills to succeed - Ruby Platform;Google Analytics Certification;SI Associate Certification Program;SQL (Intermediate);SQL (Basic);SQL (Advanced);Mendix Rapid Developer;Oracle Cloud Data Management 2023 Certified Foundations Associate;Oracle Cloud Infrastructure 2023 Certified Foundations Associate;NVIDIA Getting Started with AI on Jetson Nano;Core Designer Certificate;Advanced Designer Certificate;AWS Certified Cloud Practitioner | I44: FHM CMS | J44: HCM | K44: FHM | L44: FHM CMS | M44: C/C++ | N44: Senior | O44: Python Platform | P44: Senior | Q44: DEVE04 | R44: COX-AM | S44: =VLOOKUP(R44,Customer_Mapping!A:B,2,FALSE) -> Customer_009 | T44: FSO.HCM.FHM.AKAT | U44: FVD2025 | V44: C99.I5.VS 2026 | W44: =IF(U44="","",IFERROR(_xlfn.XLOOKUP(U44,Mapping!$A:$A,Mapping!$B:$B),"")) -> Project_004 | X44: =IF(V44="","",IFERROR(_xlfn.XLOOKUP(V44,Mapping!$A:$A,Mapping!$B:$B),"")) -> Project_024 | Y44: External | Z44: C/C++
A45: 44 | B45: Nguyễn Đức Danh | C45: user044 | D45: OFF | E45: 45931 | F45: Senior Software Tester | I45: FHM CMS | J45: HCM | K45: FHM | L45: FHM CMS | O45: Manual Test | P45: Middle | Q45: TEST03 | R45: FR | S45: =VLOOKUP(R45,Customer_Mapping!A:B,2,FALSE) -> Customer_001 | T45: FSO.HCM.FHM.CMS | U45: C99.I5.LOG 2026 | V45: FVD2025 | W45: =IF(U45="","",IFERROR(_xlfn.XLOOKUP(U45,Mapping!$A:$A,Mapping!$B:$B),"")) -> Project_012 | X45: =IF(V45="","",IFERROR(_xlfn.XLOOKUP(V45,Mapping!$A:$A,Mapping!$B:$B),"")) -> Project_004 | Y45: External
A46: 45 | B46: Chou Tùng Đạt | C46: user045 | D46: OFF | E46: 43102 | F46: Senior Software Engineer | G46: 955 | H46: Developing ASP.NET MVC Web Applications;C# Fundamentals;Microsoft Certified: Azure DevOps Engineer Expert;FSOFT Foreign Language Proficiency Test - TOEIC Test;TOEIC (Internal);EnglishScore;Cloud DevOps Engineer;Microsoft Certified: Azure Architect Technologies;Microsoft Specialist: Programming in C#;Associate Traditional Web Developer O11;Microsoft Certified: Azure Developer Associate;GitHub Copilot | I46: FHM CMS | J46: HCM | K46: FHM | L46: FHM CMS | M46: Azure Cloud | O46: Azure Cloud | P46: Senior | Q46: DEVE04 | R46: COX-AM | S46: =VLOOKUP(R46,Customer_Mapping!A:B,2,FALSE) -> Customer_009 | T46: FSO.HCM.FHM.AKAT | U46: FHM.One | V46: C99.I5.LOG 2026 | W46: =IF(U46="","",IFERROR(_xlfn.XLOOKUP(U46,Mapping!$A:$A,Mapping!$B:$B),"")) -> Project_025 | X46: =IF(V46="","",IFERROR(_xlfn.XLOOKUP(V46,Mapping!$A:$A,Mapping!$B:$B),"")) -> Project_012 | Y46: External | Z46: Azure Cloud
A47: 46 | B47: Hoàng Cao Đạt | C47: user046 | D47: OFF | E47: 45977 | F47: Senior Business Analyst | H47: TOEIC Listening & Reading;Japanese Language Proficiency Test N1 | I47: FHM JFL | J47: HCM | K47: FHM | L47: FHM JFL | O47: Project Management | P47: Middle | Q47: BANE03 | R47: FSU-FHM | S47: =VLOOKUP(R47,Customer_Mapping!A:B,2,FALSE) -> #N/A | T47: FSO.HCM.FHM.META | U47: FRWMS2026 | V47: FHM.One | W47: =IF(U47="","",IFERROR(_xlfn.XLOOKUP(U47,Mapping!$A:$A,Mapping!$B:$B),"")) -> Project_013 | X47: =IF(V47="","",IFERROR(_xlfn.XLOOKUP(V47,Mapping!$A:$A,Mapping!$B:$B),"")) -> Project_025 | Y47: Internal
A48: 47 | B48: Lương Hồ Đắc Đạt | C48: user047 | D48: OFF | E48: 45130 | F48: Software Engineer | G48: 710 | H48: Advanced Designer Certificate;Core Designer Certificate;NVIDIA Getting Started with AI on Jetson Nano;GitHub Copilot;Oracle Cloud Infrastructure 2025 Certified Foundations Associate;Oracle Data Platform 2025 Certified Foundations Associate;AWS Certified Solutions Architect - Associate;Google Cloud Certified Generative AI Leader;Enrich skills to succeed - Low-Code;ML Practitioner Certificate;Developer Certificate;MLOps Practitioner Certificate;EnglishScore | I48: FHM CMS | J48: HCM | K48: FHM | L48: FHM CMS | M48: Fullstack QE/QC | O48: Java Framework | P48: Middle | Q48: DEVE02 | R48: FR | S48: =VLOOKUP(R48,Customer_Mapping!A:B,2,FALSE) -> Customer_001 | T48: FSO.HCM.FHM.CMS | U48: FRWMS2026 | V48: FRWMS2026 | W48: =IF(U48="","",IFERROR(_xlfn.XLOOKUP(U48,Mapping!$A:$A,Mapping!$B:$B),"")) -> Project_013 | X48: =IF(V48="","",IFERROR(_xlfn.XLOOKUP(V48,Mapping!$A:$A,Mapping!$B:$B),"")) -> Project_013 | Y48: External | Z48: Fullstack QE/QC
A49: 48 | B49: Nguyễn Duy Đạt | C49: user048 | D49: OFF | E49: 43822 | F49: Senior Software Engineer | G49: 710 | H49: FSOFT Foreign Language Proficiency Test - TOEIC Test;SQL;EnglishScore;Design for Performance and Scalability;Introduction to SQL;GitHub Copilot;AWS Cloud Architect;Cloud Developer;Design for Availability, Reliability, and Resiliency;Design for Security;Java Web Developer;Cloud DevOps Engineer;Java Programming;Advanced Designer Certificate;Core Designer Certificate;Oracle Cloud Infrastructure for Sunbird Ed Specialty;Digital Transformation for Business Leaders | I49: FHM CMS | J49: HCM | K49: FHM | L49: FHM CMS | M49: Java Framework | N49: Middle | O49: Java Framework | P49: Senior | Q49: DEVE03 | R49: FR | S49: =VLOOKUP(R49,Customer_Mapping!A:B,2,FALSE) -> Customer_001 | T49: FSO.HCM.FHM.CMS | U49: MetalAlpha | V49: FRWMS2026 | W49: =IF(U49="","",IFERROR(_xlfn.XLOOKUP(U49,Mapping!$A:$A,Mapping!$B:$B),"")) -> Project_018 | X49: =IF(V49="","",IFERROR(_xlfn.XLOOKUP(V49,Mapping!$A:$A,Mapping!$B:$B),"")) -> Project_013 | Y49: External | Z49: Java Framework
A50: 49 | B50: Nguyễn Lê Thành Đạt | C50: user049 | D50: OFF | E50: 46023 | F50: Associate Business Analyst | H50: GitHub Copilot | I50: FHM CMS | J50: HCM | K50: FHM | L50: FHM CMS | O50: BA | P50: Junior | Q50: BANE01 | R50: MOC | S50: =VLOOKUP(R50,Customer_Mapping!A:B,2,FALSE) -> Customer_012 | T50: FSO.HCM.FHM.CMS | U50: JOCAR_Replace | V50: MetalAlpha | W50: =IF(U50="","",IFERROR(_xlfn.XLOOKUP(U50,Mapping!$A:$A,Mapping!$B:$B),"")) -> Project_003 | X50: =IF(V50="","",IFERROR(_xlfn.XLOOKUP(V50,Mapping!$A:$A,Mapping!$B:$B),"")) -> Project_018 | Y50: External
A51: 50 | B51: Phạm Thành Đạt | C51: user050 | D51: OFF | E51: 45398 | F51: Senior Software Tester | G51: 710 | H51: EnglishScore;ISTQB Certified Tester Advanced Level - Test Analyst | I51: FHM CMS | J51: HCM | K51: FHM | L51: FHM CMS | O51: Manual Test | P51: Middle | Q51: TEST03 | R51: JJCM | S51: =VLOOKUP(R51,Customer_Mapping!A:B,2,FALSE) -> Customer_003 | T51: FSO.HCM.FHM.CMS | U51: OPNEXT88 | V51: JOCAR_Replace | W51: =IF(U51="","",IFERROR(_xlfn.XLOOKUP(U51,Mapping!$A:$A,Mapping!$B:$B),"")) -> Project_020 | X51: =IF(V51="","",IFERROR(_xlfn.XLOOKUP(V51,Mapping!$A:$A,Mapping!$B:$B),"")) -> Project_003 | Y51: External
A52: 51 | B52: Trần Bá Đạt | C52: user051 | D52: OFF | E52: 44136 | F52: Senior Software Tester | G52: 755 | H52: Oracle Cloud Infrastructure 2023 AI Certified Foundations Associate;Alteryx Foundation Micro Credential;Enrich skills to succeed - Automation Test;ISTQB Certified Tester Advanced Level - Test Analyst;Machine Learning Fundamentals;Enrich skills to succeed - Manual Test;Advanced Designer Certificate;Core Designer Certificate;ML Practitioner Certificate;MLOps Practitioner Certificate;Developer Certificate;SQL (Advanced);The Fundamentals of Digital Marketing;SQL (Basic);SQL (Intermediate);Oracle Cloud Data Management 2023 Certified Foundations Associate;Oracle Cloud Infrastructure 2023 Certified Foundations Associate;Google Analytics Certification;ISTQB Certified Tester - Foundation Level;EnglishScore | I52: FHM CMS | J52: HCM | K52: FHM | L52: FHM CMS | M52: Manual Test | N52: Senior | O52: Manual Test | P52: Middle | Q52: TEST03 | R52: OddsPark | S52: =VLOOKUP(R52,Customer_Mapping!A:B,2,FALSE) -> Customer_014 | T52: FSO.HCM.FHM.JPG | U52: FR.SF.2025 | V52: OPNEXT88 | W52: =IF(U52="","",IFERROR(_xlfn.XLOOKUP(U52,Mapping!$A:$A,Mapping!$B:$B),"")) -> Project_021 | X52: =IF(V52="","",IFERROR(_xlfn.XLOOKUP(V52,Mapping!$A:$A,Mapping!$B:$B),"")) -> Project_020 | Y52: External | Z52: Manual Test
A53: 52 | B53: Trần Quốc Đạt | C53: user052 | D53: OFF | E53: 41214 | F53: Senior Software Engineer | G53: 190 | H53: FSOFT Foreign Language Proficiency Test - TOEIC Test;EnglishScore;Salesforce Certified Platform Developer I;Developing Microsoft SharePoint Server 2013 Core Solutions;Softskill - Communication in the 21st Century Workplace;C#;CSS;HTML;Java;JavaScript;Leadership Communication for Maximum Impact: Storytelling;C++ | I53: FHM CMS | J53: HCM | K53: FHM | L53: FHM CMS | M53: Java Framework | N53: Middle | O53: Low-Code & No-Code Development | P53: Junior | Q53: DEVE03 | R53: FR | S53: =VLOOKUP(R53,Customer_Mapping!A:B,2,FALSE) -> Customer_001 | T53: FSO.HCM.FHM.CMS | U53: SAIN | V53: FR.SF.2025 | W53: =IF(U53="","",IFERROR(_xlfn.XLOOKUP(U53,Mapping!$A:$A,Mapping!$B:$B),"")) -> Project_026 | X53: =IF(V53="","",IFERROR(_xlfn.XLOOKUP(V53,Mapping!$A:$A,Mapping!$B:$B),"")) -> Project_021 | Y53: External | Z53: Java Framework
A54: 53 | B54: Nguyễn Thị Thúy Diễm | C54: user053 | D54: OFF | E54: 44188 | F54: Senior Software Engineer | G54: 620 | H54: AWS Fundamentals: Addressing Security Risk;AWS Cloud Technical Essentials;AWS Fundamentals: Migrating to the Cloud;NVIDIA Getting Started with AI on Jetson Nano;Advanced Designer Certificate;Core Designer Certificate;EnglishScore;Developer Certificate;MLOps Practitioner Certificate;ML Practitioner Certificate;Creative Problem Solving;Digital Transformation | I54: FHM CMS | J54: HCM | K54: FHM | L54: FHM CMS | M54: Java Framework | N54: Senior | O54: .NET Framework | P54: Middle | Q54: DEVE04 | R54: SBR | S54: =VLOOKUP(R54,Customer_Mapping!A:B,2,FALSE) -> Customer_004 | T54: FSO.HCM.FHM.CMS | U54: FRSPL26 | V54: SAIN | W54: =IF(U54="","",IFERROR(_xlfn.XLOOKUP(U54,Mapping!$A:$A,Mapping!$B:$B),"")) -> Project_027 | X54: =IF(V54="","",IFERROR(_xlfn.XLOOKUP(V54,Mapping!$A:$A,Mapping!$B:$B),"")) -> Project_026 | Y54: External | Z54: Java Framework
A55: 54 | B55: Trần Văn Định | C55: user054 | D55: OFF | E55: 45992 | F55: Senior Software Engineer | I55: FHM CMS | J55: HCM | K55: FHM | L55: FHM CMS | O55: Java Framework | P55: Senior | Q55: DEVE04 | R55: FR | S55: =VLOOKUP(R55,Customer_Mapping!A:B,2,FALSE) -> Customer_001 | T55: FSO.HCM.FHM.CMS | U55: FRWMS2026 | V55: FRSPL26 | W55: =IF(U55="","",IFERROR(_xlfn.XLOOKUP(U55,Mapping!$A:$A,Mapping!$B:$B),"")) -> Project_013 | X55: =IF(V55="","",IFERROR(_xlfn.XLOOKUP(V55,Mapping!$A:$A,Mapping!$B:$B),"")) -> Project_027 | Y55: External
A56: 55 | B56: Thái Văn Đồng | C56: user055 | D56: OFF | E56: 43070 | F56: Senior Software Engineer | G56: 665 | H56: Microsoft Certified: AI Transformation Leader;Cloud Developer;Data Analyst;GitHub Copilot;FSOFT Foreign Language Proficiency Test - TOEIC Test;EnglishScore | I56: FHM CMS | J56: HCM | K56: FHM | L56: FHM CMS | M56: Android Platform | N56: Senior | O56: Android Platform | P56: Senior | Q56: DEVE04 | R56: FR | S56: =VLOOKUP(R56,Customer_Mapping!A:B,2,FALSE) -> Customer_001 | T56: FSO.HCM.FHM.CMS | V56: FRWMS2026 | W56: =IF(U56="","",IFERROR(_xlfn.XLOOKUP(U56,Mapping!$A:$A,Mapping!$B:$B),"")) | X56: =IF(V56="","",IFERROR(_xlfn.XLOOKUP(V56,Mapping!$A:$A,Mapping!$B:$B),"")) -> Project_013 | Y56: External | Z56: Android Platform
A57: 56 | B57: Võ Sỹ Giang Đông | C57: user056 | D57: OFF | E57: 41686 | F57: Software Development Head | G57: 640 | H57: PROFESSIONAL SCRUM MASTER™ I;Project Management Professional (PMP);EnglishScore;AWS Certified Solutions Architect - Associate;FSOFT Foreign Language Proficiency Test - TOEIC Test;Cloud Computing for Business Leaders | I57: FHM CMS | J57: HCM | K57: FHM | L57: FHM CMS | M57: Project Management | Q57: SGMT01 | S57: =VLOOKUP(R57,Customer_Mapping!A:B,2,FALSE) -> #N/A | U57: OPNEXT88 | W57: =IF(U57="","",IFERROR(_xlfn.XLOOKUP(U57,Mapping!$A:$A,Mapping!$B:$B),"")) -> Project_020 | X57: =IF(V57="","",IFERROR(_xlfn.XLOOKUP(V57,Mapping!$A:$A,Mapping!$B:$B),"")) | Z57: Project Management
A58: 57 | B58: Trương Quý Đức | C58: user057 | D58: OFF | E58: 46158 | F58: Senior Software Engineer | I58: FHM CMS | J58: HCM | K58: FHM | L58: FHM CMS | O58: Java Framework | P58: Middle | Q58: DEVE03 | R58: OddsPark | S58: =VLOOKUP(R58,Customer_Mapping!A:B,2,FALSE) -> Customer_014 | T58: FSO.HCM.FHM.JPG | U58: Portal_EU01 | V58: OPNEXT88 | W58: =IF(U58="","",IFERROR(_xlfn.XLOOKUP(U58,Mapping!$A:$A,Mapping!$B:$B),"")) -> Project_002 | X58: =IF(V58="","",IFERROR(_xlfn.XLOOKUP(V58,Mapping!$A:$A,Mapping!$B:$B),"")) -> Project_020 | Y58: External
A59: 58 | B59: Mai Tiến Dũng | C59: user058 | D59: OFF | E59: 44384 | F59: Senior Software Engineer | G59: 710 | H59: EnglishScore;Cloud Developer | I59: FHM CMS | J59: HCM | K59: FHM | L59: FHM CMS | M59: NodeJs Server Implementation | N59: Middle | O59: Fullstack QE/QC | P59: Middle | Q59: DEVE03 | R59: Casio-Europe | S59: =VLOOKUP(R59,Customer_Mapping!A:B,2,FALSE) -> Customer_002 | T59: FSO.HCM.FHM.CMS | U59: CDX_MS | V59: Portal_EU01 | W59: =IF(U59="","",IFERROR(_xlfn.XLOOKUP(U59,Mapping!$A:$A,Mapping!$B:$B),"")) -> Project_007 | X59: =IF(V59="","",IFERROR(_xlfn.XLOOKUP(V59,Mapping!$A:$A,Mapping!$B:$B),"")) -> Project_002 | Y59: External | Z59: NodeJs Server Implementation
A60: 59 | B60: Phan Ngọc Dũng | C60: user059 | D60: OFF | E60: 43175 | F60: Senior Software Engineer | G60: 620 | H60: IT Basic for Comtors;Agile with Atlassian Jira;Advanced Designer Certificate;Core Designer Certificate;FSOFT Foreign Language Proficiency Test - TOEIC Test;EnglishScore;Generative AI Practitioner Certificate | I60: FHM CMS | J60: HCM | K60: FHM | L60: FHM CMS | M60: AWS Cloud | O60: AWS Cloud | P60: Senior | Q60: DEVE03 | R60: SonyGS | S60: =VLOOKUP(R60,Customer_Mapping!A:B,2,FALSE) -> Customer_006 | T60: FSO.HCM.FHM.CMS | U60: UBT.ODC | V60: CDX_MS | W60: =IF(U60="","",IFERROR(_xlfn.XLOOKUP(U60,Mapping!$A:$A,Mapping!$B:$B),"")) -> Project_028 | X60: =IF(V60="","",IFERROR(_xlfn.XLOOKUP(V60,Mapping!$A:$A,Mapping!$B:$B),"")) -> Project_007 | Y60: External | Z60: AWS Cloud
A61: 60 | B61: Đỗ Thanh Dương | C61: user060 | D61: OFF | E61: 42552 | F61: Senior Project Manager | G61: 950 | H61: EnglishScore;AWS Certified Solutions Architect - Associate;Microsoft Specialist: Programming in C#;Developing ASP.NET MVC Web Applications;Project Management Professional (PMP);PROFESSIONAL SCRUM MASTER™ I;PROFESSIONAL SCRUM MASTER™ II;Microsoft Certified: Azure Fundamentals;Microsoft Certified: Azure Developer Associate;Agile with Atlassian Jira;Managing Employee Performance;FSOFT Foreign Language Proficiency Test - TOEIC Test;PMI Agile Certified Practitioner (PMI-ACP)® | I61: FHM CMS | J61: HCM | K61: FHM | L61: FHM CMS | M61: Project Management | N61: Senior | O61: Project Management | P61: Senior | Q61: SPMA03 | R61: UBT | S61: =VLOOKUP(R61,Customer_Mapping!A:B,2,FALSE) -> Customer_015 | T61: FSO.HCM.FHM.ADG | U61: STL_AG_02 | V61: UBT.ODC | W61: =IF(U61="","",IFERROR(_xlfn.XLOOKUP(U61,Mapping!$A:$A,Mapping!$B:$B),"")) -> Project_009 | X61: =IF(V61="","",IFERROR(_xlfn.XLOOKUP(V61,Mapping!$A:$A,Mapping!$B:$B),"")) -> Project_028 | Y61: External | Z61: Project Management
A62: 61 | B62: Đặng Vũ Tùng Dương | C62: user061 | D62: OFF | E62: 44332 | F62: Senior Software Engineer | G62: 830 | H62: Cloud DevOps Engineer;EnglishScore;SQL (Basic);PROFESSIONAL SCRUM MASTER™ II;PMI Agile Certified Practitioner (PMI-ACP)®;PROFESSIONAL SCRUM MASTER™ I | I62: FHM CMS | J62: HCM | K62: FHM | L62: FHM CMS | M62: Scrum Master | O62: DE | P62: Middle | Q62: DEVE03 | R62: ANA | S62: =VLOOKUP(R62,Customer_Mapping!A:B,2,FALSE) -> Customer_007 | T62: FSO.HCM.FHM.CMS | U62: STL_AG_02 | V62: STL_AG_02 | W62: =IF(U62="","",IFERROR(_xlfn.XLOOKUP(U62,Mapping!$A:$A,Mapping!$B:$B),"")) -> Project_009 | X62: =IF(V62="","",IFERROR(_xlfn.XLOOKUP(V62,Mapping!$A:$A,Mapping!$B:$B),"")) -> Project_009 | Y62: External | Z62: Scrum Master
A63: 62 | B63: Nguyễn Đông Dương | C63: user062 | D63: OFF | E63: 44735 | F63: Senior Software Tester | G63: 735 | H63: ISTQB Foundation Level CTFL Training for 2021;ISTQB Certified Tester - Foundation Level;EnglishScore;Enrich skills to succeed - Manual Test;Japanese Language Proficiency Test N5 | I63: FHM CMS | J63: HCM | K63: FHM | L63: FHM CMS | M63: Manual Test | N63: Junior | O63: Manual Test | P63: Middle | Q63: TEST03 | R63: ANA | S63: =VLOOKUP(R63,Customer_Mapping!A:B,2,FALSE) -> Customer_007 | T63: FSO.HCM.FHM.CMS | U63: C99.I5.WM.AM 2026 | V63: STL_AG_02 | W63: =IF(U63="","",IFERROR(_xlfn.XLOOKUP(U63,Mapping!$A:$A,Mapping!$B:$B),"")) -> Project_029 | X63: =IF(V63="","",IFERROR(_xlfn.XLOOKUP(V63,Mapping!$A:$A,Mapping!$B:$B),"")) -> Project_009 | Y63: External | Z63: Manual Test
A64: 63 | B64: Nguyễn Thanh Dương | C64: user063 | D64: OFF | E64: 43906 | F64: Senior Software Engineer | G64: 735 | H64: EnglishScore;Oracle Certified Associate, Java SE 8 Programmer I;Cloud Developer;AWS Cloud Architect;Intermediate Python;FSOFT Foreign Language Proficiency Test - TOEIC Test;React Developer Certified Level 1;Advanced Designer Certificate;NVIDIA Getting Started with AI on Jetson Nano;PROFESSIONAL SCRUM MASTER™ I;Professional Scrum Product Owner I;AWS Certified Data Analytics - Specialty | I64: FHM CMS | J64: HCM | K64: FHM | L64: FHM CMS | M64: Java Framework | N64: Middle | O64: ReactJS Framework | P64: Senior | Q64: DEVE04 | R64: COX-AM | S64: =VLOOKUP(R64,Customer_Mapping!A:B,2,FALSE) -> Customer_009 | T64: FSO.HCM.FHM.AKAT | U64: STL_AG_02 | V64: C99.I5.WM.AM 2026 | W64: =IF(U64="","",IFERROR(_xlfn.XLOOKUP(U64,Mapping!$A:$A,Mapping!$B:$B),"")) -> Project_009 | X64: =IF(V64="","",IFERROR(_xlfn.XLOOKUP(V64,Mapping!$A:$A,Mapping!$B:$B),"")) -> Project_029 | Y64: External | Z64: Java Framework
A65: 64 | B65: Quan Huỳnh Quang Dương | C65: user064 | D65: OFF | E65: 45861 | F65: Pre-Associate Data Engineer | H65: IELTS 7.5 | I65: FHM CMS | J65: HCM | K65: FHM | L65: FHM CMS | O65: DE | P65: Middle | Q65: DSEN00 | R65: ANA | S65: =VLOOKUP(R65,Customer_Mapping!A:B,2,FALSE) -> Customer_007 | T65: FSO.HCM.FHM.CMS | U65: C99.CMS.AUD.AE 2026 | V65: STL_AG_02 | W65: =IF(U65="","",IFERROR(_xlfn.XLOOKUP(U65,Mapping!$A:$A,Mapping!$B:$B),"")) -> Project_030 | X65: =IF(V65="","",IFERROR(_xlfn.XLOOKUP(V65,Mapping!$A:$A,Mapping!$B:$B),"")) -> Project_009 | Y65: External
A66: 65 | B66: Lê Đình Duy | C66: user065 | D66: OFF | E66: 44278 | F66: Senior Software Engineer | G66: 880 | H66: EnglishScore;Core Designer Certificate;Advanced Designer Certificate;Oracle Cloud Infrastructure 2023 Certified Foundations Associate;A Life of Happiness and Fulfillment;Mendix Rapid Developer | I66: FHM CMS | J66: HCM | K66: FHM | L66: FHM CMS | M66: iOS Platform | N66: Senior | O66: Flutter UI Framework | P66: Senior | Q66: DEVE04 | R66: COX-AM | S66: =VLOOKUP(R66,Customer_Mapping!A:B,2,FALSE) -> Customer_009 | T66: FSO.HCM.FHM.AKAT | U66: FR.SF.2025 | V66: C99.CMS.AUD.AE 2026 | W66: =IF(U66="","",IFERROR(_xlfn.XLOOKUP(U66,Mapping!$A:$A,Mapping!$B:$B),"")) -> Project_021 | X66: =IF(V66="","",IFERROR(_xlfn.XLOOKUP(V66,Mapping!$A:$A,Mapping!$B:$B),"")) -> Project_030 | Y66: External | Z66: iOS Platform
A67: 66 | B67: Nguyễn Hoàng Duy | C67: user066 | D67: OFF | E67: 44363 | F67: Software Engineer | G67: 575 | H67: Japanese Language Proficiency Test N5;Cloud DevOps Engineer;EnglishScore | I67: FHM CMS | J67: HCM | K67: FHM | L67: FHM CMS | M67: PHP Platform | O67: Azure Cloud | P67: Middle | Q67: DEVE02 | R67: FR | S67: =VLOOKUP(R67,Customer_Mapping!A:B,2,FALSE) -> Customer_001 | T67: FSO.HCM.FHM.CMS | U67: JOCAR_Replace | V67: FR.SF.2025 | W67: =IF(U67="","",IFERROR(_xlfn.XLOOKUP(U67,Mapping!$A:$A,Mapping!$B:$B),"")) -> Project_003 | X67: =IF(V67="","",IFERROR(_xlfn.XLOOKUP(V67,Mapping!$A:$A,Mapping!$B:$B),"")) -> Project_021 | Y67: External | Z67: PHP Platform
A68: 67 | B68: Nguyễn Lê Duy | C68: user067 | D68: OFF | E68: 46014 | F68: Senior Software Engineer | I68: FHM CMS | J68: HCM | K68: FHM | L68: FHM CMS | O68: Java Framework | P68: Junior | Q68: DEVE04 | R68: JJCM | S68: =VLOOKUP(R68,Customer_Mapping!A:B,2,FALSE) -> Customer_003 | T68: FSO.HCM.FHM.CMS | U68: OPNEXT88 | V68: JOCAR_Replace | W68: =IF(U68="","",IFERROR(_xlfn.XLOOKUP(U68,Mapping!$A:$A,Mapping!$B:$B),"")) -> Project_020 | X68: =IF(V68="","",IFERROR(_xlfn.XLOOKUP(V68,Mapping!$A:$A,Mapping!$B:$B),"")) -> Project_003 | Y68: External
A69: 68 | B69: Phạm Văn Duy | C69: user068 | D69: OFF | E69: 46180 | F69: Associate Software Engineer | I69: FHM CMS | J69: HCM | K69: FHM | L69: FHM CMS | O69: Java Framework | P69: Middle | Q69: DEVE01 | R69: OddsPark | S69: =VLOOKUP(R69,Customer_Mapping!A:B,2,FALSE) -> Customer_014 | T69: FSO.HCM.FHM.JPG | U69: FRSPL26 | V69: OPNEXT88 | W69: =IF(U69="","",IFERROR(_xlfn.XLOOKUP(U69,Mapping!$A:$A,Mapping!$B:$B),"")) -> Project_027 | X69: =IF(V69="","",IFERROR(_xlfn.XLOOKUP(V69,Mapping!$A:$A,Mapping!$B:$B),"")) -> Project_020 | Y69: External
A70: 69 | B70: Trần Quốc Duy | C70: user069 | D70: OFF | E70: 41928 | F70: Solution Architect | G70: 815 | H70: Microsoft Certified: Azure Developer Associate;Microsoft Certified: Azure Administrator Associate;Oracle Certified Professional, Java SE 6 Programmer;Microsoft Certified: Azure Architect Technologies;Microsoft Certified: Azure DevOps Engineer Expert;Core Designer Certificate;Microsoft Certified: Azure AI Engineer Associate;AWS Certified Solutions Architect - Associate;EnglishScore;FSOFT Foreign Language Proficiency Test - TOEIC Test;TOEIC (Internal);Microsoft Certified: Azure Solutions Architect Expert | I70: FHM CMS | J70: HCM | K70: FHM | L70: FHM CMS | M70: .NET Framework | N70: Senior | O70: Java Framework | P70: Expert | Q70: SARE02 | R70: FR | S70: =VLOOKUP(R70,Customer_Mapping!A:B,2,FALSE) -> Customer_001 | T70: FSO.HCM.FHM.CMS | U70: C99.I5.WM.AM 2026 | V70: FRSPL26 | W70: =IF(U70="","",IFERROR(_xlfn.XLOOKUP(U70,Mapping!$A:$A,Mapping!$B:$B),"")) -> Project_029 | X70: =IF(V70="","",IFERROR(_xlfn.XLOOKUP(V70,Mapping!$A:$A,Mapping!$B:$B),"")) -> Project_027 | Y70: External | Z70: .NET Framework
A71: 70 | B71: Võ Phương Duy | C71: user070 | D71: OFF | E71: 43040 | F71: Senior Software Engineer | G71: 910 | H71: NVIDIA Getting Started with AI on Jetson Nano;Microsoft Certified: Azure Fundamentals;FSOFT Foreign Language Proficiency Test - TOEIC Test;GitHub Copilot;Associate Traditional Web Developer O11;EnglishScore;React | I71: FHM CMS | J71: HCM | K71: FHM | L71: FHM CMS | M71: Java Framework | N71: Middle | O71: ReactJS Framework | P71: Senior | Q71: DEVE03 | R71: COX-AM | S71: =VLOOKUP(R71,Customer_Mapping!A:B,2,FALSE) -> Customer_009 | T71: FSO.HCM.FHM.AKAT | U71: FMCS3 | V71: C99.I5.WM.AM 2026 | W71: =IF(U71="","",IFERROR(_xlfn.XLOOKUP(U71,Mapping!$A:$A,Mapping!$B:$B),"")) -> Project_017 | X71: =IF(V71="","",IFERROR(_xlfn.XLOOKUP(V71,Mapping!$A:$A,Mapping!$B:$B),"")) -> Project_029 | Y71: External | Z71: Java Framework
A72: 71 | B72: Võ Thanh Duy | C72: user071 | D72: OFF | E72: 45459 | F72: Senior Software Engineer | G72: 665 | H72: EnglishScore;GitHub Copilot | I72: FHM CMS | J72: HCM | K72: FHM | L72: FHM CMS | O72: Java Framework | P72: Middle | Q72: DEVE03 | R72: FR | S72: =VLOOKUP(R72,Customer_Mapping!A:B,2,FALSE) -> Customer_001 | T72: FSO.HCM.FHM.CMS | U72: FVD2025 | V72: FMCS3 | W72: =IF(U72="","",IFERROR(_xlfn.XLOOKUP(U72,Mapping!$A:$A,Mapping!$B:$B),"")) -> Project_004 | X72: =IF(V72="","",IFERROR(_xlfn.XLOOKUP(V72,Mapping!$A:$A,Mapping!$B:$B),"")) -> Project_017 | Y72: External
A73: 72 | B73: Nguyễn Ngọc Trường Giang | C73: user072 | D73: OFF | E73: 46014 | F73: Associate Software Engineer | H73: TOEIC Listening & Reading | I73: FHM CMS | J73: HCM | K73: FHM | L73: FHM CMS | O73: Java Framework | P73: Junior | Q73: DEVE01 | R73: FR | S73: =VLOOKUP(R73,Customer_Mapping!A:B,2,FALSE) -> Customer_001 | T73: FSO.HCM.FHM.CMS | U73: J_RSDB200 | V73: FVD2025 | W73: =IF(U73="","",IFERROR(_xlfn.XLOOKUP(U73,Mapping!$A:$A,Mapping!$B:$B),"")) -> Project_031 | X73: =IF(V73="","",IFERROR(_xlfn.XLOOKUP(V73,Mapping!$A:$A,Mapping!$B:$B),"")) -> Project_004 | Y73: External
A74: 73 | B74: Phạm Thanh Giang | C74: user073 | D74: OFF | E74: 45444 | F74: Principal BA Consultant | G74: 865 | H74: Japanese Language Proficiency Test N2;EnglishScore | I74: FHM JFL | J74: HCM | K74: FHM | L74: FHM JFL | O74: BA | P74: Senior | Q74: BANE05 | R74: JIT | S74: =VLOOKUP(R74,Customer_Mapping!A:B,2,FALSE) -> Customer_013 | T74: FSO.HCM.FHM.JPG | U74: SBR_Buhin26 | V74: J_RSDB200 | W74: =IF(U74="","",IFERROR(_xlfn.XLOOKUP(U74,Mapping!$A:$A,Mapping!$B:$B),"")) -> Project_005 | X74: =IF(V74="","",IFERROR(_xlfn.XLOOKUP(V74,Mapping!$A:$A,Mapping!$B:$B),"")) -> Project_031 | Y74: External
A75: 74 | B75: Lê Minh Hải | C75: user074 | D75: OFF | E75: 43366 | F75: Senior Software Engineer | G75: 665 | H75: Japanese Language Proficiency Test N3;EnglishScore;FSOFT Foreign Language Proficiency Test - TOEIC Test;PROFESSIONAL SCRUM MASTER™ I;Advanced Designer Certificate;Microsoft Certified: Azure Fundamentals;Microsoft Certified: Azure Data Fundamentals;Microsoft Certified: Azure Data Engineer Associate | I75: FHM CMS | J75: HCM | K75: FHM | L75: FHM CMS | M75: .NET Framework | N75: Middle | O75: Java Framework | P75: Senior | Q75: DEVE04 | R75: SBR | S75: =VLOOKUP(R75,Customer_Mapping!A:B,2,FALSE) -> Customer_004 | T75: FSO.HCM.FHM.CMS | U75: CL555.DE.PrintLab 2026 | V75: SBR_Buhin26 | W75: =IF(U75="","",IFERROR(_xlfn.XLOOKUP(U75,Mapping!$A:$A,Mapping!$B:$B),"")) -> Project_032 | X75: =IF(V75="","",IFERROR(_xlfn.XLOOKUP(V75,Mapping!$A:$A,Mapping!$B:$B),"")) -> Project_005 | Y75: External | Z75: .NET Framework
A76: 75 | B76: Nguyễn Hoàng Hải | C76: user075 | D76: OFF | E76: 45206 | F76: Senior Software Engineer | H76: React Developer Certified Level 1;Vue.js Developer Level I;React Developer Certified Level 2;Backend Development with Node.js;TOEIC Listening & Reading;React Developer Certified Level 3;AWS Certified Solutions Architect - Associate;React;Go Language (Golang) | I76: FHM CMS | J76: HCM | K76: FHM | L76: FHM CMS | M76: VueJS Framework | N76: Senior | O76: DevOps & CI/CD Engineering | P76: Junior | Q76: DEVE04 | R76: DiscovEdu | S76: =VLOOKUP(R76,Customer_Mapping!A:B,2,FALSE) -> Customer_016 | T76: FSO.HCM.FHM.AKAT | U76: FRSPL26 | V76: CL555.DE.PrintLab 2026 | W76: =IF(U76="","",IFERROR(_xlfn.XLOOKUP(U76,Mapping!$A:$A,Mapping!$B:$B),"")) -> Project_027 | X76: =IF(V76="","",IFERROR(_xlfn.XLOOKUP(V76,Mapping!$A:$A,Mapping!$B:$B),"")) -> Project_032 | Y76: External | Z76: VueJS Framework
A77: 76 | B77: Nguyễn Lê Thanh Hải | C77: user076 | D77: OFF | E77: 46149 | F77: Principal Software Engineer | I77: FHM CMS | J77: HCM | K77: FHM | L77: FHM CMS | O77: ReactJS Framework | P77: Senior | Q77: DEVE05 | R77: FR | S77: =VLOOKUP(R77,Customer_Mapping!A:B,2,FALSE) -> Customer_001 | T77: FSO.HCM.FHM.CMS | U77: OPNEXT88 | V77: FRSPL26 | W77: =IF(U77="","",IFERROR(_xlfn.XLOOKUP(U77,Mapping!$A:$A,Mapping!$B:$B),"")) -> Project_020 | X77: =IF(V77="","",IFERROR(_xlfn.XLOOKUP(V77,Mapping!$A:$A,Mapping!$B:$B),"")) -> Project_027 | Y77: External
A78: 77 | B78: Nguyễn Phương Hải | C78: user077 | D78: OFF | E78: 45084 | F78: Senior Software Engineer | G78: 830 | H78: Introduction to Data Analysis with Pandas and NumPy;EnglishScore;Design for Availability, Reliability, and Resiliency;Digital Transformation for Business Leaders;Data Analyst;Advanced Data Wrangling;AWS Cloud Architect;Design for Security;Cloud DevOps Engineer;AWS Cloud Fundamentals;Design for Performance and Scalability;Data Visualization with Matplotlib and Seaborn;Build CI/CD Pipelines, Monitoring, and Logging;Microservices at Scale using AWS and Kubernetes;Advanced Designer Certificate;Oracle Cloud Data Management 2023 Certified Foundations Associate;Oracle Cloud Infrastructure for Sunbird Ed Specialty;Oracle Cloud Infrastructure 2023 Certified Foundations Associate | I78: FHM CMS | J78: HCM | K78: FHM | L78: FHM CMS | M78: Java Framework | N78: Middle | O78: Java Framework | P78: Middle | Q78: DEVE03 | R78: OddsPark | S78: =VLOOKUP(R78,Customer_Mapping!A:B,2,FALSE) -> Customer_014 | T78: FSO.HCM.FHM.JPG | U78: FVD2025 | V78: OPNEXT88 | W78: =IF(U78="","",IFERROR(_xlfn.XLOOKUP(U78,Mapping!$A:$A,Mapping!$B:$B),"")) -> Project_004 | X78: =IF(V78="","",IFERROR(_xlfn.XLOOKUP(V78,Mapping!$A:$A,Mapping!$B:$B),"")) -> Project_020 | Y78: External | Z78: Java Framework
A79: 78 | B79: Nguyễn Thanh Hải | C79: user078 | D79: OFF | E79: 44440 | F79: Senior Software Tester | G79: 710 | H79: PROFESSIONAL SCRUM MASTER™ I;ISTQB Certified Tester Advanced Level - Test Analyst;Enrich skills to succeed - Quality Assurance;Oracle Cloud Infrastructure for Sunbird Ed Specialty;Advanced Designer Certificate;EnglishScore;ISTQB Certified Tester - Foundation Level;Japanese Language Proficiency Test N5 | I79: FHM CMS | J79: HCM | K79: FHM | L79: FHM CMS | M79: Manual Test | O79: Manual Test | P79: Middle | Q79: TEST03 | R79: FR | S79: =VLOOKUP(R79,Customer_Mapping!A:B,2,FALSE) -> Customer_001 | T79: FSO.HCM.FHM.CMS | U79: OPNEXT88 | V79: FVD2025 | W79: =IF(U79="","",IFERROR(_xlfn.XLOOKUP(U79,Mapping!$A:$A,Mapping!$B:$B),"")) -> Project_020 | X79: =IF(V79="","",IFERROR(_xlfn.XLOOKUP(V79,Mapping!$A:$A,Mapping!$B:$B),"")) -> Project_004 | Y79: External | Z79: Manual Test
A80: 79 | B80: Trần Ngọc Hải | C80: user079 | D80: OFF | E80: 46128 | F80: Senior Software Engineer | H80: Vietnamese Standardized Test of English Proficiency (VSTEP) - Level 3/CEFR B1 | I80: FHM CMS | J80: HCM | K80: FHM | L80: FHM CMS | O80: Java Framework | P80: Middle | Q80: DEVE03 | R80: OddsPark | S80: =VLOOKUP(R80,Customer_Mapping!A:B,2,FALSE) -> Customer_014 | T80: FSO.HCM.FHM.JPG | U80: JOCAR_Replace | V80: OPNEXT88 | W80: =IF(U80="","",IFERROR(_xlfn.XLOOKUP(U80,Mapping!$A:$A,Mapping!$B:$B),"")) -> Project_003 | X80: =IF(V80="","",IFERROR(_xlfn.XLOOKUP(V80,Mapping!$A:$A,Mapping!$B:$B),"")) -> Project_020 | Y80: External
A81: 80 | B81: Hoàng Thị Hằng | C81: user080 | D81: OFF | E81: 45923 | F81: Principal Test Analyst | I81: FHM CMS | J81: HCM | K81: FHM | L81: FHM CMS | O81: Manual Test | P81: Senior | Q81: TEST05 | R81: JJCM | S81: =VLOOKUP(R81,Customer_Mapping!A:B,2,FALSE) -> Customer_003 | T81: FSO.HCM.FHM.CMS | U81: STL_AG_02 | V81: JOCAR_Replace | W81: =IF(U81="","",IFERROR(_xlfn.XLOOKUP(U81,Mapping!$A:$A,Mapping!$B:$B),"")) -> Project_009 | X81: =IF(V81="","",IFERROR(_xlfn.XLOOKUP(V81,Mapping!$A:$A,Mapping!$B:$B),"")) -> Project_003 | Y81: External
A82: 81 | B82: Lê Thị Thúy Hằng | C82: user081 | D82: OFF | E82: 43897 | F82: Senior Software Tester | G82: 620 | H82: Excel Skills for Business: Intermediate II;Core Designer Certificate;Advanced Designer Certificate;FSOFT Foreign Language Proficiency Test - TOEIC Test;EnglishScore | I82: FHM CMS | J82: HCM | K82: FHM | L82: FHM CMS | M82: Manual Test | N82: Senior | O82: Manual Test | P82: Senior | Q82: TEST03 | R82: ANA | S82: =VLOOKUP(R82,Customer_Mapping!A:B,2,FALSE) -> Customer_007 | T82: FSO.HCM.FHM.CMS | U82: STL_AG_02 | V82: STL_AG_02 | W82: =IF(U82="","",IFERROR(_xlfn.XLOOKUP(U82,Mapping!$A:$A,Mapping!$B:$B),"")) -> Project_009 | X82: =IF(V82="","",IFERROR(_xlfn.XLOOKUP(V82,Mapping!$A:$A,Mapping!$B:$B),"")) -> Project_009 | Y82: External | Z82: Manual Test
A83: 82 | B83: Bùi Tấn Hạnh | C83: user082 | D83: OFF | E83: 44850 | F83: Senior Software Engineer | G83: 595 | H83: PROFESSIONAL SCRUM MASTER™ I;Microsoft Certified: Azure Fundamentals;Microsoft Certified: Azure Data Fundamentals;Cloud Developer;Java Web Developer;AWS Cloud Architect;EnglishScore;AWS Certified Developer - Associate | I83: FHM CMS | J83: HCM | K83: FHM | L83: FHM CMS | M83: .NET Framework | N83: Junior | O83: ReactJS Framework | P83: Middle | Q83: DEVE03 | R83: ANA | S83: =VLOOKUP(R83,Customer_Mapping!A:B,2,FALSE) -> Customer_007 | T83: FSO.HCM.FHM.CMS | U83: FR.SF.2025 | V83: STL_AG_02 | W83: =IF(U83="","",IFERROR(_xlfn.XLOOKUP(U83,Mapping!$A:$A,Mapping!$B:$B),"")) -> Project_021 | X83: =IF(V83="","",IFERROR(_xlfn.XLOOKUP(V83,Mapping!$A:$A,Mapping!$B:$B),"")) -> Project_009 | Y83: External | Z83: .NET Framework
A84: 83 | B84: Võ Thị Kim Hạnh | C84: user083 | D84: OFF | E84: 42720 | F84: Senior Software Tester | G84: 785 | H84: FSOFT Foreign Language Proficiency Test - TOEIC Test;EnglishScore;PROFESSIONAL SCRUM MASTER™ I;Truyền thông và Mạng máy tính;Điện toán đám mây;Working with SQL;SQL Căn bản;Foundation Certificate in Software Testing;NVIDIA Getting Started with AI on Jetson Nano;Oracle Cloud Infrastructure for Sunbird Ed Specialty;Core Designer Certificate;ISTQB Certified Tester Advanced Level - Test Analyst;Phần mềm máy tính | I84: FHM CMS | J84: HCM | K84: FHM | L84: FHM CMS | M84: Manual Test | N84: Senior | O84: Manual Test | P84: Middle | Q84: TEST03 | R84: FR | S84: =VLOOKUP(R84,Customer_Mapping!A:B,2,FALSE) -> Customer_001 | T84: FSO.HCM.FHM.CMS | U84: FRSME26 | V84: FR.SF.2025 | W84: =IF(U84="","",IFERROR(_xlfn.XLOOKUP(U84,Mapping!$A:$A,Mapping!$B:$B),"")) -> Project_033 | X84: =IF(V84="","",IFERROR(_xlfn.XLOOKUP(V84,Mapping!$A:$A,Mapping!$B:$B),"")) -> Project_021 | Y84: External | Z84: Manual Test
A85: 84 | B85: Nguyễn Ngọc Hà | C85: user084 | D85: OFF | E85: 44332 | F85: Senior Software Engineer | G85: 550 | H85: React;AI Programming with Python;Cloud Developer;AWS Cloud Architect;GitHub Copilot;Google Cloud Certified Generative AI Leader;Full Stack JavaScript Developer;Cloud DevOps Engineer;Cloud Developer using Microsoft Azure;EnglishScore;ML Practitioner Certificate;MLOps Practitioner Certificate;Advanced Designer Certificate;Core Designer Certificate;Developer Certificate;AWS Certified Developer - Associate;NVIDIA Getting Started with AI on Jetson Nano;Microsoft Certified: Azure Fundamentals;Microsoft Certified: Azure AI Engineer Associate;TOEIC Listening & Reading;Microsoft Certified: Azure Data Fundamentals | I85: FHM CMS | J85: HCM | K85: FHM | L85: FHM CMS | M85: Java Framework | O85: Java Framework | P85: Senior | Q85: DEVE03 | R85: FR | S85: =VLOOKUP(R85,Customer_Mapping!A:B,2,FALSE) -> Customer_001 | T85: FSO.HCM.FHM.CMS | U85: SBR_Buhin26 | V85: FRSME26 | W85: =IF(U85="","",IFERROR(_xlfn.XLOOKUP(U85,Mapping!$A:$A,Mapping!$B:$B),"")) -> Project_005 | X85: =IF(V85="","",IFERROR(_xlfn.XLOOKUP(V85,Mapping!$A:$A,Mapping!$B:$B),"")) -> Project_033 | Y85: External | Z85: Java Framework
A86: 85 | B86: Ngô Nguyễn Thu Hà | C86: user085 | D86: PRO | E86: 46226 | F86: Associate Business Analyst | I86: FHM CMS | J86: HCM | K86: FHM | L86: FHM CMS | O86: Project Management | P86: Middle | Q86: BANE01 | R86: SBR | S86: =VLOOKUP(R86,Customer_Mapping!A:B,2,FALSE) -> Customer_004 | T86: FSO.HCM.FHM.CMS | U86: FRSPL26 | V86: SBR_Buhin26 | W86: =IF(U86="","",IFERROR(_xlfn.XLOOKUP(U86,Mapping!$A:$A,Mapping!$B:$B),"")) -> Project_027 | X86: =IF(V86="","",IFERROR(_xlfn.XLOOKUP(V86,Mapping!$A:$A,Mapping!$B:$B),"")) -> Project_005 | Y86: External
A87: 86 | B87: Trương Phan Văn Hào | C87: user086 | D87: OFF | E87: 44363 | F87: Senior Software Engineer | G87: 950 | H87: Certified SAFe 6 Scrum Master;PROFESSIONAL SCRUM MASTER™ I;Microsoft Certified: Azure Data Fundamentals;Microsoft Certified: Azure Developer Associate;Java Web Developer Nanodegree;Japanese Language Proficiency Test N3;Katalon Practitioner Certification;Katalon Professional Level Certification;Katalon Expert Certification;Oracle Cloud Infrastructure 2024 Certified Foundations Associate;Core Designer Certificate;Advanced Designer Certificate;Google Cloud Certified Professional Data Engineer;Google Cloud Certified Professional Cloud DevOps Engineer;Google Cloud Certified Professional Cloud Network Engineer;Google Cloud Certified Professional Cloud Architect;Google Cloud Certified Professional Cloud Database Engineer;Oracle Cloud Infrastructure 2023 Certified Foundations Associate;Oracle Cloud Infrastructure for Sunbird Ed Specialty;Oracle Cloud Data Management 2023 Certified Foundations Associate;Oracle Cloud Infrastructure 2023 AI Certified Foundations Associate;PROFESSIONAL SCRUM MASTER™ II;Google Cloud Certified - Associate Cloud Engineer;EnglishScore;SQL;Agile Software Developer;Front End Web Developer;AWS Cloud Architect | I87: FHM CMS | J87: HCM | K87: FHM | L87: FHM CMS | M87: Database Engineering | O87: Java Framework | P87: Middle | Q87: DEVE04 | R87: FR | S87: =VLOOKUP(R87,Customer_Mapping!A:B,2,FALSE) -> Customer_001 | T87: FSO.HCM.FHM.CMS | U87: FRDLO | V87: FRSPL26 | W87: =IF(U87="","",IFERROR(_xlfn.XLOOKUP(U87,Mapping!$A:$A,Mapping!$B:$B),"")) -> Project_001 | X87: =IF(V87="","",IFERROR(_xlfn.XLOOKUP(V87,Mapping!$A:$A,Mapping!$B:$B),"")) -> Project_027 | Y87: External | Z87: Database Engineering
A88: 87 | B88: Huỳnh Trần Công Hậu | C88: user087 | D88: OFF | E88: 44332 | F88: Senior Software Engineer | G88: 785 | H88: EnglishScore;Java Web Developer;Google Ads Display Certification;Cloud Developer;NVIDIA Getting Started with AI on Jetson Nano | I88: FHM CMS | J88: HCM | K88: FHM | L88: FHM CMS | M88: Java Framework | O88: Java Framework | P88: Senior | Q88: DEVE04 | R88: FR | S88: =VLOOKUP(R88,Customer_Mapping!A:B,2,FALSE) -> Customer_001 | T88: FSO.HCM.FHM.CMS | U88: OPNEXT88 | V88: FRDLO | W88: =IF(U88="","",IFERROR(_xlfn.XLOOKUP(U88,Mapping!$A:$A,Mapping!$B:$B),"")) -> Project_020 | X88: =IF(V88="","",IFERROR(_xlfn.XLOOKUP(V88,Mapping!$A:$A,Mapping!$B:$B),"")) -> Project_001 | Y88: External | Z88: Java Framework
A89: 88 | B89: Nguyễn Ngọc Hậu | C89: user088 | D89: OFF | E89: 45253 | F89: Senior Software Tester | G89: 955 | H89: EnglishScore;Japanese Language Proficiency Test N3 | I89: FHM CMS | J89: HCM | K89: FHM | L89: FHM CMS | O89: Java Framework | P89: Middle | Q89: TEST04 | R89: OddsPark | S89: =VLOOKUP(R89,Customer_Mapping!A:B,2,FALSE) -> Customer_014 | T89: FSO.HCM.FHM.JPG | U89: OPNEXT88 | V89: OPNEXT88 | W89: =IF(U89="","",IFERROR(_xlfn.XLOOKUP(U89,Mapping!$A:$A,Mapping!$B:$B),"")) -> Project_020 | X89: =IF(V89="","",IFERROR(_xlfn.XLOOKUP(V89,Mapping!$A:$A,Mapping!$B:$B),"")) -> Project_020 | Y89: External
A90: 89 | B90: Võ Thị Ngọc Hiền | C90: user089 | D90: OFF | E90: 42902 | F90: Senior Software Tester | G90: 595 | H90: ISTQB advanced level - Test Manager;ISTQB® Certified Tester - AI Testing (ISTQB CT-AI);FSOFT Foreign Language Proficiency Test - TOEIC Test;EnglishScore;ISTQB Certified Tester - Foundation Level;Core Designer Certificate;Advanced Designer Certificate;ISTQB Certified Tester Advanced Level - Test Analyst;PROFESSIONAL SCRUM MASTER™ II;PROFESSIONAL SCRUM MASTER™ I | I90: FHM CMS | J90: HCM | K90: FHM | L90: FHM CMS | M90: Manual Test | N90: Senior | O90: Manual Test | P90: Junior | Q90: TEST03 | R90: OddsPark | S90: =VLOOKUP(R90,Customer_Mapping!A:B,2,FALSE) -> Customer_014 | T90: FSO.HCM.FHM.JPG | U90: FMCS3 | V90: OPNEXT88 | W90: =IF(U90="","",IFERROR(_xlfn.XLOOKUP(U90,Mapping!$A:$A,Mapping!$B:$B),"")) -> Project_017 | X90: =IF(V90="","",IFERROR(_xlfn.XLOOKUP(V90,Mapping!$A:$A,Mapping!$B:$B),"")) -> Project_020 | Y90: External | Z90: Manual Test
A91: 90 | B91: Trương Song Hiệp | C91: user090 | D91: OFF | E91: 45962 | F91: Senior Software Engineer | H91: GitHub Copilot | I91: FHM CMS | J91: HCM | K91: FHM | L91: FHM CMS | O91: Java Framework | P91: Middle | Q91: DEVE03 | R91: FR | S91: =VLOOKUP(R91,Customer_Mapping!A:B,2,FALSE) -> Customer_001 | T91: FSO.HCM.FHM.CMS | U91: JOCAR_Replace | V91: FMCS3 | W91: =IF(U91="","",IFERROR(_xlfn.XLOOKUP(U91,Mapping!$A:$A,Mapping!$B:$B),"")) -> Project_003 | X91: =IF(V91="","",IFERROR(_xlfn.XLOOKUP(V91,Mapping!$A:$A,Mapping!$B:$B),"")) -> Project_017 | Y91: External
A92: 91 | B92: Nguyễn Đông Hiếu | C92: user091 | D92: OFF | E92: 46082 | F92: Project Manager | I92: FHM CMS | J92: HCM | K92: FHM | L92: FHM CMS | O92: Project Management | P92: Middle | Q92: SPMA02 | R92: JJCM | S92: =VLOOKUP(R92,Customer_Mapping!A:B,2,FALSE) -> Customer_003 | T92: FSO.HCM.FHM.CMS | U92: FVD2025 | V92: JOCAR_Replace | W92: =IF(U92="","",IFERROR(_xlfn.XLOOKUP(U92,Mapping!$A:$A,Mapping!$B:$B),"")) -> Project_004 | X92: =IF(V92="","",IFERROR(_xlfn.XLOOKUP(V92,Mapping!$A:$A,Mapping!$B:$B),"")) -> Project_003 | Y92: External
A93: 92 | B93: Nguyễn Quang Minh Hiếu | C93: user092 | D93: OFF | E93: 46060 | F93: Associate Project Manager | H93: Japanese Language Proficiency Test N2;TOEIC Listening & Reading | I93: FHM JFL | J93: HCM | K93: FHM | L93: FHM JFL | O93: Project Management | P93: Junior | Q93: SPMA01 | R93: FR | S93: =VLOOKUP(R93,Customer_Mapping!A:B,2,FALSE) -> Customer_001 | T93: FSO.HCM.FHM.CMS | U93: STL_AG_02 | V93: FVD2025 | W93: =IF(U93="","",IFERROR(_xlfn.XLOOKUP(U93,Mapping!$A:$A,Mapping!$B:$B),"")) -> Project_009 | X93: =IF(V93="","",IFERROR(_xlfn.XLOOKUP(V93,Mapping!$A:$A,Mapping!$B:$B),"")) -> Project_004 | Y93: External
A94: 93 | B94: Đỗ Huy Hoàng | C94: user093 | D94: OFF | E94: 45062 | F94: Senior Software Engineer | G94: 845 | H94: Google Cloud Certified Generative AI Leader;TOEIC (Internal);Microsoft Certified: Azure AI Engineer Associate;Microsoft Certified: Azure Data Scientist Associate;EnglishScore;Developing ASP.NET MVC Web Applications;FSOFT Foreign Language Proficiency Test - TOEIC Test;Microsoft Certified: Azure Architect Technologies;Associate Traditional Web Developer O11;Microsoft Specialist: Programming in C#;Core Designer Certificate;Advanced Designer Certificate;AWS Certified SysOps Administrator - Associate;AWS Certified Cloud Practitioner;Microsoft Certified: Azure Solutions Architect Expert;Microsoft Certified: Azure Database Administrator Associate | I94: FHM CMS | J94: HCM | K94: FHM | L94: FHM CMS | M94: AWS Cloud | O94: DE | P94: Senior | Q94: DEVE04 | R94: ANA | S94: =VLOOKUP(R94,Customer_Mapping!A:B,2,FALSE) -> Customer_007 | T94: FSO.HCM.FHM.CMS | U94: SBR_Buhin26 | V94: STL_AG_02 | W94: =IF(U94="","",IFERROR(_xlfn.XLOOKUP(U94,Mapping!$A:$A,Mapping!$B:$B),"")) -> Project_005 | X94: =IF(V94="","",IFERROR(_xlfn.XLOOKUP(V94,Mapping!$A:$A,Mapping!$B:$B),"")) -> Project_009 | Y94: External | Z94: AWS Cloud
A95: 94 | B95: Hoàng Kim Bảo Hoàng | C95: user094 | D95: OFF | E95: 43669 | F95: Business Analyst | G95: 735 | H95: Core Designer Certificate;Advanced Designer Certificate;EnglishScore;Japanese Language Proficiency Test N1;Data Visualization;FSOFT Foreign Language Proficiency Test - TOEIC Test | I95: FHM CMS | J95: HCM | K95: FHM | L95: FHM CMS | M95: BA | N95: Middle | O95: BA | P95: Junior | Q95: BANE02 | R95: SBR | S95: =VLOOKUP(R95,Customer_Mapping!A:B,2,FALSE) -> Customer_004 | T95: FSO.HCM.FHM.CMS | U95: SF_Link_2026 | V95: SBR_Buhin26 | W95: =IF(U95="","",IFERROR(_xlfn.XLOOKUP(U95,Mapping!$A:$A,Mapping!$B:$B),"")) -> Project_008 | X95: =IF(V95="","",IFERROR(_xlfn.XLOOKUP(V95,Mapping!$A:$A,Mapping!$B:$B),"")) -> Project_005 | Y95: External | Z95: BA
A96: 95 | B96: Nguyễn Huy Hoàng | C96: user095 | D96: OFF | E96: 42614 | F96: Senior Software Engineer | G96: 690 | H96: Introduction to Blockchain Technologies;Digital Transformation;Budgeting and Scheduling Projects;Digital Business Models;Microsoft Certified: Azure Administrator Associate;EnglishScore;FSOFT Foreign Language Proficiency Test - TOEIC Test;Microsoft Certified: Azure DevOps Engineer Expert;AWS Certified Solutions Architect - Associate | I96: FHM CMS | J96: HCM | K96: FHM | L96: FHM CMS | M96: Azure Cloud | O96: Azure Cloud | P96: Senior | Q96: DEVE03 | R96: SBR | S96: =VLOOKUP(R96,Customer_Mapping!A:B,2,FALSE) -> Customer_004 | T96: FSO.HCM.FHM.CMS | U96: NEWKONG2 | V96: SF_Link_2026 | W96: =IF(U96="","",IFERROR(_xlfn.XLOOKUP(U96,Mapping!$A:$A,Mapping!$B:$B),"")) -> Project_014 | X96: =IF(V96="","",IFERROR(_xlfn.XLOOKUP(V96,Mapping!$A:$A,Mapping!$B:$B),"")) -> Project_008 | Y96: External | Z96: Azure Cloud
A97: 96 | B97: Nguyễn Minh Hoàng | C97: user096 | D97: OFF | E97: 43359 | F97: Senior Software Engineer | G97: 755 | H97: FSOFT Foreign Language Proficiency Test - TOEIC Test;Cloud Developer using Microsoft Azure;EnglishScore | I97: FHM CMS | J97: HCM | K97: FHM | L97: FHM CMS | M97: .NET Framework | N97: Senior | O97: .NET Framework | P97: Senior | Q97: DEVE04 | R97: FXSS | S97: =VLOOKUP(R97,Customer_Mapping!A:B,2,FALSE) -> Customer_010 | T97: FSO.HCM.FHM.CMS | U97: NEWKONG2 | V97: NEWKONG2 | W97: =IF(U97="","",IFERROR(_xlfn.XLOOKUP(U97,Mapping!$A:$A,Mapping!$B:$B),"")) -> Project_014 | X97: =IF(V97="","",IFERROR(_xlfn.XLOOKUP(V97,Mapping!$A:$A,Mapping!$B:$B),"")) -> Project_014 | Y97: External | Z97: .NET Framework
A98: 97 | B98: Nguyễn Vũ Hoàng | C98: user097 | D98: OFF | E98: 45185 | F98: Senior Software Engineer | H98: Japanese Language Proficiency Test N4 | I98: FHM CMS | J98: HCM | K98: FHM | L98: FHM CMS | M98: VueJS Framework | N98: Senior | O98: .NET Framework | P98: Senior | Q98: DEVE04 | R98: FXSS | S98: =VLOOKUP(R98,Customer_Mapping!A:B,2,FALSE) -> Customer_010 | T98: FSO.HCM.FHM.CMS | U98: FRSME26 | V98: NEWKONG2 | W98: =IF(U98="","",IFERROR(_xlfn.XLOOKUP(U98,Mapping!$A:$A,Mapping!$B:$B),"")) -> Project_033 | X98: =IF(V98="","",IFERROR(_xlfn.XLOOKUP(V98,Mapping!$A:$A,Mapping!$B:$B),"")) -> Project_014 | Y98: External | Z98: VueJS Framework
A99: 98 | B99: Phạm Huy Hoàng | C99: user098 | D99: OFF | E99: 44911 | F99: Software Engineer | G99: 950 | H99: NVIDIA Getting Started with AI on Jetson Nano;Mendix Rapid Developer;AWS Certified Solutions Architect - Associate;Oracle Certified Associate, Java SE 8 Programmer I;AWS Certified Cloud Practitioner;IELTS 7.0;OKR Certification: Leadership and Goal Setting;Microsoft Azure Fundamentals AZ-900 Exam Prep;GitHub Copilot;Microsoft Certified: Azure AI Apps and Agents Developer Associate;EnglishScore;Cloud Developer using Microsoft Azure | I99: FHM CMS | J99: HCM | K99: FHM | L99: FHM CMS | M99: Java Framework | N99: Junior | O99: Java Framework | P99: Junior | Q99: DEVE02 | R99: FR | S99: =VLOOKUP(R99,Customer_Mapping!A:B,2,FALSE) -> Customer_001 | T99: FSO.HCM.FHM.CMS | U99: SF_Link_2026 | V99: FRSME26 | W99: =IF(U99="","",IFERROR(_xlfn.XLOOKUP(U99,Mapping!$A:$A,Mapping!$B:$B),"")) -> Project_008 | X99: =IF(V99="","",IFERROR(_xlfn.XLOOKUP(V99,Mapping!$A:$A,Mapping!$B:$B),"")) -> Project_033 | Y99: External | Z99: Java Framework
A100: 99 | B100: Vũ Văn Hoàng | C100: user099 | D100: OFF | E100: 44470 | F100: Senior Software Engineer | G100: 925 | H100: EnglishScore;Cloud Developer;GitHub Copilot;AWS Certified Developer - Associate;Core Designer Certificate;Advanced Designer Certificate;SQL (Advanced);Oracle Cloud Infrastructure for Sunbird Ed Specialty;Microsoft 365 Fundamentals;Microsoft Certified: Dynamics 365 Fundamentals (CRM);Google Cloud Certified Professional Cloud Architect;Microsoft 365 Certified: Fundamentals;Google Cloud Certified Cloud Digital Leader;Microsoft Certified: Security, Compliance, and Identity Fundamentals;NVIDIA Getting Started with AI on Jetson Nano;Oracle Cloud Infrastructure 2023 Certified Foundations Associate;Mendix Rapid Developer;Oracle Cloud Infrastructure 2023 AI Certified Foundations Associate;Google Cloud Certified Professional Cloud Developer;Oracle Cloud Data Management 2023 Certified Foundations Associate;Microsoft Certified: Azure AI Fundamentals;Google Cloud Certified - Associate Cloud Engineer;Microsoft Certified: Azure Data Scientist Associate;Microsoft Certified: Azure Data Engineer Associate;Microsoft Certified: Azure Fundamentals;Microsoft Certified: Azure AI Engineer Associate | I100: FHM CMS | J100: HCM | K100: FHM | L100: FHM CMS | M100: Java Framework | O100: Database Engineering | P100: Middle | Q100: DEVE03 | R100: SBR | S100: =VLOOKUP(R100,Customer_Mapping!A:B,2,FALSE) -> Customer_004 | T100: FSO.HCM.FHM.CMS | U100: OPNEXT88 | V100: SF_Link_2026 | W100: =IF(U100="","",IFERROR(_xlfn.XLOOKUP(U100,Mapping!$A:$A,Mapping!$B:$B),"")) -> Project_020 | X100: =IF(V100="","",IFERROR(_xlfn.XLOOKUP(V100,Mapping!$A:$A,Mapping!$B:$B),"")) -> Project_008 | Y100: External | Z100: Java Framework
...

Sheet Update Agent usage sync
A1: no | B1: account | C1: v0.10.5 | D1: v0.10.8 | E1: v0.10.10 | F1: v0.10.12 | G1: v0.10.13 | H1: v0.0.15
A2: 1 | B2: user001 | C2: 1 | D2: 0 | E2: 0 | F2: 1 | G2: 0 | H2: =IF(RAND()<0.6,0,1) -> 1
A3: 2 | B3: user002 | C3: 1 | D3: 1 | E3: 0 | F3: 1 | G3: 1 | H3: =IF(RAND()<0.6,0,1) -> 1
A4: 3 | B4: user003 | C4: 0 | D4: 1 | E4: 0 | F4: 0 | G4: 1 | H4: =IF(RAND()<0.6,0,1) -> 1
A5: 4 | B5: user004 | C5: 1 | D5: 1 | E5: 1 | F5: 0 | G5: 0 | H5: =IF(RAND()<0.6,0,1) -> 0
A6: 5 | B6: user005 | C6: 1 | D6: 0 | E6: 1 | F6: 1 | G6: 1 | H6: =IF(RAND()<0.6,0,1) -> 0
A7: 6 | B7: user006 | C7: 1 | D7: 0 | E7: 1 | F7: 0 | G7: 0 | H7: =IF(RAND()<0.6,0,1) -> 1
A8: 7 | B8: user007 | C8: 0 | D8: 0 | E8: 0 | F8: 0 | G8: 1 | H8: =IF(RAND()<0.6,0,1) -> 0
A9: 8 | B9: user008 | C9: 1 | D9: 0 | E9: 0 | F9: 0 | G9: 0 | H9: =IF(RAND()<0.6,0,1) -> 0
A10: 9 | B10: user009 | C10: 0 | D10: 1 | E10: 0 | F10: 0 | G10: 1 | H10: =IF(RAND()<0.6,0,1) -> 1
A11: 10 | B11: user010 | C11: 1 | D11: 0 | E11: 0 | F11: 1 | G11: 1 | H11: =IF(RAND()<0.6,0,1) -> 0
A12: 11 | B12: user011 | C12: 0 | D12: 0 | E12: 1 | F12: 1 | G12: 0 | H12: =IF(RAND()<0.6,0,1) -> 0
A13: 12 | B13: user012 | C13: 0 | D13: 1 | E13: 0 | F13: 0 | G13: 0 | H13: =IF(RAND()<0.6,0,1) -> 0
... A390: 389 | B390: user389 | C390: 1 | D390: 0 | E390: 0 | F390: 1 | G390: 1 | H390: =IF(RAND()<0.6,0,1) -> 1

Sheet Worklog Compliance
D1: Total Worklog (h)
A2: employee_id | B2: Total | C2: unlogged_days | D2: 8/10 | E2: 8/11 | F2: 8/12 | G2: 8/13 | H2: 8/14 | I2: 8/17 | J2: 8/18 | K2: 8/19 | L2: 8/20 | M2: 8/21 | N2: 8/24 | O2: 8/25 | P2: 8/26 | Q2: 8/27 | R2: 8/28 | S2: 9/3 | T2: 9/4
A3: 1 | B3: =COUNTIF(D3:T3,0) -> 16 | C3: {=_xlfn.TEXTJOIN(", ",TRUE,IF(D3:T3=0,TEXT(D$2:T$2,"dd/mm"),""))} -> 10/08, 11/08, 12/08, 13/08, 14/08, 18/08, 19/08, 20/08, 21/08, 24/08, 25/08, 26/08, 27/08, 28/08, 03/09, 04/09 | D3: 0 | E3: 0 | F3: 0 | G3: 0 | H3: 0 | I3: 12 | J3: 0 | K3: 0 | L3: 0 | M3: 0 | N3: 0 | O3: 0 | P3: 0 | Q3: 0 | R3: 0 | S3: 0 | T3: 0
A4: 2 | B4: =COUNTIF(D4:T4,0) -> 15 | C4: {=_xlfn.TEXTJOIN(", ",TRUE,IF(D4:T4=0,TEXT(D$2:T$2,"dd/mm"),""))} -> 10/08, 11/08, 12/08, 13/08, 17/08, 18/08, 19/08, 20/08, 21/08, 24/08, 25/08, 26/08, 27/08, 03/09, 04/09 | D4: 0 | E4: 0 | F4: 0 | G4: 0 | H4: 8 | I4: 0 | J4: 0 | K4: 0 | L4: 0 | M4: 0 | N4: 0 | O4: 0 | P4: 0 | Q4: 0 | R4: 8 | S4: 0 | T4: 0
A5: 3 | B5: =COUNTIF(D5:T5,0) -> 16 | C5: {=_xlfn.TEXTJOIN(", ",TRUE,IF(D5:T5=0,TEXT(D$2:T$2,"dd/mm"),""))} -> 10/08, 11/08, 12/08, 13/08, 14/08, 17/08, 18/08, 19/08, 20/08, 21/08, 24/08, 25/08, 27/08, 28/08, 03/09, 04/09 | D5: 0 | E5: 0 | F5: 0 | G5: 0 | H5: 0 | I5: 0 | J5: 0 | K5: 0 | L5: 0 | M5: 0 | N5: 0 | O5: 0 | P5: 8 | Q5: 0 | R5: 0 | S5: 0 | T5: 0
A6: 4 | B6: =COUNTIF(D6:T6,0) -> 3 | C6: {=_xlfn.TEXTJOIN(", ",TRUE,IF(D6:T6=0,TEXT(D$2:T$2,"dd/mm"),""))} -> 17/08, 18/08, 03/09 | D6: 8 | E6: 8 | F6: 8 | G6: 8 | H6: 8 | I6: 0 | J6: 0 | K6: 8 | L6: 8 | M6: 8 | N6: 8 | O6: 8 | P6: 8 | Q6: 8 | R6: 8 | S6: 0 | T6: 4
A7: 5 | B7: =COUNTIF(D7:T7,0) -> 16 | C7: {=_xlfn.TEXTJOIN(", ",TRUE,IF(D7:T7=0,TEXT(D$2:T$2,"dd/mm"),""))} -> 10/08, 11/08, 12/08, 13/08, 14/08, 17/08, 18/08, 20/08, 21/08, 24/08, 25/08, 26/08, 27/08, 28/08, 03/09, 04/09 | D7: 0 | E7: 0 | F7: 0 | G7: 0 | H7: 0 | I7: 0 | J7: 0 | K7: 8 | L7: 0 | M7: 0 | N7: 0 | O7: 0 | P7: 0 | Q7: 0 | R7: 0 | S7: 0 | T7: 0
A8: 6 | B8: =COUNTIF(D8:T8,0) -> 17 | C8: {=_xlfn.TEXTJOIN(", ",TRUE,IF(D8:T8=0,TEXT(D$2:T$2,"dd/mm"),""))} -> 10/08, 11/08, 12/08, 13/08, 14/08, 17/08, 18/08, 19/08, 20/08, 21/08, 24/08, 25/08, 26/08, 27/08, 28/08, 03/09, 04/09 | D8: 0 | E8: 0 | F8: 0 | G8: 0 | H8: 0 | I8: 0 | J8: 0 | K8: 0 | L8: 0 | M8: 0 | N8: 0 | O8: 0 | P8: 0 | Q8: 0 | R8: 0 | S8: 0 | T8: 0
A9: 7 | B9: =COUNTIF(D9:T9,0) -> 17 | C9: {=_xlfn.TEXTJOIN(", ",TRUE,IF(D9:T9=0,TEXT(D$2:T$2,"dd/mm"),""))} -> 10/08, 11/08, 12/08, 13/08, 14/08, 17/08, 18/08, 19/08, 20/08, 21/08, 24/08, 25/08, 26/08, 27/08, 28/08, 03/09, 04/09 | D9: 0 | E9: 0 | F9: 0 | G9: 0 | H9: 0 | I9: 0 | J9: 0 | K9: 0 | L9: 0 | M9: 0 | N9: 0 | O9: 0 | P9: 0 | Q9: 0 | R9: 0 | S9: 0 | T9: 0
A10: 8 | B10: =COUNTIF(D10:T10,0) -> 17 | C10: {=_xlfn.TEXTJOIN(", ",TRUE,IF(D10:T10=0,TEXT(D$2:T$2,"dd/mm"),""))} -> 10/08, 11/08, 12/08, 13/08, 14/08, 17/08, 18/08, 19/08, 20/08, 21/08, 24/08, 25/08, 26/08, 27/08, 28/08, 03/09, 04/09 | D10: 0 | E10: 0 | F10: 0 | G10: 0 | H10: 0 | I10: 0 | J10: 0 | K10: 0 | L10: 0 | M10: 0 | N10: 0 | O10: 0 | P10: 0 | Q10: 0 | R10: 0 | S10: 0 | T10: 0
A11: 9 | B11: =COUNTIF(D11:T11,0) -> 9 | C11: {=_xlfn.TEXTJOIN(", ",TRUE,IF(D11:T11=0,TEXT(D$2:T$2,"dd/mm"),""))} -> 11/08, 13/08, 17/08, 19/08, 24/08, 27/08, 28/08, 03/09, 04/09 | D11: 8 | E11: 0 | F11: 8 | G11: 0 | H11: 8 | I11: 0 | J11: 8 | K11: 0 | L11: 4.3 | M11: 1 | N11: 0 | O11: 8 | P11: 8 | Q11: 0 | R11: 0 | S11: 0 | T11: 0
A12: 10 | B12: =COUNTIF(D12:T12,0) -> 13 | C12: {=_xlfn.TEXTJOIN(", ",TRUE,IF(D12:T12=0,TEXT(D$2:T$2,"dd/mm"),""))} -> 10/08, 11/08, 12/08, 13/08, 14/08, 17/08, 19/08, 20/08, 21/08, 25/08, 26/08, 27/08, 04/09 | D12: 0 | E12: 0 | F12: 0 | G12: 0 | H12: 0 | I12: 0 | J12: 8 | K12: 0 | L12: 0 | M12: 0 | N12: 8 | O12: 0 | P12: 0 | Q12: 0 | R12: 8 | S12: 8 | T12: 0
A13: 11 | B13: =COUNTIF(D13:T13,0) -> 3 | C13: {=_xlfn.TEXTJOIN(", ",TRUE,IF(D13:T13=0,TEXT(D$2:T$2,"dd/mm"),""))} -> 20/08, 28/08, 03/09 | D13: 8 | E13: 8 | F13: 8 | G13: 8 | H13: 8 | I13: 8 | J13: 8 | K13: 6 | L13: 0 | M13: 8 | N13: 8 | O13: 8 | P13: 8 | Q13: 8 | R13: 0 | S13: 0 | T13: 8
A14: 12 | B14: =COUNTIF(D14:T14,0) -> 6 | C14: {=_xlfn.TEXTJOIN(", ",TRUE,IF(D14:T14=0,TEXT(D$2:T$2,"dd/mm"),""))} -> 11/08, 14/08, 26/08, 28/08, 03/09, 04/09 | D14: 8 | E14: 0 | F14: 8 | G14: 8 | H14: 0 | I14: 8 | J14: 8 | K14: 8 | L14: 8 | M14: 8 | N14: 8 | O14: 8 | P14: 0 | Q14: 8 | R14: 0 | S14: 0 | T14: 0
... A35: 33 | B35: =COUNTIF(D35:T35,0) -> 17 | C35: {=_xlfn.TEXTJOIN(", ",TRUE,IF(D35:T35=0,TEXT(D$2:T$2,"dd/mm"),""))} -> 10/08, 11/08, 12/08, 13/08, 14/08, 17/08, 18/08, 19/08, 20/08, 21/08, 24/08, 25/08, 26/08, 27/08, 28/08, 03/09, 04/09 | D35: 0 | E35: 0 | F35: 0 | G35: 0 | H35: 0 | I35: 0 | J35: 0 | K35: 0 | L35: 0 | M35: 0 | N35: 0 | O35: 0 | P35: 0 | Q35: 0 | R35: 0 | S35: 0 | T35: 0

Sheet Certificate registration
A1: employee_id | B1: AI Certification | C1: AI Claude
A2: 1 | B2: 0 | C2: 0
A3: 2 | B3: 1 | C3: 1
A4: 3 | B4: 1 | C4: 0
A5: 4 | B5: 0 | C5: 0
A6: 5 | B6: 0 | C6: 0
A7: 6 | B7: 0 | C7: 0
A8: 7 | B8: 0 | C8: 1
A9: 8 | B9: 0 | C9: 1
A10: 9 | B10: 0 | C10: 1
A11: 10 | B11: 0 | C11: 0
A12: 11 | B12: 0 | C12: 0
A13: 12 | B13: 1 | C13: 1
... A39: 38 | B39: 1 | C39: 1
A40: 39
A41: 40
A42: 41
A43: 42
A44: 43
A45: 44
A46: 45
A47: 46
A48: 47
A49: 48
A50: 49

Sheet KG data training
A1: STT | B1: training_hours | C1: manager_support_score | D1: burnout_score | E1: engagement_score | F1: work_life_balance_score | G1: performance_rating | H1: last_review_score | I1: uses_ai_tools_at_work | J1: perceived_ai_job_risk
A2: 1 | B2: 17 | C2: 9.4 | D2: 1 | E2: 9.7 | F2: 7.7 | G2: 3 | H2: 8.3 | I2: TRUE | J2: 4.8
A3: 2 | B3: 21 | C3: 4.2 | D3: 1.9 | E3: 5.4 | F3: 7.8 | G3: 3 | H3: 8 | I3: TRUE | J3: 2.9
A4: 3 | B4: 22 | C4: 7.5 | D4: 5.3 | E4: 6.5 | F4: 7 | G4: 4 | H4: 9.5 | I4: TRUE | J4: 7.2
A5: 4 | B5: 21 | C5: 8.7 | D5: 4.3 | E5: 7.3 | F5: 3.5 | G5: 4 | H5: 7.9 | I5: FALSE | J5: 5.2
A6: 5 | B6: 20 | C6: 7.5 | D6: 2.3 | E6: 7 | F6: 7.2 | G6: 4 | H6: 8.5 | I6: FALSE | J6: 6.4
A7: 6 | B7: 13 | C7: 6.8 | D7: 4.5 | E7: 8.2 | F7: 7 | G7: 4 | H7: 7.9 | I7: TRUE | J7: 7.3
A8: 7 | B8: 7 | C8: 10 | D8: 3.8 | E8: 6.2 | F8: 6.9 | G8: 4 | H8: 7.5 | I8: FALSE | J8: 7.9
A9: 8 | B9: 16 | C9: 5.4 | D9: 5.5 | E9: 7.2 | F9: 7 | G9: 4 | H9: 10 | I9: TRUE | J9: 3.7
A10: 9 | B10: 17 | C10: 7.3 | D10: 5.1 | E10: 7.5 | F10: 5.7 | G10: 3 | H10: 9.5 | I10: TRUE | J10: 4.8
A11: 10 | B11: 41 | C11: 8.6 | D11: 2.3 | E11: 9.1 | F11: 6.3 | G11: 4 | H11: 8.8 | I11: FALSE | J11: 5.5
A12: 11 | B12: 27 | C12: 3.1 | D12: 3.8 | E12: 4.7 | F12: 7.3 | G12: 3 | H12: 5.8 | I12: FALSE | J12: 5.6
A13: 12 | B13: 21 | C13: 4.4 | D13: 6.3 | E13: 5.1 | F13: 4.7 | G13: 4 | H13: 10 | I13: TRUE | J13: 8.5
... A49: 48 | B49: 14 | C49: 7 | D49: 2.7 | E49: 6.1 | F49: 6.3 | G49: 4 | H49: 10 | I49: TRUE | J49: 4

Sheet Bảng data nhân sự full
A1: STT | B1: Full Name | C1: Account | D1: Contract Type | E1: Hire Date | F1: Job Title | G1: Toeic Score | H1: Certificates | I1: Department | J1: Location | K1: Parent Department | L1: Child Department | M1: Main Skill | N1: Seniority(Main) | O1: Current Skill | P1: Seniority(Current)
A2: 1 | B2: Lê Văn Thân | C2: ThanLV | D2: OFF | E2: 44958 | F2: Senior Project Manager | G2: 955 | H2: EnglishScore;Project Management Professional (PMP) | I2: FHM CMS | J2: HCM | K2: FHM | L2: FHM CMS | M2: Project Management | O2: Project Management | P2: Middle
A3: 2 | B3: Nguyễn Đông Hiếu | C3: HieuND97 | D3: OFF | E3: 46082 | F3: Project Manager | I3: FHM CMS | J3: HCM | K3: FHM | L3: FHM CMS | O3: Project Management | P3: Middle
A4: 3 | B4: Nguyễn Minh Nhựt | C4: NhutNM5 | D4: OFF | E4: 44667 | F4: Associate Project Manager | G4: 910 | H4: PROFESSIONAL SCRUM MASTER™ I;EnglishScore;PROFESSIONAL SCRUM MASTER™ II;Oracle Cloud Infrastructure 2023 Certified Foundations Associate;Oracle Cloud Data Management 2023 Certified Foundations Associate;Oracle Cloud Infrastructure 2023 AI Certified Foundations Associate;Core Designer Certificate;Advanced Designer Certificate;Oracle Cloud Infrastructure for Sunbird Ed Specialty;Aptis General - Listening Reading Speaking Writing - Level B2 | I4: FHM CMS | J4: HCM | K4: FHM | L4: FHM CMS | M4: .NET Framework | N4: Junior | O4: Project Management | P4: Junior
A5: 4 | B5: Nguyễn Hoàng Tuyên | C5: TuyenNH1 | D5: OFF | E5: 43062 | F5: Project Manager | G5: 620 | H5: C++ Standard Template Library;EnglishScore;FSOFT Foreign Language Proficiency Test - TOEIC Test;PROFESSIONAL SCRUM MASTER™ I;TOEIC (Internal);PMI Agile Certified Practitioner (PMI-ACP)® | I5: FHM CMS | J5: HCM | K5: FHM | L5: FHM CMS | M5: Project Management | O5: Project Management | P5: Junior
A6: 5 | B6: Tran Duc Hien | C6: HienDT25 | D6: OFF | E6: 45427 | F6: Senior Software Engineer | G6: 720 | H6: EnglishScore;Azure Fundamentals | I6: FHM CMS | J6: HCM | K6: FHM | L6: FHM CMS | M6: .NET Framework | O6: .NET Framework | P6: Middle
A7: 6 | B7: Nguyen Hoang Thong | C7: ThongNH7 | D7: OFF | E7: 45870 | F7: Solution Architect | G7: 740 | H7: Google Cloud Certified Professional Cloud Developer;Google Cloud Certified - Associate Cloud Engineer;Microsoft Certified: Azure Fundamentals;Microsoft Certified: Azure Developer Associate;Microsoft Certified: Azure Data Engineer Associate;Microsoft Certified: Azure Solutions Architect Expert;Microsoft Certified: DevOps Engineer Expert;Cloud Architect using Microsoft Azure;EnglishScore;FSOFT Foreign Language Proficiency Test - TOEIC Test;GitHub Copilot;Agile Scrum Foundation;Secure Coding | I7: FHM CMS | J7: HCM | K7: FHM | L7: FHM CMS | M7: .NET Framework | O7: Azure Cloud | P7: Middle
A8: 7 | B8: Châu Hồng Vũ | C8: VuCH2 | D8: OFF | E8: 43983 | F8: Solution Architect | G8: 755 | H8: Google Cloud Certified Professional Cloud Developer;Core Designer Certificate;Advanced Designer Certificate;Microsoft Certified: Azure Data Engineer Associate;Microsoft Certified: Azure Database Administrator Associate;Microsoft Certified: Azure IoT Developer Specialty;Microsoft Certified: Azure Solutions Architect Expert;Microsoft Certified: DevOps Engineer Expert;Google Cloud Certified - Associate Cloud Engineer;Microsoft Certified: Azure Fundamentals;Microsoft Certified: Azure Developer Associate;FSOFT Foreign Language Proficiency Test - TOEIC Test;EnglishScore;Cloud Architect using Microsoft Azure | I8: FHM CMS | J8: HCM | K8: FHM | L8: FHM CMS | M8: .NET Framework | N8: Middle | O8: Azure Cloud | P8: Senior
A9: 8 | B9: Nguyễn Quốc Bảo | C9: BaoNQ12 | D9: OFF | E9: 43366 | F9: Associate Solution Architect | G9: 735 | H9: Microsoft Certified: Azure Solutions Architect Expert;Developing ASP.NET MVC Web Applications;Microsoft Certified: Azure Developer Associate;PROFESSIONAL SCRUM MASTER™ I;Microsoft Certified Solutions Associate: Web Applications;Cloud Native Application Architecture;Th?c s? K? thu?t Ph?n m?m (AI MSE);Google Cloud Certified: Cloud Digital Leader;Agile Development;Data Mining Foundations and Practice;Microsoft Certified: Azure DevOps Engineer Expert;Core Designer Certificate;Advanced Designer Certificate;Microsoft Specialist: Programming in C#;Microsoft Certified: Azure Fundamentals;EnglishScore;Microsoft Certified: Azure Architect Technologies;AWS Cloud Architect;FSOFT Foreign Language Proficiency Test - TOEIC Test;Associate Traditional Web Developer O11 | I9: FHM CMS | J9: HCM | K9: FHM | L9: FHM CMS | M9: Azure Cloud | O9: Azure Cloud | P9: Senior
A10: 9 | B10: Hoàng Yến Anh | C10: AnhHY | D10: OFF | E10: 44028 | F10: Senior Software Engineer | G10: 955 | H10: Advanced Designer Certificate;Core Designer Certificate;EnglishScore;FSOFT Foreign Language Proficiency Test - TOEIC Test;GitHub Copilot;Google Cloud Certified - Associate Cloud Engineer;AWS Certified Developer - Associate;Microsoft Certified: Azure AI Engineer Associate;PROFESSIONAL SCRUM MASTER™ I;PROFESSIONAL SCRUM MASTER™ II;Enrich skills to succeed - Go Platform;AWS Certified Solutions Architect - Associate;Microsoft Certified: Azure AI Fundamentals;Microsoft Certified: Azure Data Fundamentals | I10: FHM CMS | J10: HCM | K10: FHM | L10: FHM CMS | M10: Java Framework | N10: Middle | O10: Java Framework | P10: Middle
A11: 10 | B11: Võ Minh Tâm | C11: TamVM7 | D11: OFF | E11: 45084 | F11: Senior Software Engineer | G11: 550 | H11: EnglishScore | I11: FHM CMS | J11: HCM | K11: FHM | L11: FHM CMS | M11: ReactJS Framework | N11: Senior | O11: ReactJS Framework | P11: Senior
A12: 11 | B12: Phạm Duy An | C12: AnPD3 | D12: OFF | E12: 46007 | F12: Senior Software Engineer | I12: FHM CMS | J12: HCM | K12: FHM | L12: FHM CMS | M12: .NET Framework | N12: Middle | O12: Java Framework | P12: Junior
A13: 12 | B13: Nguyễn Đình Toại | C13: ToaiND2 | D13: OFF | E13: 46026 | F13: Application Developer | H13: EnglishScore;Developer Certificate;GitHub Copilot;Microsoft Certified: Azure Fundamentals;Java Programming;Agile Scrum Foundation | I13: F1 JDC | J13: HCM | K13: F1 | L13: F1 JDC | M13: Java Framework | N13: Junior | O13: Java Framework | P13: Junior
A14: 13 | B14: Lê Hồng Như | C14: NhuLH18 | D14: OFF | E14: 45084 | F14: Senior Software Engineer | G14: 665 | H14: Cloud Developer;EnglishScore;Product Manager | I14: FHM CMS | J14: HCM | K14: FHM | L14: FHM CMS | M14: ReactJS Framework | N14: Middle | O14: Java Framework | P14: Middle
A15: 14 | B15: Nguyễn Quốc Minh | C15: MinhNQ12 | D15: OFF | E15: 44005 | F15: Senior Business Analyst | G15: 710 | H15: EnglishScore;Japanese Language Proficiency Test N2;FSOFT Foreign Language Proficiency Test - TOEIC Test;Introduction to Data Science in Python;FSOFT Customer Interview Training;Interview Skill for Interviewer | I15: FHM CMS | J15: HCM | K15: FHM | L15: FHM CMS | M15: BA | N15: Senior | O15: BA | P15: Junior
A16: 15 | B16: Nguyễn Thị Minh Ngọc | C16: NgocNTM37 | D16: OFF | E16: 46023 | F16: Associate Business Analyst | H16: Japanese Language Proficiency Test N3 | I16: FHM CMS | J16: HCM | K16: FHM | L16: FHM CMS | O16: BA | P16: Junior
A17: 16 | B17: Phan Thị Tuyết Nhi | C17: NhiPTT8 | D17: OFF | E17: 45283 | F17: Business Analyst | G17: 755 | H17: EnglishScore;Business Analytics;Developer Certificate;Generative AI Practitioner Certificate;ML Practitioner Certificate;AI in Office;Core Designer Certificate;Advanced Designer Certificate | I17: FHM CMS | J17: HCM | K17: FHM | L17: FHM CMS | M17: BA | N17: Junior | O17: BA | P17: Junior
A18: 17 | B18: Nguyễn Quang Phát | C18: PhatNQ15 | D18: OFF | E18: 45854 | F18: Business Analyst | H18: Japanese Language Proficiency Test N2 | I18: FHM CMS | J18: HCM | K18: FHM | L18: FHM CMS | O18: BA | P18: Middle
A19: 18 | B19: Nguyễn Quỳnh Như | C19: NhuNQ16 | D19: OFF | E19: 45283 | F19: Business Analyst | H19: Japanese Language Proficiency Test N2;Japanese Language Proficiency Test N3;TOEIC Listening & Reading;Professional Scrum Product Owner I;Core Designer Certificate;Business Intelligence Analytics;Programming for Data Science with Python;Introduction to Python;Microsoft Certified: Azure Fundamentals;Professional Scrum Product Owner II;Certification of Capability in Business Analysis (CCBA);Introduction to Version Control | I19: FHM CMS | J19: HCM | K19: FHM | L19: FHM CMS | M19: BA | N19: Junior | O19: BA | P19: Junior
A20: 19 | B20: Phan Thị Cẩm Tiên | C20: TienPTC10 | D20: OFF | E20: 45283 | F20: Business Analyst | H20: SQL;Japanese Language Proficiency Test N2 | I20: FHM CMS | J20: HCM | K20: FHM | L20: FHM CMS | M20: BA | N20: Junior | O20: BA | P20: Junior
A21: 20 | B21: Nguyễn Lê Duy | C21: DuyNL15 | D21: OFF | E21: 46014 | F21: Senior Software Engineer | I21: FHM CMS | J21: HCM | K21: FHM | L21: FHM CMS | O21: Java Framework | P21: Junior
A22: 21 | B22: Trần Duy Minh Mẫn | C22: ManTDM2 | D22: OFF | E22: 46149 | F22: Senior Software Engineer | I22: FHM CMS | J22: HCM | K22: FHM | L22: FHM CMS | O22: ReactJS Framework | P22: Senior
A23: 22 | B23: Giảng Hán Tài | C23: TaiGH | D23: OFF | E23: 45885 | F23: Senior Software Engineer | G23: 690 | H23: Microsoft Certified: Azure Data Fundamentals;PROFESSIONAL SCRUM MASTER™ I | I23: FHM CMS | J23: HCM | K23: FHM | L23: FHM CMS | M23: .NET Framework | O23: .NET Framework | P23: Middle
A24: 23 | B24: Nguyễn Ngọc Thái Vĩ | C24: ViNNT7 | D24: OFF | E24: 46168 | F24: Application Developer | G24: 710 | H24: EnglishScore;Developer Certificate;GitHub Copilot;Microsoft Certified: Azure Fundamentals;Java Programming;SQL | I24: F1 JDC | J24: HCM | K24: F1 | L24: F1 JDC | M24: Java Framework | N24: Junior | O24: Java Framework | P24: Junior
A25: 24 | B25: Nguyễn Thị Thủy Tiên | C25: TienNTT | D25: OFF | E25: 40929 | F25: Senior Business Analyst | G25: 595 | H25: FSOFT Foreign Language Proficiency Test - TOEIC Test;ISTQB Certified Tester - Foundation Level;EnglishScore | I25: FHM CMS | J25: HCM | K25: FHM | L25: FHM CMS | M25: BA | N25: Senior | O25: DevOps & CI/CD Engineering | P25: Junior
A26: 25 | B26: Phạm Văn Sỹ | C26: SYPV1 | D26: OFF | E26: 43182 | F26: Senior Software Engineer | G26: 575 | H26: Effective Problem-Solving and Decision-Making;Developing Web Apps (OutSystems 11);EnglishScore;FSOFT Foreign Language Proficiency Test - TOEIC Test | I26: FHM CMS | J26: HCM | K26: FHM | L26: FHM CMS | M26: .NET Framework | N26: Senior | O26: DevOps & CI/CD Engineering | P26: Junior
A27: 26 | B27: Trần Duy Khánh | C27: KhanhTD17 | D27: OFF | E27: 46174 | F27: Application Developer | G27: 880 | H27: EnglishScore;Developer Certificate;GitHub Copilot;Microsoft Certified: Azure Fundamentals;Agile Scrum Foundation | I27: F1 JDC | J27: HCM | K27: F1 | L27: F1 JDC | M27: Java Framework | N27: Junior | O27: Java Framework | P27: Junior
A28: 27 | B28: Tạ Minh Giang | C28: GiangTM4 | D28: OFF | E28: 46174 | F28: Application Developer | G28: 850 | H28: Cloud Developer;EnglishScore;Product Manager;GitHub Copilot;React Developer;Microsoft Certified: Azure Fundamentals;Agile Scrum Foundation | I28: F1 JDC | J28: HCM | K28: F1 | L28: F1 JDC | M28: ReactJS Framework | N28: Middle | O28: ReactJS Framework | P28: Middle
A29: 28 | B29: Nguyễn Đình Khôi | C29: KhoiND3 | D29: OFF | E29: 46218 | F29: Application Developer | I29: F1 JDC | J29: HCM | K29: F1 | L29: F1 JDC | M29: Java Framework | N29: Junior | O29: Java Framework | P29: Junior
A30: 29 | B30: Hoàng Thị Hằng | C30: HangHT50 | D30: OFF | E30: 45923 | F30: Principal Test Analyst | I30: FHM CMS | J30: HCM | K30: FHM | L30: FHM CMS | O30: Manual Test | P30: Senior
A31: 30 | B31: Lê Thị Mỹ Hoa | C31: HoaLTM6 | D31: OFF | E31: 46168 | F31: Manual Test | I31: FHM CMS | J31: HCM | K31: FHM | L31: FHM CMS | O31: Manual Test | P31: Junior
A32: 31 | B32: Phạm Thành Đạt | C32: DatPT102 | D32: OFF | E32: 45398 | F32: Senior Software Tester | G32: 710 | H32: EnglishScore;ISTQB Certified Tester Advanced Level - Test Analyst | I32: FHM CMS | J32: HCM | K32: FHM | L32: FHM CMS | O32: Manual Test | P32: Middle
A33: 32 | B33: Phạm Hoàng Phương Khanh | C33: KhanhPHP1 | D33: OFF | E33: 45937 | F33: Senior Software Tester | I33: FHM CMS | J33: HCM | K33: FHM | L33: FHM CMS | O33: Manual Test | P33: Middle
A34: 33 | B34: Hồ Bình Kha | C34: KhaHB | D34: OFF | E34: 43206 | F34: Senior Software Engineer | G34: 620 | H34: EnglishScore;PROFESSIONAL SCRUM MASTER™ I;Developing ASP.NET MVC Web Applications;Microsoft Specialist: Programming in C#;FSOFT Foreign Language Proficiency Test - TOEIC Test;Microsoft Certified: Azure Fundamentals;Microsoft Certified: Azure DevOps Engineer Expert;Microsoft Certified: DevOps Engineer Expert;Microsoft Certified: Azure Administrator Associate;TOEIC (Internal);TOEIC Listening & Reading;Microsoft Certified: Azure Solutions Architect Expert;Microsoft Certified: Identity and Access Administrator Associate;Microsoft Certified: Security, Compliance, and Identity Fundamentals;Microsoft Certified: Azure Data Engineer Associate;Microsoft Certified: Azure Data Fundamentals;Microsoft Certified: Azure Network Engineer Associate;Microsoft Certified: Azure Developer Associate | I34: FHM CMS | J34: HCM | K34: FHM | L34: FHM CMS | M34: .NET Framework | N34: Middle | O34: Azure Cloud | P34: Senior
A35: 34 | B35: Võ Huỳnh Anh Tuấn | C35: TuanVHA2 | D35: OFF | E35: 46149 | F35: Associate Business Analyst | H35: Japanese Language Proficiency Test N3 | I35: FHM JFL | J35: HCM | K35: FHM | L35: FHM JFL | O35: BA | P35: Junior
A36: 35 | B36: Nguyễn Bình Phương Ana | C36: AnaNBP | D36: OFF | E36: 46244 | F36: Manual Test | H36: ISTQB Foundation;EnglishScore;Automation Testing;API Testing | I36: IVS | J36: HCM | K36: IVS | L36: IVS | O36: Manual Test | P36: Middle
A37: 36 | B37: Phạm Thị Mỹ Nhung | C37: NhungPTM2 | D37: OFF | E37: 46237 | F37: Business Analyst | H37: EnglishScore;Business Analytics;Agile Scrum Foundation;Japanese Language Proficiency Test N3;Generative AI Practitioner Certificate | I37: FHM JFL | J37: HCM | K37: FHM | L37: FHM JFL | M37: BA | O37: BA | P37: Middle
A38: 37 | B38: Lương Hà Thi | C38: ThiLH5 | D38: OFF | E38: 46237 | F38: Business Analyst | I38: FHM JFL | J38: HCM | K38: FHM | L38: FHM JFL
A39: 38 | B39: Nguyễn Vĩ Văn | C39: VanNV5 | D39: OFF | E39: 46237 | F39: Application Developer | H39: EnglishScore;Developer Certificate;GitHub Copilot;Microsoft Certified: Azure Fundamentals | I39: FHM CMS | J39: HCM | K39: FHM | L39: FHM CMS
A40: 39 | B40: Nguyễn Văn Minh Huy | C40: HuyNVM1 | D40: OFF | E40: 46029 | F40: Intern - DEV | I40: FHM CMS | J40: HCM | K40: FHM | L40: FHM CMS | O40: Java Framework | P40: Intern
A41: 40 | B41: Lê Nguyễn Hoàng Duy | C41: DuyLNH2 | D41: OFF | E41: 46029 | F41: Intern - DEV | I41: FHM CMS | J41: HCM | K41: FHM | L41: FHM CMS | O41: Java Framework | P41: Intern
A42: 41 | B42: Phạm Thanh Thành Bảo | C42: BaoPTT2 | D42: OFF | E42: 46029 | F42: Intern - DEV | I42: FHM CMS | J42: HCM | K42: FHM | L42: FHM CMS | O42: Java Framework | P42: Intern
A43: 42 | B43: Đỗ Minh Huy | C43: HuyDM17 | D43: OFF | E43: 46029 | F43: Intern - DEV | I43: FHM CMS | J43: HCM | K43: FHM | L43: FHM CMS | O43: Java Framework | P43: Intern
A44: 43 | B44: Trần Thanh Minh | C44: MinhTT23 | D44: OFF | E44: 46089 | F44: OJT - DEV | I44: FHM CMS | J44: HCM | K44: FHM | L44: FHM CMS | O44: Java Framework | P44: OJT
A45: 44 | B45: Trần Thanh Tâm | C45: TamTT45 | D45: OFF | E45: 46089 | F45: OJT - DEV | I45: FHM CMS | J45: HCM | K45: FHM | L45: FHM CMS | O45: Java Framework | P45: OJT
A46: 45 | B46: Lê Minh Tấn | C46: TanLM6 | D46: OFF | E46: 46089 | F46: OJT - DEV | I46: FHM CMS | J46: HCM | K46: FHM | L46: FHM CMS | O46: Java Framework | P46: OJT
A47: 46 | B47: Nguyễn Bình Phương Trâm | C47: TramNBP | D47: OFF | E47: 46258 | F47: Intern - Tester | I47: FHM CMS | J47: HCM | K47: FHM | L47: FHM CMS | O47: Manual Test | P47: Intern
A48: 47 | B48: Trần Thị Kim Ngọc | C48: NgocTTK10 | D48: OFF | E48: 46258 | F48: Intern - Tester | I48: FHM CMS | J48: HCM | K48: FHM | L48: FHM CMS | O48: Manual Test | P48: Intern
A49: 48 | B49: Nguyễn Thị Thu Linh | C49: LinhNTT201 | D49: OFF | E49: 46258 | F49: Intern - Tester | I49: FHM CMS | J49: HCM | K49: FHM | L49: FHM CMS | O49: Manual Test | P49: Intern
A50: 49 | B50: Nguyễn Ngọc Minh | C50: MinhNN73 | D50: PRO | E50: 46250 | F50: Senior Software Engineer | G50: 895 | H50: IELTS 6.5;AWS Cloud Architect;Java Programming;EnglishScore;Data Structures and Algorithms;ML Practitioner Certificate;MLOps Practitioner Certificate;Core Designer Certificate;Advanced Designer Certificate;Developer Certificate;Google Data Analytics | I50: FHM CMS | J50: HCM | K50: FHM | L50: FHM CMS | M50: Java Framework | N50: Junior | O50: Java Framework | P50: Junior

Sheet Data nhân sự
A1: STT | B1: Full Name | C1: Account | D1: Contract Type | E1: Hire Date | F1: Job Title | G1: Toeic Score | H1: Certificates | I1: Department | J1: Location | K1: Parent Department | L1: Child Department | M1: Main Skill | N1: Seniority(Main) | O1: Current Skill | P1: Seniority(Current)
A2: 1 | B2: Lê Văn Thân | C2: ThanLV | D2: OFF | E2: 44958 | F2: Senior Project Manager | G2: 955 | H2: EnglishScore;Project Management Professional (PMP) | I2: FHM CMS | J2: HCM | K2: FHM | L2: FHM CMS | M2: Project Management | O2: Project Management | P2: Middle
A3: 2 | B3: Nguyễn Đông Hiếu | C3: HieuND97 | D3: OFF | E3: 46082 | F3: Project Manager | I3: FHM CMS | J3: HCM | K3: FHM | L3: FHM CMS | O3: Project Management | P3: Middle
A4: 3 | B4: Nguyễn Minh Nhựt | C4: NhutNM5 | D4: OFF | E4: 44667 | F4: Associate Project Manager | G4: 910 | H4: PROFESSIONAL SCRUM MASTER™ I;EnglishScore;PROFESSIONAL SCRUM MASTER™ II;Oracle Cloud Infrastructure 2023 Certified Foundations Associate;Oracle Cloud Data Management 2023 Certified Foundations Associate;Oracle Cloud Infrastructure 2023 AI Certified Foundations Associate;Core Designer Certificate;Advanced Designer Certificate;Oracle Cloud Infrastructure for Sunbird Ed Specialty;Aptis General - Listening Reading Speaking Writing - Level B2 | I4: FHM CMS | J4: HCM | K4: FHM | L4: FHM CMS | M4: .NET Framework | N4: Junior | O4: Project Management | P4: Junior
A5: 4 | B5: Nguyễn Hoàng Tuyên | C5: TuyenNH1 | D5: OFF | E5: 43062 | F5: Project Manager | G5: 620 | H5: C++ Standard Template Library;EnglishScore;FSOFT Foreign Language Proficiency Test - TOEIC Test;PROFESSIONAL SCRUM MASTER™ I;TOEIC (Internal);PMI Agile Certified Practitioner (PMI-ACP)® | I5: FHM CMS | J5: HCM | K5: FHM | L5: FHM CMS | M5: Project Management | O5: Project Management | P5: Junior
A6: 5 | C6: HienDT25 | D6: OFF
A7: 6 | C7: ThongNH7 | D7: OFF
A8: 7 | B8: Châu Hồng Vũ | C8: VuCH2 | D8: OFF | E8: 43983 | F8: Solution Architect | G8: 755 | H8: Google Cloud Certified Professional Cloud Developer;Core Designer Certificate;Advanced Designer Certificate;Microsoft Certified: Azure Data Engineer Associate;Microsoft Certified: Azure Database Administrator Associate;Microsoft Certified: Azure IoT Developer Specialty;Microsoft Certified: Azure Solutions Architect Expert;Microsoft Certified: DevOps Engineer Expert;Google Cloud Certified - Associate Cloud Engineer;Microsoft Certified: Azure Fundamentals;Microsoft Certified: Azure Developer Associate;FSOFT Foreign Language Proficiency Test - TOEIC Test;EnglishScore;Cloud Architect using Microsoft Azure | I8: FHM CMS | J8: HCM | K8: FHM | L8: FHM CMS | M8: .NET Framework | N8: Middle | O8: Azure Cloud | P8: Senior
A9: 8 | B9: Nguyễn Quốc Bảo | C9: BaoNQ12 | D9: OFF | E9: 43366 | F9: Associate Solution Architect | G9: 735 | H9: Microsoft Certified: Azure Solutions Architect Expert;Developing ASP.NET MVC Web Applications;Microsoft Certified: Azure Developer Associate;PROFESSIONAL SCRUM MASTER™ I;Microsoft Certified Solutions Associate: Web Applications;Cloud Native Application Architecture;Th?c s? K? thu?t Ph?n m?m (AI MSE);Google Cloud Certified: Cloud Digital Leader;Agile Development;Data Mining Foundations and Practice;Microsoft Certified: Azure DevOps Engineer Expert;Core Designer Certificate;Advanced Designer Certificate;Microsoft Specialist: Programming in C#;Microsoft Certified: Azure Fundamentals;EnglishScore;Microsoft Certified: Azure Architect Technologies;AWS Cloud Architect;FSOFT Foreign Language Proficiency Test - TOEIC Test;Associate Traditional Web Developer O11 | I9: FHM CMS | J9: HCM | K9: FHM | L9: FHM CMS | M9: Azure Cloud | O9: Azure Cloud | P9: Senior
A10: 9 | B10: Hoàng Yến Anh | C10: AnhHY | D10: OFF | E10: 44028 | F10: Senior Software Engineer | G10: 955 | H10: Advanced Designer Certificate;Core Designer Certificate;EnglishScore;FSOFT Foreign Language Proficiency Test - TOEIC Test;GitHub Copilot;Google Cloud Certified - Associate Cloud Engineer;AWS Certified Developer - Associate;Microsoft Certified: Azure AI Engineer Associate;PROFESSIONAL SCRUM MASTER™ I;PROFESSIONAL SCRUM MASTER™ II;Enrich skills to succeed - Go Platform;AWS Certified Solutions Architect - Associate;Microsoft Certified: Azure AI Fundamentals;Microsoft Certified: Azure Data Fundamentals | I10: FHM CMS | J10: HCM | K10: FHM | L10: FHM CMS | M10: Java Framework | N10: Middle | O10: Java Framework | P10: Middle
A11: 10 | B11: Võ Minh Tâm | C11: TamVM7 | D11: OFF | E11: 45084 | F11: Senior Software Engineer | G11: 550 | H11: EnglishScore | I11: FHM CMS | J11: HCM | K11: FHM | L11: FHM CMS | M11: ReactJS Framework | N11: Senior | O11: ReactJS Framework | P11: Senior
A12: 11 | B12: Phạm Duy An | C12: AnPD3 | D12: OFF | E12: 46007 | F12: Senior Software Engineer | I12: FHM CMS | J12: HCM | K12: FHM | L12: FHM CMS | M12: .NET Framework | N12: Middle | O12: Java Framework | P12: Junior
A13: 12 | C13: ToaiND2 | D13: OFF
A14: 13 | B14: Lê Hồng Như | C14: NhuLH18 | D14: OFF | E14: 45084 | F14: Senior Software Engineer | G14: 665 | H14: Cloud Developer;EnglishScore;Product Manager | I14: FHM CMS | J14: HCM | K14: FHM | L14: FHM CMS | M14: ReactJS Framework | N14: Middle | O14: Java Framework | P14: Middle
A15: 14 | B15: Nguyễn Quốc Minh | C15: MinhNQ12 | D15: OFF | E15: 44005 | F15: Senior Business Analyst | G15: 710 | H15: EnglishScore;Japanese Language Proficiency Test N2;FSOFT Foreign Language Proficiency Test - TOEIC Test;Introduction to Data Science in Python;FSOFT Customer Interview Training;Interview Skill for Interviewer | I15: FHM CMS | J15: HCM | K15: FHM | L15: FHM CMS | M15: BA | N15: Senior | O15: BA | P15: Junior
A16: 15 | B16: Nguyễn Thị Minh Ngọc | C16: NgocNTM37 | D16: OFF | E16: 46023 | F16: Associate Business Analyst | H16: Japanese Language Proficiency Test N3 | I16: FHM CMS | J16: HCM | K16: FHM | L16: FHM CMS | O16: BA | P16: Junior
A17: 16 | B17: Phan Thị Tuyết Nhi | C17: NhiPTT8 | D17: OFF | E17: 45283 | F17: Business Analyst | G17: 755 | H17: EnglishScore;Business Analytics;Developer Certificate;Generative AI Practitioner Certificate;ML Practitioner Certificate;AI in Office;Core Designer Certificate;Advanced Designer Certificate | I17: FHM CMS | J17: HCM | K17: FHM | L17: FHM CMS | M17: BA | N17: Junior | O17: BA | P17: Junior
A18: 17 | B18: Nguyễn Quang Phát | C18: PhatNQ15 | D18: OFF | E18: 45854 | F18: Business Analyst | H18: Japanese Language Proficiency Test N2 | I18: FHM CMS | J18: HCM | K18: FHM | L18: FHM CMS | O18: BA | P18: Middle
A19: 18 | B19: Nguyễn Quỳnh Như | C19: NhuNQ16 | D19: OFF | E19: 45283 | F19: Business Analyst | H19: Japanese Language Proficiency Test N2;Japanese Language Proficiency Test N3;TOEIC Listening & Reading;Professional Scrum Product Owner I;Core Designer Certificate;Business Intelligence Analytics;Programming for Data Science with Python;Introduction to Python;Microsoft Certified: Azure Fundamentals;Professional Scrum Product Owner II;Certification of Capability in Business Analysis (CCBA);Introduction to Version Control | I19: FHM CMS | J19: HCM | K19: FHM | L19: FHM CMS | M19: BA | N19: Junior | O19: BA | P19: Junior
A20: 19 | B20: Phan Thị Cẩm Tiên | C20: TienPTC10 | D20: OFF | E20: 45283 | F20: Business Analyst | H20: SQL;Japanese Language Proficiency Test N2 | I20: FHM CMS | J20: HCM | K20: FHM | L20: FHM CMS | M20: BA | N20: Junior | O20: BA | P20: Junior
A21: 20 | B21: Nguyễn Lê Duy | C21: DuyNL15 | D21: OFF | E21: 46014 | F21: Senior Software Engineer | I21: FHM CMS | J21: HCM | K21: FHM | L21: FHM CMS | O21: Java Framework | P21: Junior
A22: 21 | B22: Trần Duy Minh Mẫn | C22: ManTDM2 | D22: OFF | E22: 46149 | F22: Senior Software Engineer | I22: FHM CMS | J22: HCM | K22: FHM | L22: FHM CMS | O22: ReactJS Framework | P22: Senior
A23: 22 | B23: Giảng Hán Tài | C23: TaiGH | D23: OFF | E23: 45885 | F23: Senior Software Engineer | G23: 690 | H23: Microsoft Certified: Azure Data Fundamentals;PROFESSIONAL SCRUM MASTER™ I | I23: FHM CMS | J23: HCM | K23: FHM | L23: FHM CMS | M23: .NET Framework | O23: .NET Framework | P23: Middle
A24: 23 | C24: ViNNT7 | D24: OFF
A25: 24 | B25: Nguyễn Thị Thủy Tiên | C25: TienNTT | D25: OFF | E25: 40929 | F25: Senior Business Analyst | G25: 595 | H25: FSOFT Foreign Language Proficiency Test - TOEIC Test;ISTQB Certified Tester - Foundation Level;EnglishScore | I25: FHM CMS | J25: HCM | K25: FHM | L25: FHM CMS | M25: BA | N25: Senior | O25: DevOps & CI/CD Engineering | P25: Junior
A26: 25 | B26: Phạm Văn Sỹ | C26: SYPV1 | D26: OFF | E26: 43182 | F26: Senior Software Engineer | G26: 575 | H26: Effective Problem-Solving and Decision-Making;Developing Web Apps (OutSystems 11);EnglishScore;FSOFT Foreign Language Proficiency Test - TOEIC Test | I26: FHM CMS | J26: HCM | K26: FHM | L26: FHM CMS | M26: .NET Framework | N26: Senior | O26: DevOps & CI/CD Engineering | P26: Junior
A27: 26 | C27: KhanhTD17 | D27: OFF
A28: 27 | C28: GiangTM4 | D28: OFF
A29: 28 | C29: KhoiND3 | D29: OFF
A30: 29 | B30: Hoàng Thị Hằng | C30: HangHT50 | D30: OFF | E30: 45923 | F30: Principal Test Analyst | I30: FHM CMS | J30: HCM | K30: FHM | L30: FHM CMS | O30: Manual Test | P30: Senior
A31: 30 | C31: HoaLTM6 | D31: OFF
A32: 31 | B32: Phạm Thành Đạt | C32: DatPT102 | D32: OFF | E32: 45398 | F32: Senior Software Tester | G32: 710 | H32: EnglishScore;ISTQB Certified Tester Advanced Level - Test Analyst | I32: FHM CMS | J32: HCM | K32: FHM | L32: FHM CMS | O32: Manual Test | P32: Middle
A33: 32 | B33: Phạm Hoàng Phương Khanh | C33: KhanhPHP1 | D33: OFF | E33: 45937 | F33: Senior Software Tester | I33: FHM CMS | J33: HCM | K33: FHM | L33: FHM CMS | O33: Manual Test | P33: Middle
A34: 33 | B34: Hồ Bình Kha | C34: KhaHB | D34: OFF | E34: 43206 | F34: Senior Software Engineer | G34: 620 | H34: EnglishScore;PROFESSIONAL SCRUM MASTER™ I;Developing ASP.NET MVC Web Applications;Microsoft Specialist: Programming in C#;FSOFT Foreign Language Proficiency Test - TOEIC Test;Microsoft Certified: Azure Fundamentals;Microsoft Certified: Azure DevOps Engineer Expert;Microsoft Certified: DevOps Engineer Expert;Microsoft Certified: Azure Administrator Associate;TOEIC (Internal);TOEIC Listening & Reading;Microsoft Certified: Azure Solutions Architect Expert;Microsoft Certified: Identity and Access Administrator Associate;Microsoft Certified: Security, Compliance, and Identity Fundamentals;Microsoft Certified: Azure Data Engineer Associate;Microsoft Certified: Azure Data Fundamentals;Microsoft Certified: Azure Network Engineer Associate;Microsoft Certified: Azure Developer Associate | I34: FHM CMS | J34: HCM | K34: FHM | L34: FHM CMS | M34: .NET Framework | N34: Middle | O34: Azure Cloud | P34: Senior
A35: 34 | B35: Võ Huỳnh Anh Tuấn | C35: TuanVHA2 | D35: OFF | E35: 46149 | F35: Associate Business Analyst | H35: Japanese Language Proficiency Test N3 | I35: FHM JFL | J35: HCM | K35: FHM | L35: FHM JFL | O35: BA | P35: Junior
A36: 35 | C36: AnaNBP | D36: OFF
A37: 36 | C37: NhungPTM2 | D37: OFF
A38: 37 | B38: Lương Hà Thi | C38: ThiLH5 | D38: OFF | E38: 46029 | F38: Associate Business Analyst | H38: Japanese Language Proficiency Test N2;Japanese Language Proficiency Test N3 | I38: FHM JFL | J38: HCM | K38: FHM | L38: FHM JFL | O38: BA | P38: Junior
A39: 38 | C39: VanNV5 | D39: OFF | F39: Application Developer | M39: BE
A40: 39 | C40: HuyNVM1 | D40: OFF | F40: Intern - DEV
A41: 40 | C41: DuyLNH2 | D41: OFF | F41: Intern - DEV
A42: 41 | C42: BaoPTT2 | D42: OFF | F42: Intern - DEV
A43: 42 | C43: HuyDM17 | D43: OFF
A44: 43 | C44: MinhTT23 | D44: OFF | F44: OJT - DEV
A45: 44 | C45: TamTT45 | D45: OFF | F45: OJT - DEV
A46: 45 | C46: TanLM6 | D46: OFF | F46: OJT - DEV
A47: 46 | C47: TramNBP | D47: OFF | F47: OJT - Test
A48: 47 | C48: NgocTTK10 | D48: OFF | F48: OJT - Test
A49: 48 | C49: LinhNTT201 | D49: OFF | F49: OJT - Test
A50: 49 | B50: Nguyễn Ngọc Minh | C50: MinhNN73 | D50: PRO | E50: 46250 | F50: Senior Software Engineer | G50: 895 | H50: IELTS 6.5;AWS Cloud Architect;Java Programming;EnglishScore;Data Structures and Algorithms;ML Practitioner Certificate;MLOps Practitioner Certificate;Core Designer Certificate;Advanced Designer Certificate;Developer Certificate;Google Data Analytics | I50: FHM CMS | J50: HCM | K50: FHM | L50: FHM CMS | M50: Java Framework | N50: Junior | O50: Java Framework | P50: Junior

Sheet AWS Certified Generative AI Dev
A1: No | B1: FSU (*) | C1: BU (*) | D1: Location (*) | E1: Certification Full Name (*) | F1: Level (*) | G1: Priority (*) | H1: Provider (*) | I1: Link (*) | J1: Cost (USD) (*) | K1: Num of Certificates (*) | L1: List of employees | M1: Project code | N1: Project code | O1: Role of Employees | P1: Target Exam Month (*) | Q1: Why this Certification? (*) | R1: Value of this Certificate to FSU (*) | S1: Impact if doesnt have this cert (*) | T1: Client Name (*) | U1: Requested Support from FSA (*) | V1: FSU Contact point (*) | W1: Approved | X1: Target Exam Date (*) | Y1: AI cert
A2: 1 | B2: FHM | C2: CMS | D2: HCM | E2: AWS Certified Generative AI Dev | F2: Foundation | G2: High | H2: AWS | I2: https://aws.amazon.com/certification/certified-generative-ai-developer-professional/ | J2: 300$ | K2: 1 | L2: user004 | M2: FVD2025 | N2: =IFERROR(VLOOKUP(TRIM(M2),Mapping!$A:$B,2,FALSE),"") -> Project_004 | O2: us | P2: Sep | Q2: Nâng cao năng lực AI | R2: Chứng minh năng lực với khách hàng | U2: FSA supports Exam fee and the registration process | V2: PhuNT2 | W2: FSU sponsor | Y2: Yes
A3: 2 | B3: FHM | C3: CMS | D3: HCM | E3: AWS Certified Generative AI Dev | F3: Foundation | G3: High | H3: AWS | I3: https://aws.amazon.com/certification/certified-generative-ai-developer-professional/ | J3: 300$ | K3: 1 | L3: user007 | M3: CDX_MS | N3: =IFERROR(VLOOKUP(TRIM(M3),Mapping!$A:$B,2,FALSE),"") -> Project_007 | O3: Cloud Engineer | P3: Sep | Q3: Nâng cao năng lực AI | R3: Chứng minh năng lực với khách hàng | U3: FSA supports Exam fee and the registration process | V3: PhuNT2 | W3: FSU sponsor | Y3: Yes
A4: 3 | B4: FHM | C4: CMS | D4: HCM | E4: AWS Certified Generative AI Dev | F4: Foundation | G4: High | H4: AWS | I4: https://aws.amazon.com/certification/certified-generative-ai-developer-professional/ | J4: 300$ | K4: 1 | L4: user012 | M4: C99.CMS.AUD.IPDS 2026 | N4: =IFERROR(VLOOKUP(TRIM(M4),Mapping!$A:$B,2,FALSE),"") -> Project_011 | O4: Application Developer | P4: Sep | Q4: Nâng cao năng lực AI | R4: Chứng minh năng lực với khách hàng | U4: FSA supports Exam fee and the registration process | V4: PhuNT2 | W4: FSU sponsor | Y4: Yes
A5: 4 | B5: FHM | C5: CMS | D5: HCM | E5: AWS Certified Generative AI Dev | F5: Foundation | G5: High | H5: AWS | I5: https://aws.amazon.com/certification/certified-generative-ai-developer-professional/ | J5: 300$ | K5: 1 | L5: user016 | M5: NEWKONG2 | N5: =IFERROR(VLOOKUP(TRIM(M5),Mapping!$A:$B,2,FALSE),"") -> Project_014 | O5: Solution Architect | P5: Sep | Q5: Nâng cao năng lực AI | R5: Chứng minh năng lực với khách hàng | U5: FSA supports Exam fee and the registration process | V5: PhuNT2 | W5: FSU sponsor | Y5: Yes
A6: 5 | B6: FHM | C6: CMS | D6: HCM | E6: AWS Certified Generative AI Dev | F6: Foundation | G6: High | H6: AWS | I6: https://aws.amazon.com/certification/certified-generative-ai-developer-professional/ | J6: 300$ | K6: 1 | L6: user021 | M6: FRWMS2026 | N6: =IFERROR(VLOOKUP(TRIM(M6),Mapping!$A:$B,2,FALSE),"") -> Project_013 | O6: Data Engineer | P6: Sep | Q6: Nâng cao năng lực AI | R6: Chứng minh năng lực với khách hàng | U6: FSA supports Exam fee and the registration process | V6: PhuNT2 | W6: FSU sponsor | Y6: Yes
A7: 6 | B7: FHM | C7: CMS | D7: HCM | E7: AWS Certified Generative AI Dev | F7: Foundation | G7: High | H7: AWS | I7: https://aws.amazon.com/certification/certified-generative-ai-developer-professional/ | J7: 300$ | K7: 1 | L7: user024 | M7: C99.I5.WM.AA 2026 | N7: =IFERROR(VLOOKUP(TRIM(M7),Mapping!$A:$B,2,FALSE),"") -> Project_016 | O7: DevOps Engineer | P7: Sep | Q7: Nâng cao năng lực AI | R7: Chứng minh năng lực với khách hàng | U7: FSA supports Exam fee and the registration process | V7: PhuNT2 | W7: FSU sponsor | Y7: Yes
A8: 7 | B8: FHM | C8: CMS | D8: HCM | E8: AWS Certified Generative AI Dev | F8: Foundation | G8: High | H8: AWS | I8: https://aws.amazon.com/certification/certified-generative-ai-developer-professional/ | J8: 300$ | K8: 1 | L8: user029 | M8: FR.SF.2025 | N8: =IFERROR(VLOOKUP(TRIM(M8),Mapping!$A:$B,2,FALSE),"") -> Project_021 | O8: Manual Tester | P8: Sep | Q8: Nâng cao năng lực AI | R8: Chứng minh năng lực với khách hàng | U8: FSA supports Exam fee and the registration process | V8: PhuNT2 | W8: FSU sponsor | Y8: Yes
A9: 8 | B9: FHM | C9: CMS | D9: HCM | E9: AWS Certified Generative AI Dev | F9: Foundation | G9: High | H9: AWS | I9: https://aws.amazon.com/certification/certified-generative-ai-developer-professional/ | J9: 300$ | K9: 1 | L9: user034 | M9: NEWKONG2 | N9: =IFERROR(VLOOKUP(TRIM(M9),Mapping!$A:$B,2,FALSE),"") -> Project_014 | O9: Software Developer | P9: Sep | Q9: Nâng cao năng lực AI | R9: Chứng minh năng lực với khách hàng | U9: FSA supports Exam fee and the registration process | V9: PhuNT2 | W9: FSU sponsor | Y9: Yes
A10: 9 | B10: FHM | C10: CMS | D10: HCM | E10: AWS Certified Generative AI Dev | F10: Foundation | G10: High | H10: AWS | I10: https://aws.amazon.com/certification/certified-generative-ai-developer-professional/ | J10: 300$ | K10: 1 | L10: user038 | M10: FRDLO | N10: =IFERROR(VLOOKUP(TRIM(M10),Mapping!$A:$B,2,FALSE),"") -> Project_001 | O10: Software Developer | P10: Sep | Q10: Nâng cao năng lực AI | R10: Chứng minh năng lực với khách hàng | U10: FSA supports Exam fee and the registration process | V10: PhuNT2 | W10: FSU sponsor | Y10: Yes
A11: 10 | B11: FHM | C11: CMS | D11: HCM | E11: AWS Certified Generative AI Dev | F11: Foundation | G11: High | H11: AWS | I11: https://aws.amazon.com/certification/certified-generative-ai-developer-professional/ | J11: 300$ | K11: 1 | L11: user043 | M11: FVD2025 | N11: =IFERROR(VLOOKUP(TRIM(M11),Mapping!$A:$B,2,FALSE),"") -> Project_004 | O11: Software Developer | P11: Sep | Q11: Nâng cao năng lực AI | R11: Chứng minh năng lực với khách hàng | U11: FSA supports Exam fee and the registration process | V11: PhuNT2 | W11: FSU sponsor | Y11: Yes
A12: 11 | B12: FHM | C12: CMS | D12: HCM | E12: AWS Certified Generative AI Dev | F12: Foundation | G12: High | H12: AWS | I12: https://aws.amazon.com/certification/certified-generative-ai-developer-professional/ | J12: 300$ | K12: 1 | L12: user046 | M12: FRWMS2026 | N12: =IFERROR(VLOOKUP(TRIM(M12),Mapping!$A:$B,2,FALSE),"") -> Project_013 | O12: Software Developer | P12: Sep | Q12: Nâng cao năng lực AI | R12: Chứng minh năng lực với khách hàng | U12: FSA supports Exam fee and the registration process | V12: PhuNT2 | W12: FSU sponsor | Y12: Yes
A13: 12 | B13: FHM | C13: CMS | D13: HCM | E13: AWS Certified Generative AI Dev | F13: Foundation | G13: High | H13: AWS | I13: https://aws.amazon.com/certification/certified-generative-ai-developer-professional/ | J13: 300$ | K13: 1 | L13: user050 | M13: OPNEXT88 | N13: =IFERROR(VLOOKUP(TRIM(M13),Mapping!$A:$B,2,FALSE),"") -> Project_020 | O13: BA | P13: Sep | Q13: Nâng cao năng lực AI | R13: Chứng minh năng lực với khách hàng | U13: FSA supports Exam fee and the registration process | V13: PhuNT2 | W13: FSU sponsor | Y13: Yes
... A77: 76 | B77: FHM | C77: CMS | D77: HCM | E77: AWS Certified Generative AI Dev | F77: Foundation | G77: High | H77: AWS | I77: https://aws.amazon.com/certification/certified-generative-ai-developer-professional/ | J77: 300$ | K77: 1 | L77: user306 | M77: C99.I5.WM.AA 2026 | N77: =IFERROR(VLOOKUP(TRIM(M77),Mapping!$A:$B,2,FALSE),"") -> Project_016 | O77: Project Manager | P77: Oct | Q77: Nâng cao năng lực AI | R77: Chứng minh năng lực với khách hàng | U77: FSA supports Exam fee and the registration process | V77: PhuNT2 | W77: FSU sponsor | Y77: Yes

Sheet AI Claude Foundati Certificate 
A1: No | B1: FSU (*) | C1: BU (*) | D1: Location (*) | E1: Certification Full Name (*) | F1: Level (*) | G1: Priority (*) | H1: Provider (*) | I1: Link (*) | J1: Cost (USD) (*) | K1: Num of Certificates (*) | L1: List of employees | M1: Project code | N1: Project code | O1: Role of Employees | P1: Target Exam Month (*) | Q1: Why this Certification? (*) | R1: Value of this Certificate to FSU (*) | S1: Impact if doesnt have this cert (*) | T1: Client Name (*) | U1: Requested Support from FSA (*) | V1: FSU Contact point (*) | W1: Approved | X1: Target Exam Date (*) | Y1: AI cert
A2: 1 | B2: FHM | C2: CMS | D2: HCM | E2: Claude Certified Architect - Foundations (CCA-F) | F2: Foundation | G2: High | H2: Anthropic | I2: Claude Certified Architect — Foundations (CCA-F) | J2: 125$ | K2: 1 | L2: user014 | M2: C99.I5.LOG 2026 | N2: =IFERROR(VLOOKUP(TRIM(M2),Mapping!$A:$B,2,FALSE),"") -> Project_012 | O2: Software Developer | P2: Sep | Q2: Nâng cao năng lực AI | R2: Chứng minh năng lực với khách hàng | U2: FSA supports Exam fee and the registration process | V2: PhuNT2 | W2: FSU sponsor | Y2: Yes
A3: 2 | B3: FHM | C3: CMS | D3: HCM | E3: Claude Certified Architect - Foundations (CCA-F) | F3: Foundation | G3: High | H3: Anthropic | I3: Claude Certified Architect — Foundations (CCA-F) | J3: 125$ | K3: 1 | L3: user027 | M3: J_POLARIS | N3: =IFERROR(VLOOKUP(TRIM(M3),Mapping!$A:$B,2,FALSE),"") -> Project_019 | O3: Software Developer | P3: Sep | Q3: Nâng cao năng lực AI | R3: Chứng minh năng lực với khách hàng | U3: FSA supports Exam fee and the registration process | V3: PhuNT2 | W3: FSU sponsor | Y3: Yes
A4: 3 | B4: FHM | C4: CMS | D4: HCM | E4: Claude Certified Architect - Foundations (CCA-F) | F4: Foundation | G4: High | H4: Anthropic | I4: Claude Certified Architect — Foundations (CCA-F) | J4: 125$ | K4: 1 | L4: user033 | M4: FRWMS2026 | N4: =IFERROR(VLOOKUP(TRIM(M4),Mapping!$A:$B,2,FALSE),"") -> Project_013 | O4: Tester | P4: Sep | Q4: Nâng cao năng lực AI | R4: Chứng minh năng lực với khách hàng | U4: FSA supports Exam fee and the registration process | V4: PhuNT2 | W4: FSU sponsor | Y4: Yes
A5: 4 | B5: FHM | C5: CMS | D5: HCM | E5: Claude Certified Architect - Foundations (CCA-F) | F5: Foundation | G5: High | H5: Anthropic | I5: Claude Certified Architect — Foundations (CCA-F) | J5: 125$ | K5: 1 | L5: user041 | M5: SBR_Buhin26 | N5: =IFERROR(VLOOKUP(TRIM(M5),Mapping!$A:$B,2,FALSE),"") -> Project_005 | O5: Application Developer | P5: Sep | Q5: Nâng cao năng lực AI | R5: Chứng minh năng lực với khách hàng | U5: FSA supports Exam fee and the registration process | V5: PhuNT2 | W5: FSU sponsor | Y5: Yes
A6: 5 | B6: FHM | C6: CMS | D6: HCM | E6: Claude Certified Architect - Foundations (CCA-F) | F6: Foundation | G6: High | H6: Anthropic | I6: Claude Certified Architect — Foundations (CCA-F) | J6: 125$ | K6: 1 | L6: user048 | M6: MetalAlpha | N6: =IFERROR(VLOOKUP(TRIM(M6),Mapping!$A:$B,2,FALSE),"") -> Project_018 | O6: Software Developer | P6: Sep | Q6: Nâng cao năng lực AI | R6: Chứng minh năng lực với khách hàng | U6: FSA supports Exam fee and the registration process | V6: PhuNT2 | W6: FSU sponsor | Y6: Yes
A7: 6 | B7: FHM | C7: CMS | D7: HCM | E7: Claude Certified Architect - Foundations (CCA-F) | F7: Foundation | G7: High | H7: Anthropic | I7: Claude Certified Architect — Foundations (CCA-F) | J7: 125$ | K7: 1 | L7: user052 | M7: SAIN | N7: =IFERROR(VLOOKUP(TRIM(M7),Mapping!$A:$B,2,FALSE),"") -> Project_026 | O7: Software Developer | P7: Sep | Q7: Nâng cao năng lực AI | R7: Chứng minh năng lực với khách hàng | U7: FSA supports Exam fee and the registration process | V7: PhuNT2 | W7: FSU sponsor | Y7: Yes
A8: 7 | B8: FHM | C8: CMS | D8: HCM | E8: Claude Certified Architect - Foundations (CCA-F) | F8: Foundation | G8: High | H8: Anthropic | I8: Claude Certified Architect — Foundations (CCA-F) | J8: 125$ | K8: 1 | L8: user057 | M8: Portal_EU01 | N8: =IFERROR(VLOOKUP(TRIM(M8),Mapping!$A:$B,2,FALSE),"") -> Project_002 | O8: Application Developer | P8: Sep | Q8: Nâng cao năng lực AI | R8: Chứng minh năng lực với khách hàng | U8: FSA supports Exam fee and the registration process | V8: PhuNT2 | W8: FSU sponsor | Y8: Yes
A9: 8 | B9: FHM | C9: CMS | D9: HCM | E9: Claude Certified Architect - Foundations (CCA-F) | F9: Foundation | G9: High | H9: Anthropic | I9: Claude Certified Architect — Foundations (CCA-F) | J9: 125$ | K9: 1 | L9: user063 | M9: STL_AG_02 | N9: =IFERROR(VLOOKUP(TRIM(M9),Mapping!$A:$B,2,FALSE),"") -> Project_009 | O9: Software Developer | P9: Sep | Q9: Nâng cao năng lực AI | R9: Chứng minh năng lực với khách hàng | U9: FSA supports Exam fee and the registration process | V9: PhuNT2 | W9: FSU sponsor | Y9: Yes
A10: 9 | B10: FHM | C10: CMS | D10: HCM | E10: Claude Certified Architect - Foundations (CCA-F) | F10: Foundation | G10: High | H10: Anthropic | I10: Claude Certified Architect — Foundations (CCA-F) | J10: 125$ | K10: 1 | L10: user068 | M10: FRSPL26 | N10: =IFERROR(VLOOKUP(TRIM(M10),Mapping!$A:$B,2,FALSE),"") -> Project_027 | O10: Tester | P10: Sep | Q10: Nâng cao năng lực AI | R10: Chứng minh năng lực với khách hàng | U10: FSA supports Exam fee and the registration process | V10: PhuNT2 | W10: FSU sponsor | Y10: Yes
A11: 10 | B11: FHM | C11: CMS | D11: HCM | E11: Claude Certified Architect - Foundations (CCA-F) | F11: Foundation | G11: High | H11: Anthropic | I11: Claude Certified Architect — Foundations (CCA-F) | J11: 125$ | K11: 1 | L11: user074 | M11: CL555.DE.PrintLab 2026 | N11: =IFERROR(VLOOKUP(TRIM(M11),Mapping!$A:$B,2,FALSE),"") -> Project_032 | O11: Application Developer | P11: Sep | Q11: Nâng cao năng lực AI | R11: Chứng minh năng lực với khách hàng | U11: FSA supports Exam fee and the registration process | V11: PhuNT2 | W11: FSU sponsor | Y11: Yes
A12: 11 | B12: FHM | C12: CMS | D12: HCM | E12: Claude Certified Architect - Foundations (CCA-F) | F12: Foundation | G12: High | H12: Anthropic | I12: Claude Certified Architect — Foundations (CCA-F) | J12: 125$ | K12: 1 | L12: user079 | M12: JOCAR_Replace | N12: =IFERROR(VLOOKUP(TRIM(M12),Mapping!$A:$B,2,FALSE),"") -> Project_003 | O12: Business Analyst | P12: Sep | Q12: Nâng cao năng lực AI | R12: Chứng minh năng lực với khách hàng | U12: FSA supports Exam fee and the registration process | V12: PhuNT2 | W12: FSU sponsor | Y12: Yes
A13: 12 | B13: FHM | C13: CMS | D13: HCM | E13: Claude Certified Architect - Foundations (CCA-F) | F13: Foundation | G13: High | H13: Anthropic | I13: Claude Certified Architect — Foundations (CCA-F) | J13: 125$ | K13: 1 | L13: user083 | M13: FRSME26 | N13: =IFERROR(VLOOKUP(TRIM(M13),Mapping!$A:$B,2,FALSE),"") -> Project_033 | O13: Tester | P13: Sep | Q13: Nâng cao năng lực AI | R13: Chứng minh năng lực với khách hàng | U13: FSA supports Exam fee and the registration process | V13: PhuNT2 | W13: FSU sponsor | Y13: Yes
... A93: 92 | B93: FHM | C93: CMS | D93: HCM | E93: Claude Certified Architect - Foundations (CCA-F) | F93: Foundation | G93: High | H93: Anthropic | I93: Claude Certified Architect — Foundations (CCA-F) | J93: 125$ | K93: 1 | L93: user117 | M93: FVD2025 | N93: =IFERROR(VLOOKUP(TRIM(M93),Mapping!$A:$B,2,FALSE),"") -> Project_004 | O93: Application Developer | P93: Sep | Q93: Nâng cao năng lực AI | R93: Chứng minh năng lực với khách hàng | U93: FSA supports Exam fee and the registration process | V93: PhuNT2 | W93: FSU sponsor | Y93: Yes

Sheet  GitHub Copilot Certification (
A1: No | B1: FSU (*) | C1: BU (*) | D1: Location (*) | E1: Certification Full Name (*) | F1: Level (*) | G1: Priority (*) | H1: Provider (*) | I1: Link (*) | J1: Cost (USD) (*) | K1: Num of Certificates (*) | L1: List of employees | M1: pro | N1: Project code | O1: Role of Employees | P1: Target Exam Month (*) | Q1: Why this Certification? (*) | R1: Value of this Certificate to FSU (*) | S1: Impact if doesnt have this cert (*) | T1: Client Name (*) | U1: Requested Support from FSA (*) | V1: FSU Contact point (*) | W1: Approved | X1: Target Exam Date (*) | Y1: AI cert
A2: 1 | B2: FHM | C2: CMS | D2: HCM | E2: GitHub Copilot Certification (GH-300) | F2: Foundation | G2: High | H2: GitHub | I2: https://learn.microsoft.com/en-us/credentials/certifications/github-copilot/ | J2: 99$ | K2: 1 | L2: user001 | M2: FRDLO | N2: =IFERROR(VLOOKUP(TRIM(M2),Mapping!$A:$B,2,FALSE),"") -> Project_001 | O2: Software Developer | P2: Oct | Q2: Nâng cao năng lực AI và Copilot | R2: Thúc đẩy ứng dụng AI trong dự án | U2: FSA supports Exam fee and the registration process | V2: PhuNT2 | W2: FSU sponsor | Y2: Yes
A3: 2 | B3: FHM | C3: CMS | D3: HCM | E3: GitHub Copilot Certification (GH-300) | F3: Foundation | G3: High | H3: GitHub | I3: https://learn.microsoft.com/en-us/credentials/certifications/github-copilot/ | J3: 99$ | K3: 1 | L3: user002 | M3: Portal_EU01 | N3: =IFERROR(VLOOKUP(TRIM(M3),Mapping!$A:$B,2,FALSE),"") -> Project_002 | O3: Software Developer | P3: Oct | Q3: Nâng cao năng lực AI và Copilot | R3: Thúc đẩy ứng dụng AI trong dự án | U3: FSA supports Exam fee and the registration process | V3: PhuNT2 | W3: FSU sponsor | Y3: Yes
A4: 3 | B4: FHM | C4: CMS | D4: HCM | E4: GitHub Copilot Certification (GH-300) | F4: Foundation | G4: High | H4: GitHub | I4: https://learn.microsoft.com/en-us/credentials/certifications/github-copilot/ | J4: 99$ | K4: 1 | L4: user003 | M4: JOCAR_Replace | N4: =IFERROR(VLOOKUP(TRIM(M4),Mapping!$A:$B,2,FALSE),"") -> Project_003 | O4: Business Analyst | P4: Nov | Q4: Nâng cao năng lực AI và Copilot | R4: Thúc đẩy ứng dụng AI trong dự án | U4: FSA supports Exam fee and the registration process | V4: PhuNT2 | W4: FSU sponsor | Y4: Yes
A5: 4 | B5: FHM | C5: CMS | D5: HCM | E5: GitHub Copilot Certification (GH-300) | F5: Foundation | G5: High | H5: GitHub | I5: https://learn.microsoft.com/en-us/credentials/certifications/github-copilot/ | J5: 99$ | K5: 1 | L5: user004 | M5: FVD2025 | N5: =IFERROR(VLOOKUP(TRIM(M5),Mapping!$A:$B,2,FALSE),"") -> Project_004 | O5: Software Developer | P5: Dec | Q5: Nâng cao năng lực AI và Copilot | R5: Thúc đẩy ứng dụng AI trong dự án | U5: FSA supports Exam fee and the registration process | V5: PhuNT2 | W5: FSU sponsor | Y5: Yes
A6: 5 | B6: FHM | C6: CMS | D6: HCM | E6: GitHub Copilot Certification (GH-300) | F6: Foundation | G6: High | H6: GitHub | I6: https://learn.microsoft.com/en-us/credentials/certifications/github-copilot/ | J6: 99$ | K6: 1 | L6: user005 | M6: SBR_Buhin26 | N6: =IFERROR(VLOOKUP(TRIM(M6),Mapping!$A:$B,2,FALSE),"") -> Project_005 | O6: Project Manager | P6: Dec | Q6: Nâng cao năng lực AI và Copilot | R6: Thúc đẩy ứng dụng AI trong dự án | U6: FSA supports Exam fee and the registration process | V6: PhuNT2 | W6: FSU sponsor | Y6: Yes
A7: 6 | B7: FHM | C7: CMS | D7: HCM | E7: GitHub Copilot Certification (GH-300) | F7: Foundation | G7: High | H7: GitHub | I7: https://learn.microsoft.com/en-us/credentials/certifications/github-copilot/ | J7: 99$ | K7: 1 | L7: user007 | M7: CDX_MS | N7: =IFERROR(VLOOKUP(TRIM(M7),Mapping!$A:$B,2,FALSE),"") -> Project_007 | O7: Cloud Engineer | P7: Nov | Q7: Nâng cao năng lực AI và Copilot | R7: Thúc đẩy ứng dụng AI trong dự án | U7: FSA supports Exam fee and the registration process | V7: PhuNT2 | W7: FSU sponsor | Y7: Yes
A8: 7 | B8: FHM | C8: CMS | D8: HCM | E8: GitHub Copilot Certification (GH-300) | F8: Foundation | G8: High | H8: GitHub | I8: https://learn.microsoft.com/en-us/credentials/certifications/github-copilot/ | J8: 99$ | K8: 1 | L8: user008 | M8: SF_Link_2026 | N8: =IFERROR(VLOOKUP(TRIM(M8),Mapping!$A:$B,2,FALSE),"") -> Project_008 | O8: Project Manager | P8: Oct | Q8: Nâng cao năng lực AI và Copilot | R8: Thúc đẩy ứng dụng AI trong dự án | U8: FSA supports Exam fee and the registration process | V8: PhuNT2 | W8: FSU sponsor | Y8: Yes
A9: 8 | B9: FHM | C9: CMS | D9: HCM | E9: GitHub Copilot Certification (GH-300) | F9: Foundation | G9: High | H9: GitHub | I9: https://learn.microsoft.com/en-us/credentials/certifications/github-copilot/ | J9: 99$ | K9: 1 | L9: user009 | M9: JOCAR_Replace | N9: =IFERROR(VLOOKUP(TRIM(M9),Mapping!$A:$B,2,FALSE),"") -> Project_003 | O9: Tester | P9: Oct | Q9: Nâng cao năng lực AI và Copilot | R9: Thúc đẩy ứng dụng AI trong dự án | U9: FSA supports Exam fee and the registration process | V9: PhuNT2 | W9: FSU sponsor | Y9: Yes
A10: 9 | B10: FHM | C10: CMS | D10: HCM | E10: GitHub Copilot Certification (GH-300) | F10: Foundation | G10: High | H10: GitHub | I10: https://learn.microsoft.com/en-us/credentials/certifications/github-copilot/ | J10: 99$ | K10: 1 | L10: user010 | M10: STL_AG_02 | N10: =IFERROR(VLOOKUP(TRIM(M10),Mapping!$A:$B,2,FALSE),"") -> Project_009 | O10: Application Developer | P10: Dec | Q10: Nâng cao năng lực AI và Copilot | R10: Thúc đẩy ứng dụng AI trong dự án | U10: FSA supports Exam fee and the registration process | V10: PhuNT2 | W10: FSU sponsor | Y10: Yes
A11: 10 | B11: FHM | C11: CMS | D11: HCM | E11: GitHub Copilot Certification (GH-300) | F11: Foundation | G11: High | H11: GitHub | I11: https://learn.microsoft.com/en-us/credentials/certifications/github-copilot/ | J11: 99$ | K11: 1 | L11: user011 | M11: SIQAX3 | N11: =IFERROR(VLOOKUP(TRIM(M11),Mapping!$A:$B,2,FALSE),"") -> Project_010 | O11: Application Developer | P11: Sep | Q11: Nâng cao năng lực AI và Copilot | R11: Thúc đẩy ứng dụng AI trong dự án | U11: FSA supports Exam fee and the registration process | V11: PhuNT2 | W11: FSU sponsor | Y11: Yes
A12: 11 | B12: FHM | C12: CMS | D12: HCM | E12: GitHub Copilot Certification (GH-300) | F12: Foundation | G12: High | H12: GitHub | I12: https://learn.microsoft.com/en-us/credentials/certifications/github-copilot/ | J12: 99$ | K12: 1 | L12: user012 | M12: C99.CMS.AUD.IPDS 2026 | N12: =IFERROR(VLOOKUP(TRIM(M12),Mapping!$A:$B,2,FALSE),"") -> Project_011 | O12: Application Developer | P12: Sep | Q12: Nâng cao năng lực AI và Copilot | R12: Thúc đẩy ứng dụng AI trong dự án | U12: FSA supports Exam fee and the registration process | V12: PhuNT2 | W12: FSU sponsor | Y12: Yes
A13: 12 | B13: FHM | C13: CMS | D13: HCM | E13: GitHub Copilot Certification (GH-300) | F13: Foundation | G13: High | H13: GitHub | I13: https://learn.microsoft.com/en-us/credentials/certifications/github-copilot/ | J13: 99$ | K13: 1 | L13: user013 | M13: FVD2025 | N13: =IFERROR(VLOOKUP(TRIM(M13),Mapping!$A:$B,2,FALSE),"") -> Project_004 | O13: Software Developer | P13: Sep | Q13: Nâng cao năng lực AI và Copilot | R13: Thúc đẩy ứng dụng AI trong dự án | U13: FSA supports Exam fee and the registration process | V13: PhuNT2 | W13: FSU sponsor | Y13: Yes
... A101: 100 | B101: FHM | C101: CMS | D101: HCM | E101: GitHub Copilot Certification (GH-300) | F101: Foundation | G101: High | H101: GitHub | I101: https://learn.microsoft.com/en-us/credentials/certifications/github-copilot/ | J101: 99$ | K101: 1 | L101: user107 | M101: FRWMS2026 | N101: =IFERROR(VLOOKUP(TRIM(M101),Mapping!$A:$B,2,FALSE),"") -> Project_013 | O101: SE | P101: Sep | Q101: Nâng cao năng lực AI và Copilot | R101: Thúc đẩy ứng dụng AI trong dự án | U101: FSA supports Exam fee and the registration process | V101: PhuNT2 | W101: FSU sponsor | Y101: Yes

Sheet training_data
A1: employee_id | B1: registration_status | C1: attendance_rate | D1: session_joined | E1: session_missed | F1: assignment_submission_rate | G1: quiz_score | H1: certificate_earned | I1: feedback_score | J1: late_submission_count | K1: reminder_count | L1: days_to_register | M1: activity_score | N1: engagement_score | O1: completion_status
A2: 1 | B2: Registered | C2: 88 | D2: 18 | E2: 2 | F2: 87 | G2: 89 | H2: Yes | I2: 3.8 | J2: 0 | K2: 2 | L2: 1 | M2: 88 | N2: 90 | O2: Completed
A3: 2 | B3: Not Registered | C3: 18 | D3: 4 | E3: 16 | F3: 20 | G3: 24 | H3: No | I3: 1.9 | J3: 3 | K3: 15 | L3: 15 | M3: 20 | N3: 5 | O3: In Progress
A4: 3 | B4: Registered | C4: 86 | D4: 17 | E4: 3 | F4: 81 | G4: 76 | H4: Yes | I4: 3.9 | J4: 0 | K4: 4 | L4: 5 | M4: 81 | N4: 78 | O4: Completed
A5: 4 | B5: Registered | C5: 80 | D5: 16 | E5: 4 | F5: 76 | G5: 86 | H5: Yes | I5: 4.1 | J5: 1 | K5: 4 | L5: 2 | M5: 80 | N5: 81 | O5: Completed
A6: 5 | B6: Registered | C6: 91 | D6: 18 | E6: 2 | F6: 82 | G6: 85 | H6: Yes | I6: 4.4 | J6: 1 | K6: 4 | L6: 0 | M6: 86 | N6: 80 | O6: Completed
A7: 6 | B7: Registered | C7: 66 | D7: 13 | E7: 7 | F7: 66 | G7: 61 | H7: Yes | I7: 4.6 | J7: 5 | K7: 8 | L7: 1 | M7: 64 | N7: 53 | O7: In Progress
A8: 7 | B8: Registered | C8: 70 | D8: 14 | E8: 6 | F8: 71 | G8: 64 | H8: No | I8: 4.6 | J8: 6 | K8: 4 | L8: 3 | M8: 68 | N8: 59 | O8: Dropped
A9: 8 | B9: Registered | C9: 79 | D9: 16 | E9: 4 | F9: 89 | G9: 89 | H9: Yes | I9: 4.1 | J9: 1 | K9: 0 | L9: 2 | M9: 85 | N9: 82 | O9: Completed
A10: 9 | B10: Not Registered | C10: 32 | D10: 6 | E10: 14 | F10: 35 | G10: 37 | H10: No | I10: 2.5 | J10: 9 | K10: 6 | L10: 15 | M10: 34 | N10: 28 | O10: In Progress
A11: 10 | B11: Registered | C11: 64 | D11: 13 | E11: 7 | F11: 70 | G11: 75 | H11: No | I11: 4.7 | J11: 5 | K11: 10 | L11: 2 | M11: 69 | N11: 64 | O11: Dropped
A12: 11 | B12: Registered | C12: 57 | D12: 11 | E12: 9 | F12: 53 | G12: 52 | H12: No | I12: 3.4 | J12: 4 | K12: 8 | L12: 5 | M12: 54 | N12: 42 | O12: In Progress
A13: 12 | B13: Registered | C13: 51 | D13: 10 | E13: 10 | F13: 59 | G13: 57 | H13: No | I13: 3.1 | J13: 10 | K13: 15 | L13: 1 | M13: 55 | N13: 42 | O13: In Progress
... A50: 49 | B50: Not Registered | C50: 44 | D50: 9 | E50: 11 | F50: 48 | G50: 52 | H50: No | I50: 2.4 | J50: 5 | K50: 6 | L50: 30 | M50: 47 | N50: 52 | O50: In Progress

Sheet FHM.CMS
A1: STT | B1: Full Name | C1: Account | D1: Project code | E1: Contract Type | F1: Hire Date | G1: Job Title | H1: Toeic Score | I1: Certificates | J1: Department | K1: Location | L1: Parent Department | M1: Child Department | N1: Main Skill | O1: Seniority(Main) | P1: Current Skill | Q1: Seniority(Current) | R1: Allocation Status | S1: Note | T1: Action | U1: Action From | V1: Action To | W1: Job Rank | X1: Allocation Sep-2026 | Y1: Allocation Oct-2026 | Z1: Allocation Nov-2026 | AA1: Effort Aug-2026 | AB1: Effort Sep-2026 | AC1: Effort Oct-2026 | AD1: Effort Nov-2026 | AE1: Busy rate(%) | AF1: Customer Code | AG1: Project Dept | AH1: Project Code2 | AI1: Project Type | AJ1: 17-Aug-26 | AK1: 24-Aug-26 | AL1: 31-Aug-26 | AM1: 07-Sep-26 | AN1: 14-Sep-26 | AO1: 21-Sep-26
A2: 1 | B2: Chu Chiêu Dủ An | C2: AnCCD | D2: FRDLO | E2: OFF | F2: 45398 | G2: Senior Software Engineer | H2: 895 | I2: EnglishScore;Developer Certificate;Advanced Designer Certificate;ML Practitioner Certificate;MLOps Practitioner Certificate;Core Designer Certificate;GitHub Copilot;Data Engineering with Microsoft Azure;TOEIC Listening & Reading | J2: FHM CMS | K2: HCM | L2: FHM | M2: FHM CMS | N2: Java Framework | O2: Middle | P2: Java Framework | Q2: Senior | R2: Allocated | S2: Nghỉ mát: 11-Aug-2026 ~ 11-Aug-2026 | W2: DEVE03 | X2: Allocated | Y2: Allocated | Z2: Allocated | AA2: 1 | AB2: 1 | AC2: 1 | AD2: 1 | AE2: 100 | AF2: FR | AG2: FSO.HCM.FHM.CMS | AH2: FMCS3 | AI2: External | AJ2: 40 | AK2: 40 | AL2: 40 | AM2: 40 | AN2: 40 | AO2: 40
A3: 2 | B3: Bùi Tuấn Anh | C3: AnhBT27 | D3: Portal_EU01 | E3: OFF | F3: 44896 | G3: Software Engineer | H3: 690 | I3: Java Web Developer;EnglishScore | J3: FHM CMS | K3: HCM | L3: FHM | M3: FHM CMS | N3: Java Framework | O3: Junior | P3: IT Service | Q3: Junior | R3: Allocated | S3: Nghỉ phép: 10-Aug-2026 ~ 10-Aug-2026 | W3: DEVE02 | X3: Allocated | Y3: Allocated | Z3: Allocated | AA3: 1 | AB3: 1 | AC3: 1 | AD3: 1 | AE3: 100 | AF3: FR | AG3: FSO.HCM.FHM.CMS | AH3: FRDLO | AI3: External | AJ3: 40 | AK3: 40 | AL3: 40 | AM3: 40 | AN3: 40 | AO3: 40
A4: 3 | B4: Huỳnh Ngọc Minh Anh | C4: AnhHNM | D4: JOCAR_Replace | E4: OFF | F4: 44902 | G4: Business Analyst | H4: 945 | I4: EnglishScore;PROFESSIONAL SCRUM MASTER™ I | J4: FHM CMS | K4: HCM | L4: FHM | M4: FHM CMS | N4: BA | O4: Junior | P4: BA | Q4: Middle | R4: Allocated | W4: BANE02 | X4: Allocated | Y4: Allocated | Z4: Allocated | AA4: 1 | AB4: 1 | AC4: 1 | AD4: 1 | AE4: 100 | AF4: Casio-Europe | AG4: FSO.HCM.FHM.CMS | AH4: Portal_EU01 | AI4: External | AJ4: 40 | AK4: 40 | AL4: 40 | AM4: 40 | AN4: 40 | AO4: 40
A5: 4 | B5: Hoàng Yến Anh | C5: AnhHY | D5: FVD2025 | E5: OFF | F5: 44028 | G5: Senior Software Engineer | H5: 955 | I5: Advanced Designer Certificate;Core Designer Certificate;EnglishScore;FSOFT Foreign Language Proficiency Test - TOEIC Test;GitHub Copilot;Google Cloud Certified - Associate Cloud Engineer;AWS Certified Developer - Associate;Microsoft Certified: Azure AI Engineer Associate;PROFESSIONAL SCRUM MASTER™ I;PROFESSIONAL SCRUM MASTER™ II;Enrich skills to succeed - Go Platform;AWS Certified Solutions Architect - Associate;Microsoft Certified: Azure AI Fundamentals;Microsoft Certified: Azure Data Fundamentals | J5: FHM CMS | K5: HCM | L5: FHM | M5: FHM CMS | N5: Java Framework | O5: Middle | P5: Java Framework | Q5: Middle | R5: Allocated | W5: DEVE03 | X5: Allocated | Y5: Allocated | Z5: Allocated | AA5: 1 | AB5: 1 | AC5: 1 | AD5: 1 | AE5: 100 | AF5: JJCM | AG5: FSO.HCM.FHM.CMS | AH5: JOCAR_Replace | AI5: External | AJ5: 40 | AK5: 40 | AL5: 40 | AM5: 40 | AN5: 40 | AO5: 40
A6: 5 | B6: Nguyễn Hà Kim Anh | C6: AnhNHK2 | D6: SBR_Buhin26 | E6: OFF | F6: 46082 | G6: Associate Project Manager | I6: IELTS 6.5 | J6: FHM CMS | K6: HCM | L6: FHM | M6: FHM CMS | N6: Project Management | O6: Junior | P6: Project Management | Q6: Junior | R6: Allocated | S6: Nghỉ phép: 19-Aug-2026 ~ 19-Aug-2026 | W6: SPMA01 | X6: Allocated | Y6: Allocated | Z6: Allocated | AA6: 1 | AB6: 1 | AC6: 1 | AD6: 1 | AE6: 100 | AF6: FR | AG6: FSO.HCM.FHM.CMS | AH6: FVD2025 | AI6: External | AJ6: 40 | AK6: 40 | AL6: 40 | AM6: 40 | AN6: 40 | AO6: 40
A7: 6 | B7: Nông Minh Anh | C7: AnhNM64 | D7: SDX_Y3 | E7: OFF | F7: 45673 | G7: Software Engineer | I7: TOEIC Listening & Reading;Japanese Language Proficiency Test N3;GitHub Copilot | J7: FHM CMS | K7: HCM | L7: FHM | M7: FHM CMS | N7: Java Framework | O7: Junior | P7: Java Framework | Q7: Middle | R7: Allocated | W7: DEVE02 | X7: Allocated | Y7: Allocated | Z7: Allocated | AA7: 1 | AB7: 1 | AC7: 1 | AD7: 1 | AE7: 100 | AF7: SBR | AG7: FSO.HCM.FHM.CMS | AH7: SBR_Buhin26 | AI7: External | AJ7: 40 | AK7: 40 | AL7: 40 | AM7: 40 | AN7: 40 | AO7: 40
A8: 7 | B8: Phạm Lê Thế Anh | C8: AnhPLT3 | D8: CDX_MS | E8: OFF | F8: 44667 | G8: Software Engineer | H8: 640 | I8: EnglishScore;Microsoft Certified: Azure Developer Associate;Software Engineer Intern;Advanced Designer Certificate;IELTS 5.5;Microsoft Certified: Azure Fundamentals | J8: FHM CMS | K8: HCM | L8: FHM | M8: FHM CMS | N8: AWS Cloud | P8: DevOps & CI/CD Engineering | Q8: Middle | R8: Allocated | W8: DEVE02 | X8: Allocated | Y8: Allocated | Z8: Not-yet-Planned | AA8: 1 | AB8: 1 | AC8: 1 | AD8: 0 | AE8: 100 | AF8: Sodexo | AG8: FSO.HCM.FHM.CMS | AH8: SDX_Y3 | AI8: External | AJ8: 40 | AK8: 40 | AL8: 40 | AM8: 40 | AN8: 40 | AO8: 40
A9: 8 | B9: Trần Quỳnh Anh | C9: AnhTQ69 | D9: SF_Link_2026 | E9: OFF | F9: 46060 | G9: Associate Project Manager | J9: FHM JFL | K9: HCM | L9: FHM | M9: FHM JFL | N9: Project Management | O9: Junior | P9: Project Management | Q9: Junior | R9: Allocated | S9: Nghỉ phép: 12-Aug-2026 ~ 13-Aug-2026 | W9: SPMA01 | X9: Allocated | Y9: Allocated | Z9: Allocated | AA9: 1 | AB9: 1 | AC9: 1 | AD9: 1 | AE9: 100 | AF9: SonyGS | AG9: FSO.HCM.FHM.CMS | AH9: CDX_MS | AI9: External | AJ9: 40 | AK9: 40 | AL9: 40 | AM9: 40 | AN9: 40 | AO9: 40
A10: 9 | B10: Nguyễn Thị Duy An | C10: AnNTD4 | D10: JOCAR_Replace | E10: OFF | F10: 45200 | G10: Senior Software Tester | H10: 550 | I10: EnglishScore;Model Context Protocol: Advanced Topics;Introduction to Agent Skills;Cluade Code in Action;Introduction to Model Context Protocol;Claude Code 101;Claude with the Anthropic API;Introduction to Claude Cowork;Introduction to subagents;ISTQB Certified Tester - Foundation Level;Agile Software Developer;Oracle Cloud Infrastructure 2023 Certified Foundations Associate;Oracle Cloud Infrastructure for Sunbird Ed Specialty | J10: FHM CMS | K10: HCM | L10: FHM | M10: FHM CMS | N10: Manual Test | O10: Senior | P10: Manual Test | Q10: Junior | R10: Allocated | W10: TEST04 | X10: Allocated | Y10: Allocated | Z10: Allocated | AA10: 1 | AB10: 1 | AC10: 1 | AD10: 1 | AE10: 100 | AF10: SBR | AG10: FSO.HCM.FHM.CMS | AH10: SF_Link_2026 | AI10: External | AJ10: 40 | AK10: 40 | AL10: 40 | AM10: 40 | AN10: 40 | AO10: 40
A11: 10 | B11: Phạm Duy An | C11: AnPD3 | D11: STL_AG_02 | E11: OFF | F11: 46007 | G11: Senior Software Engineer | J11: FHM CMS | K11: HCM | L11: FHM | M11: FHM CMS | N11: .NET Framework | O11: Middle | P11: Java Framework | Q11: Junior | R11: Allocated | W11: DEVE03 | X11: Allocated | Y11: Allocated | Z11: Allocated | AA11: 1 | AB11: 1 | AC11: 1 | AD11: 1 | AE11: 100 | AF11: JJCM | AG11: FSO.HCM.FHM.CMS | AH11: JOCAR_Replace | AI11: External | AJ11: 40 | AK11: 40 | AL11: 40 | AM11: 40 | AN11: 40 | AO11: 40
A12: 11 | B12: Phan Đình Thiên Ân | C12: AnPDT1 | D12: SIQAX3 | E12: OFF | F12: 45114 | G12: Software Engineer | H12: 895 | I12: GitHub Copilot;EnglishScore;Japanese Language Proficiency Test N5;TOEIC Listening & Reading;JUNIOR ANGULAR DEVELOPER;PROFESSIONAL SCRUM MASTER™ I;Oracle Cloud Infrastructure for Sunbird Ed Specialty;Oracle Cloud Infrastructure 2023 AI Certified Foundations Associate;Core Designer Certificate;Advanced Designer Certificate;Microsoft Certified: Azure Fundamentals;NVIDIA Getting Started with AI on Jetson Nano;Oracle Cloud Data Management 2023 Certified Foundations Associate;Oracle Cloud Infrastructure 2023 Certified Foundations Associate;Microsoft Certified: Azure AI Engineer Associate | J12: FHM CMS | K12: HCM | L12: FHM | M12: FHM CMS | N12: ReactJS Framework | P12: ReactJS Framework | Q12: Junior | R12: Allocated | W12: DEVE02 | X12: Allocated | Y12: Allocated | Z12: Allocated | AA12: 1 | AB12: 1 | AC12: 1 | AD12: 1 | AE12: 0 | AF12: ANA | AG12: FSO.HCM.FHM.CMS | AH12: STL_AG_02 | AI12: External | AJ12: 40 | AK12: 40 | AL12: 40 | AM12: 40 | AN12: 40 | AO12: 40
A13: 12 | B13: Phạm Trường An | C13: AnPT9 | D13: C99.CMS.AUD.IPDS 2026 | E13: OFF | F13: 44400 | G13: Senior Software Engineer | H13: 690 | I13: Cloud Developer using Microsoft Azure;EnglishScore;Core Designer Certificate;Advanced Designer Certificate;Cloud Architect using Microsoft Azure;IELTS 5.0;Microsoft Certified: Azure Developer Associate;Microsoft Certified: Azure Fundamentals;Microsoft Certified: Azure Data Fundamentals | J13: FHM CMS | K13: HCM | L13: FHM | M13: FHM CMS | N13: .NET Framework | O13: Middle | P13: Azure Cloud | Q13: Senior | R13: Allocated | S13: Nghỉ phép: 13-Aug-2026 ~ 13-Aug-2026 Nghỉ phép: 22-Aug-2026 ~ 22-Aug-2026 | W13: DEVE03 | X13: Allocated | Y13: Allocated | Z13: Allocated | AA13: 1 | AB13: 1 | AC13: 1 | AD13: 1 | AE13: 100 | AF13: SmartGroup | AG13: FSO.HCM.FHM.CMS | AH13: SIQAX3 | AI13: External | AJ13: 40 | AK13: 40 | AL13: 40 | AM13: 40 | AN13: 40 | AO13: 40
A14: 13 | B14: Trần Võ Hoàng Trọng Ân | C14: AnTVHT | D14: FVD2025 | E14: OFF | F14: 45754 | G14: Software Engineer | I14: GitHub Copilot | J14: FHM CMS | K14: HCM | L14: FHM | M14: FHM CMS | N14: Java Framework | O14: Junior | P14: Java Framework | Q14: Middle | R14: Allocated | S14: Nghỉ kết hôn: 30-Jul-2026 ~ 03-Aug-2026 Nghỉ phép: 14-Aug-2026 ~ 14-Aug-2026 Nghỉ phép: 13-Aug-2026 ~ 13-Aug-2026 | W14: DEVE02 | X14: Allocated | Y14: Allocated | Z14: Allocated | AA14: 1 | AB14: 1 | AC14: 1 | AD14: 1 | AE14: 95.238095 | AF14: COX-AM | AG14: FSO.HCM.FHM.AKAT | AH14: C99.CMS.AUD.IPDS 2026 | AI14: External | AJ14: 40 | AK14: 40 | AL14: 40 | AM14: 40 | AN14: 40 | AO14: 40
A15: 14 | B15: Võ Gia Ân | C15: AnVG1 | D15: C99.I5.LOG 2026 | E15: OFF | F15: 46060 | G15: Associate Software Engineer | I15: IELTS 6.5 | J15: FHM CMS | K15: HCM | L15: FHM | M15: FHM CMS | N15: Java Framework | O15: Junior | P15: Java Framework | Q15: Junior | R15: Allocated | W15: DEVE01 | X15: Allocated | Y15: Allocated | Z15: Allocated | AA15: 1 | AB15: 1 | AC15: 1 | AD15: 1 | AE15: 100 | AF15: FR | AG15: FSO.HCM.FHM.CMS | AH15: FVD2025 | AI15: External | AJ15: 40 | AK15: 40 | AL15: 40 | AM15: 40 | AN15: 40 | AO15: 40
A16: 15 | B16: Lương Xuân Bách | C16: BachLX5 | D16: FRWMS2026 | E16: OFF | F16: 45419 | G16: Associate Software Engineer | H16: 895 | I16: EnglishScore | J16: FHM CMS | K16: HCM | L16: FHM | M16: FHM CMS | N16: Java Framework | O16: Junior | P16: .NET Framework | Q16: Middle | R16: Allocated | W16: DEVE01 | X16: Allocated | Y16: Allocated | Z16: Allocated | AA16: 1 | AB16: 1 | AC16: 1 | AD16: 1 | AE16: 100 | AF16: COX-AM | AG16: FSO.HCM.FHM.AKAT | AH16: C99.I5.LOG 2026 | AI16: External | AJ16: 40 | AK16: 40 | AL16: 40 | AM16: 40 | AN16: 40 | AO16: 40
A17: 16 | B17: Phạm Công Bằng | C17: BangPC | D17: NEWKONG2 | E17: OFF | F17: 45480 | G17: Senior Solution Architect | H17: 800 | I17: TOEFL ITP;EnglishScore | J17: FHM CMS | K17: HCM | L17: FHM | M17: FHM CMS | N17: Software Solution Architecture | P17: Java Framework | Q17: Senior | R17: Allocated | S17: Nghỉ phép: 17-Aug-2026 ~ 17-Aug-2026 Nghỉ phép: 14-Aug-2026 ~ 14-Aug-2026 | W17: SARE03 | X17: Allocated | Y17: Allocated | Z17: Not-yet-Planned | AA17: 1 | AB17: 1 | AC17: 1 | AD17: 0 | AE17: 100 | AF17: FR | AG17: FSO.HCM.FHM.CMS | AH17: FRWMS2026 | AI17: External | AJ17: 40 | AK17: 40 | AL17: 40 | AM17: 40 | AN17: 40 | AO17: 40
A18: 17 | B18: Đinh Thái Bảo | C18: BaoDT3 | D18: JOCAR_Replace | E18: OFF | F18: 44013 | G18: Associate Project Manager | H18: 800 | I18: PROFESSIONAL SCRUM MASTER™ I;Advanced Designer Certificate;MLOps Practitioner Certificate;Core Designer Certificate;ML Practitioner Certificate;Developer Certificate;Oracle Cloud Data Management 2023 Certified Foundations Associate;SQL (Advanced);Google Analytics Certification;Oracle Cloud Infrastructure 2023 AI Certified Foundations Associate;ISTQB Certified Tester Advanced Level - Test Analyst;ISTQB Certified Tester - Foundation Level;FSOFT Foreign Language Proficiency Test - TOEIC Test;Product Manager;EnglishScore | J18: FHM CMS | K18: HCM | L18: FHM | M18: FHM CMS | N18: Manual Test | O18: Senior | P18: Manual Test | Q18: Junior | R18: Allocated | S18: Nghỉ phép: 03-Aug-2026 ~ 03-Aug-2026 Nghỉ phép: 10-Aug-2026 ~ 10-Aug-2026 Nghỉ mát: 26-Aug-2026 ~ 28-Aug-2026 Nghỉ phép: 18-Aug-2026 ~ 18-Aug-2026 | W18: SPMA01 | X18: Allocated | Y18: Allocated | Z18: Allocated | AA18: 1 | AB18: 1 | AC18: 1 | AD18: 1 | AE18: 100 | AF18: FXSS | AG18: FSO.HCM.FHM.CMS | AH18: NEWKONG2 | AI18: External | AJ18: 40 | AK18: 40 | AL18: 40 | AM18: 40 | AN18: 40 | AO18: 40
A19: 18 | B19: Nguyễn Quốc Bảo | C19: BaoNQ12 | D19: SCU100 | E19: OFF | F19: 43366 | G19: Associate Solution Architect | H19: 735 | I19: Microsoft Certified: Azure Solutions Architect Expert;Developing ASP.NET MVC Web Applications;Microsoft Certified: Azure Developer Associate;PROFESSIONAL SCRUM MASTER™ I;Microsoft Certified Solutions Associate: Web Applications;Cloud Native Application Architecture;Th?c s? K? thu?t Ph?n m?m (AI MSE);Google Cloud Certified: Cloud Digital Leader;Agile Development;Data Mining Foundations and Practice;Microsoft Certified: Azure DevOps Engineer Expert;Core Designer Certificate;Advanced Designer Certificate;Microsoft Specialist: Programming in C#;Microsoft Certified: Azure Fundamentals;EnglishScore;Microsoft Certified: Azure Architect Technologies;AWS Cloud Architect;FSOFT Foreign Language Proficiency Test - TOEIC Test;Associate Traditional Web Developer O11 | J19: FHM CMS | K19: HCM | L19: FHM | M19: FHM CMS | N19: Azure Cloud | P19: Azure Cloud | Q19: Senior | R19: Allocated | S19: Nghỉ mát: 31-Jul-2026 ~ 04-Aug-2026 | W19: SARE01 | X19: Allocated | Y19: Allocated | Z19: Allocated | AA19: 1 | AB19: 1 | AC19: 1 | AD19: 1 | AE19: 90.47619 | AF19: JJCM | AG19: FSO.HCM.FHM.CMS | AH19: JOCAR_Replace | AI19: External | AJ19: 40 | AK19: 40 | AL19: 40 | AM19: 40 | AN19: 40 | AO19: 40
A20: 19 | B20: Phạm Hoàng Bảo | C20: BaoPH6 | D20: C99.I5.LOG 2026 | E20: OFF | F20: 45154 | G20: Senior Software Engineer | H20: 690 | I20: AWS Certified Solutions Architect - Associate;Oracle Cloud Infrastructure for Sunbird Ed Specialty;Advanced Designer Certificate;Core Designer Certificate;EnglishScore | J20: FHM CMS | K20: HCM | L20: FHM | M20: FHM CMS | N20: .NET Framework | O20: Middle | P20: .NET Framework | Q20: Middle | R20: Allocated | S20: Nghỉ phép: 14-Aug-2026 ~ 14-Aug-2026 | W20: DEVE03 | X20: Allocated | Y20: Allocated | Z20: Allocated | AA20: 1 | AB20: 1 | AC20: 1 | AD20: 1 | AE20: 100 | AF20: ISCUBE | AG20: FSO.HCM.FHM.CMS | AH20: SCU100 | AI20: External | AJ20: 40 | AK20: 40 | AL20: 40 | AM20: 40 | AN20: 40 | AO20: 40
A21: 20 | B21: Phạm Trần Huy Bảo | C21: BaoPTH | D21: STL_AG_02 | E21: OFF | F21: 44850 | G21: Software Engineer | H21: 950 | I21: Vietnamese Standardized Test of English Proficiency (VSTEP) - Level 3/CEFR B1;Microsoft Certified: Azure Fundamentals;Full Stack Web Developer;Core Designer Certificate;Advanced Designer Certificate;EnglishScore;Java Fundamentals;Advanced Java Programming Techniques;Intermediate JavaScript;Front End Web Developer | J21: FHM CMS | K21: HCM | L21: FHM | M21: FHM CMS | N21: .NET Framework | O21: Junior | P21: .NET Framework | Q21: Junior | R21: Allocated | W21: DEVE02 | X21: Allocated | Y21: Allocated | Z21: Allocated | AA21: 1 | AB21: 1 | AC21: 1 | AD21: 1 | AE21: 100 | AF21: COX-AM | AG21: FSO.HCM.FHM.AKAT | AH21: C99.I5.LOG 2026 | AI21: External | AJ21: 40 | AK21: 40 | AL21: 40 | AM21: 40 | AN21: 40 | AO21: 40
A22: 21 | B22: Trần Gia Bảo | C22: BaoTG22 | D22: FRWMS2026 | E22: OFF | F22: 45642 | G22: Associate Data Engineer | I22: SQL (Basic) | J22: FHM CMS | K22: HCM | L22: FHM | M22: FHM CMS | N22: DE | O22: Junior | P22: DE | Q22: Middle | R22: Allocated | W22: DSEN01 | X22: Allocated | Y22: Allocated | Z22: Allocated | AA22: 1 | AB22: 1 | AC22: 1 | AD22: 1 | AE22: 0 | AF22: ANA | AG22: FSO.HCM.FHM.CMS | AH22: STL_AG_02 | AI22: External | AJ22: 40 | AK22: 40 | AL22: 40 | AM22: 40 | AN22: 40 | AO22: 40
A23: 22 | B23: Trần Hoài Bảo | C23: BaoTH1 | D23: STL_AG_02 | E23: OFF | F23: 44568 | G23: Senior Software Engineer | H23: 640 | I23: Cloud Architect using Microsoft Azure;EnglishScore;AWS Cloud Architect;Microsoft Certified: Azure Solutions Architect Expert;Microsoft Certified: Azure Administrator Associate;Professional Scrum Product Owner I;Cloud Developer;Cloud Developer using Microsoft Azure;NVIDIA Getting Started with AI on Jetson Nano;Oracle Cloud Data Management 2023 Certified Foundations Associate;Oracle Cloud Infrastructure 2023 Certified Foundations Associate;PROFESSIONAL SCRUM MASTER™ I;Microsoft Certified: Azure Developer Associate;Microsoft Certified: Azure Fundamentals;Microsoft Certified: Azure Data Fundamentals | J23: FHM CMS | K23: HCM | L23: FHM | M23: FHM CMS | N23: Azure Cloud | P23: Azure Cloud | Q23: Middle | R23: Allocated | W23: DEVE03 | X23: Not-yet-Planned | Y23: Not-yet-Planned | Z23: Not-yet-Planned | AA23: 0.48 | AB23: 0 | AC23: 0 | AD23: 0 | AE23: 47.619048 | AF23: FR | AG23: FSO.HCM.FHM.CMS | AH23: FRWMS2026 | AI23: External | AJ23: 0 | AK23: 0 | AL23: 0 | AM23: 0 | AN23: 0 | AO23: 0
A24: 23 | B24: Trần Lê Chi Bảo | C24: BaoTLC2 | D24: SBR_Buhin26 | E24: OFF | F24: 46113 | G24: Associate Business Analyst | I24: Japanese Language Proficiency Test N2 | J24: FHM CMS | K24: HCM | L24: FHM | M24: FHM CMS | N24: BA | O24: Junior | P24: Project Management | Q24: Junior | R24: Allocated | S24: Nghỉ phép: 14-Aug-2026 ~ 14-Aug-2026 | W24: BANE01 | X24: Allocated | Y24: Allocated | Z24: Allocated | AA24: 1 | AB24: 1 | AC24: 1 | AD24: 1 | AE24: 0 | AF24: ANA | AG24: FSO.HCM.FHM.CMS | AH24: STL_AG_02 | AI24: External | AJ24: 40 | AK24: 40 | AL24: 40 | AM24: 40 | AN24: 40 | AO24: 40
A25: 24 | B25: Văn Quốc Bảo | C25: BaoVQ6 | D25: C99.I5.WM.AA 2026 | E25: OFF | F25: 44621 | G25: Senior Software Engineer | H25: 880 | I25: EnglishScore;Generative AI Practitioner Certificate;Professional Scrum Developer I;Oracle Cloud Infrastructure for Sunbird Ed Specialty;Core Designer Certificate;Advanced Designer Certificate;NVIDIA Getting Started with AI on Jetson Nano;PROFESSIONAL SCRUM MASTER™ I | J25: FHM CMS | K25: HCM | L25: FHM | M25: FHM CMS | N25: DevOps & CI/CD Engineering | P25: DevOps & CI/CD Engineering | Q25: Middle | R25: Allocated | W25: DEVE03 | X25: Allocated | Y25: Allocated | Z25: Allocated | AA25: 1 | AB25: 1 | AC25: 1 | AD25: 1 | AE25: 100 | AF25: SBR | AG25: FSO.HCM.FHM.CMS | AH25: SBR_Buhin26 | AI25: External | AJ25: 40 | AK25: 40 | AL25: 40 | AM25: 40 | AN25: 40 | AO25: 40
A26: 25 | B26: Lê Thái Bình | C26: BinhLT62 | D26: FMCS3 | E26: OFF | F26: 46014 | G26: Senior Software Engineer | I26: Microsoft Certified: Azure AI Apps and Agents Developer Associate;Microsoft Certified: Agentic AI Business Solutions Architect;Vietnamese Standardized Test of English Proficiency (VSTEP) - Level 4/CEFR B2;GitHub Copilot | J26: FHM CMS | K26: HCM | L26: FHM | M26: FHM CMS | N26: Java Framework | O26: Middle | P26: Java Framework | Q26: Senior | R26: Allocated | S26: Nghỉ phép: 06-Aug-2026 ~ 06-Aug-2026 Nghỉ phép: 14-Aug-2026 ~ 14-Aug-2026 Nghỉ phép: 20-Aug-2026 ~ 20-Aug-2026 | W26: DEVE03 | X26: Allocated | Y26: Allocated | Z26: Allocated | AA26: 1 | AB26: 1 | AC26: 1 | AD26: 1 | AE26: 100 | AF26: COX-AM | AG26: FSO.HCM.FHM.AKAT | AH26: C99.I5.WM.AA 2026 | AI26: External | AJ26: 40 | AK26: 40 | AL26: 40 | AM26: 40 | AN26: 40 | AO26: 40
A27: 26 | B27: Thạch Thanh Bình | C27: BinhTT12 | D27: MetalAlpha | E27: OFF | F27: 43974 | G27: Senior Software Engineer | H27: 800 | I27: Advanced Designer Certificate;Core Designer Certificate;Agile with Atlassian Jira;Communication in the 21st Century Workplace;Project Management: The Basics for Success;Microsoft Certified: Azure Fundamentals;FSOFT Foreign Language Proficiency Test - TOEIC Test;EnglishScore | J27: FHM CMS | K27: HCM | L27: FHM | M27: FHM CMS | N27: Java Framework | O27: Middle | P27: Java Framework | Q27: Senior | R27: Allocated | W27: DEVE03 | X27: Allocated | Y27: Allocated | Z27: Allocated | AA27: 1 | AB27: 1 | AC27: 1 | AD27: 1 | AE27: 100 | AF27: FR | AG27: FSO.HCM.FHM.CMS | AH27: FMCS3 | AI27: External | AJ27: 40 | AK27: 40 | AL27: 40 | AM27: 40 | AN27: 40 | AO27: 40
A28: 27 | B28: Y In Byă | C28: ByaYI3 | D28: J_POLARIS | E28: OFF | F28: 45123 | G28: Senior Software Engineer | H28: 665 | I28: EnglishScore;Advanced Designer Certificate | J28: FHM CMS | K28: HCM | L28: FHM | M28: FHM CMS | N28: Java Framework | O28: Middle | P28: Java Framework | Q28: Junior | R28: Allocated | W28: DEVE03 | X28: Allocated | Y28: Allocated | Z28: Allocated | AA28: 1 | AB28: 1 | AC28: 1 | AD28: 1 | AE28: 100 | AF28: MOC | AG28: FSO.HCM.FHM.CMS | AH28: MetalAlpha | AI28: External | AJ28: 40 | AK28: 40 | AL28: 40 | AM28: 40 | AN28: 40 | AO28: 40
A29: 28 | B29: Đỗ Minh Chánh | C29: ChanhDM | D29: OPNEXT88 | E29: OFF | F29: 45496 | G29: Associate Solution Architect | I29: Claude Certified Architect - Foundations;Japanese Language Proficiency Test N2;TOEIC Listening & Reading;AWS Certified Developer - Associate;AWS Certified Solutions Architect - Associate;Salesforce Certified Associate | J29: FHM JFL | K29: HCM | L29: FHM | M29: FHM JFL | N29: AWS Cloud | P29: AWS Cloud | Q29: Middle | R29: Allocated | W29: SARE01 | X29: Allocated | Y29: Allocated | Z29: Allocated | AA29: 1 | AB29: 1 | AC29: 1 | AD29: 0.7 | AE29: 100 | AF29: JIT | AG29: FSO.HCM.FHM.JPG | AH29: J_POLARIS | AI29: External | AJ29: 40 | AK29: 40 | AL29: 40 | AM29: 40 | AN29: 40 | AO29: 40
A30: 29 | B30: Nguyễn Ngọc Bảo Chân | C30: ChanNNB | D30: FR.SF.2025 | E30: OFF | F30: 44005 | G30: Senior Software Tester | H30: 865 | I30: Data Analysis and Visualization with Microsoft Power BI;EnglishScore;FSOFT Foreign Language Proficiency Test - TOEIC Test;Business Intelligence Analytics;Tiếng Trung;A Life of Happiness and Fulfillment;AI for Everyone | J30: FHM CMS | K30: HCM | L30: FHM | M30: FHM CMS | N30: Manual Test | O30: Senior | P30: Manual Test | Q30: Middle | R30: Allocated | S30: Nghỉ mát: 06-Aug-2026 ~ 10-Aug-2026 Nghỉ phép: 21-Aug-2026 ~ 21-Aug-2026 | W30: TEST04 | X30: Not-yet-Planned | Y30: Not-yet-Planned | Z30: Not-yet-Planned | AA30: 0.81 | AB30: 0 | AC30: 0 | AD30: 0 | AE30: 85.714286 | AF30: OddsPark | AG30: FSO.HCM.FHM.JPG | AH30: OPNEXT88 | AI30: External | AJ30: 40 | AK30: 16 | AL30: 0 | AM30: 0 | AN30: 0 | AO30: 0
A31: 30 | B31: Lê Thị Xuân Chi | C31: ChiLTX | D31: FR VDMC Operation 2026 | E31: OFF | F31: 45246 | G31: Senior Software Tester | H31: 640 | I31: Oracle Cloud Infrastructure for Sunbird Ed Specialty;Advanced Designer Certificate;EnglishScore | J31: FHM CMS | K31: HCM | L31: FHM | M31: FHM CMS | N31: Manual Test | O31: Senior | P31: Low-Code & No-Code Development | Q31: Middle | R31: Allocated | W31: TEST04 | X31: Allocated | Y31: Allocated | Z31: Not-yet-Planned | AA31: 1 | AB31: 1 | AC31: 1 | AD31: 0 | AE31: 100 | AF31: FR | AG31: FSO.HCM.FHM.CMS | AH31: FR.SF.2025 | AI31: External | AJ31: 40 | AK31: 40 | AL31: 40 | AM31: 40 | AN31: 40 | AO31: 40
A32: 31 | B32: Đặng Ngọc Chính | C32: ChinhDN | D32: SF_Link_2026 | E32: OFF | F32: 44485 | G32: Project Manager | H32: 755 | I32: PMI Agile Certified Practitioner (PMI-ACP)®;Project Management Professional (PMP);Phần cứng máy tính;Excel Skills for Business: Essentials;Developer Certificate;MLOps Practitioner Certificate;Core Designer Certificate;ML Practitioner Certificate;Advanced Designer Certificate;Google Project Management;Project Initiation: Starting a Successful Project;Project Planning: Putting It All Together;Foundations of Project Management;Project Execution: Running the Project;EnglishScore;FSOFT Foreign Language Proficiency Test - TOEIC Test | J32: FHM CMS | K32: HCM | L32: FHM | M32: FHM CMS | N32: Project Management | P32: IT Service | Q32: Senior | R32: Allocated | W32: SPMA02 | X32: Allocated | Y32: Allocated | Z32: Allocated | AA32: 0.78 | AB32: 0.78 | AC32: 0.75 | AD32: 0.75 | AE32: 78.125 | AF32: FR | AG32: FSO.HCM.FHM.CMS | AH32: FR VDMC Operation 2026 | AI32: External | AJ32: 31.25 | AK32: 31.25 | AL32: 31.25 | AM32: 31.25 | AN32: 31.25 | AO32: 31.25
A33: 32 | B33: Nguyễn Nhân Chính | C33: ChinhNN7 | D33: SBR_Buhin26 | E33: OFF | F33: 45992 | G33: Associate Software Engineer | I33: GitHub Copilot | J33: FHM CMS | K33: HCM | L33: FHM | M33: FHM CMS | N33: .NET Framework | O33: Junior | P33: Java Framework | Q33: Junior | R33: Allocated | W33: DEVE01 | X33: Allocated | Y33: Allocated | Z33: Allocated | AA33: 1 | AB33: 1 | AC33: 1 | AD33: 1 | AE33: 100 | AF33: SBR | AG33: FSO.HCM.FHM.CMS | AH33: SF_Link_2026 | AI33: External | AJ33: 40 | AK33: 40 | AL33: 40 | AM33: 40 | AN33: 40 | AO33: 40
A34: 33 | B34: Lê Thị Chung | C34: ChungLT3 | D34: FRWMS2026 | E34: OFF | F34: 44697 | G34: Senior Software Tester | H34: 575 | I34: EnglishScore;ISTQB Certified Tester Advanced Level - Test Analyst;Oracle Cloud Infrastructure for Sunbird Ed Specialty;Advanced Designer Certificate;Core Designer Certificate;Certified Tester ISTQB Foundation Level | J34: FHM CMS | K34: HCM | L34: FHM | M34: FHM CMS | N34: Manual Test | O34: Junior | P34: Manual Test | Q34: Middle | R34: Allocated | S34: Nghỉ mát: 06-Aug-2026 ~ 10-Aug-2026 Nghỉ phép: 11-Aug-2026 ~ 11-Aug-2026 | W34: TEST03 | X34: Allocated | Y34: Allocated | Z34: Allocated | AA34: 1 | AB34: 1 | AC34: 1 | AD34: 1 | AE34: 100 | AF34: SBR | AG34: FSO.HCM.FHM.CMS | AH34: SBR_Buhin26 | AI34: External | AJ34: 40 | AK34: 40 | AL34: 40 | AM34: 40 | AN34: 40 | AO34: 40
A35: 34 | B35: Đặng Hồ Tuấn Cường | C35: CuongDHT1 | D35: NEWKONG2 | E35: OFF | F35: 46180 | G35: Associate Software Engineer | J35: FHM CMS | K35: HCM | L35: FHM | M35: FHM CMS | P35: Java Framework | Q35: Junior | R35: Allocated | W35: DEVE01 | X35: Allocated | Y35: Allocated | Z35: Not-yet-Planned | AA35: 1 | AB35: 1 | AC35: 1 | AD35: 0 | AE35: 100 | AF35: FR | AG35: FSO.HCM.FHM.CMS | AH35: FRWMS2026 | AI35: External | AJ35: 40 | AK35: 40 | AL35: 40 | AM35: 40 | AN35: 40 | AO35: 40
A36: 35 | B36: Dương Mạnh Cường | C36: CuongDM5 | D36: C99.I5.WM.AA 2026 | E36: OFF | F36: 41928 | G36: Software Development Head | H36: 960 | I36: Japanese Language Proficiency Test N2;EnglishScore;FSOFT Foreign Language Proficiency Test - TOEIC Test;Project Management Professional (PMP);AWS Certified Solutions Architect - Associate;Microsoft Certified Solutions Associate: Web Applications;Microsoft Specialist: Programming in HTML5 with JavaScript and CSS3;Predix Certified Developer;Self Awareness and the Effective Leader;Leadership Communication for Maximum Impact: Storytelling;Advanced Designer Certificate;Microsoft Certified Professional;Microsoft Certified Solutions Developer: Web Applications;PROFESSIONAL SCRUM MASTER™ I;Microsoft Certified: Azure Architect Technologies;Microsoft Certified: Azure Solutions Architect Expert | J36: FHM CMS | K36: HCM | L36: FHM | M36: FHM CMS | N36: Software Solution Architecture | P36: Software Solution Architecture | Q36: Senior | R36: Overhead | S36: Nghỉ phép: 07-Aug-2026 ~ 07-Aug-2026 | W36: SGMT01 | X36: Overhead | Y36: Overhead | Z36: Overhead | AA36: 0 | AB36: 0 | AC36: 0 | AD36: 0 | AE36: 0 | AF36: FXSS | AG36: FSO.HCM.FHM.CMS | AH36: NEWKONG2 | AI36: External | AJ36: 0 | AK36: 0 | AL36: 0 | AM36: 0 | AN36: 0 | AO36: 0
A37: 36 | B37: Nguyễn Kiên Cường | C37: CuongNK21 | D37: C99.I5.SANS 2026 | E37: OFF | F37: 45338 | G37: Software Engineer | H37: 865 | I37: Advanced Designer Certificate;Core Designer Certificate;NVIDIA Getting Started with AI on Jetson Nano;MLOps Practitioner Certificate;TOEIC Listening & Reading;Developer Certificate;ML Practitioner Certificate;EnglishScore;AWS Certified Solutions Architect - Associate;GitHub Copilot | J37: FHM CMS | K37: HCM | L37: FHM | M37: FHM CMS | N37: NodeJs Server Implementation | O37: Junior | P37: Java Framework | Q37: Middle | R37: Allocated | W37: DEVE02 | X37: Allocated | Y37: Allocated | Z37: Allocated | AA37: 1 | AB37: 1 | AC37: 1 | AD37: 1 | AE37: 100 | AF37: COX-AM | AG37: FSO.HCM.FHM.AKAT | AH37: C99.I5.WM.AA 2026 | AI37: External | AJ37: 40 | AK37: 40 | AL37: 40 | AM37: 40 | AN37: 40 | AO37: 40
A38: 37 | B38: Nguyễn Công Đắc | C38: DacNC | D38: FMCS3 | E38: OFF | F38: 44348 | G38: Senior Software Engineer | H38: 755 | I38: GitHub Copilot;EnglishScore;Cloud Developer;AWS Cloud Architect;PROFESSIONAL SCRUM MASTER™ I | J38: FHM CMS | K38: HCM | L38: FHM | M38: FHM CMS | N38: CAD Engineering | P38: IT Service | Q38: Expert | R38: Allocated | S38: Nghỉ phép: 22-Aug-2026 ~ 22-Aug-2026 | W38: DEVE04 | X38: Allocated | Y38: Allocated | Z38: Allocated | AA38: 1 | AB38: 1 | AC38: 1 | AD38: 1 | AE38: 100 | AF38: COX-AM | AG38: FSO.HCM.FHM.AKAT | AH38: C99.I5.SANS 2026 | AI38: External | AJ38: 40 | AK38: 40 | AL38: 40 | AM38: 40 | AN38: 40 | AO38: 40
A39: 38 | B39: Mai Thanh Đại | C39: DaiMT | D39: FRDLO | E39: OFF | F39: 45192 | G39: Solution Architect | H39: 785 | I39: Google Cloud Certified Generative AI Leader;EnglishScore;AWS Certified Solutions Architect - Associate | J39: FHM CMS | K39: HCM | L39: FHM | M39: FHM CMS | N39: Java Framework | O39: Senior | P39: AWS Cloud | Q39: Senior | R39: Allocated | S39: Nghỉ phép: 07-Aug-2026 ~ 07-Aug-2026 Nghỉ mát: 13-Aug-2026 ~ 13-Aug-2026 | W39: SARE02 | X39: Allocated | Y39: Allocated | Z39: Allocated | AA39: 1 | AB39: 1 | AC39: 1 | AD39: 1 | AE39: 100 | AF39: FR | AG39: FSO.HCM.FHM.CMS | AH39: FMCS3 | AI39: Hien | AJ39: 40 | AK39: 40 | AL39: 40 | AM39: 40 | AN39: 40 | AO39: 40
A40: 39 | B40: Ngô Minh Đại | C40: DaiNM | D40: SBR_Buhin26 | E40: OFF | F40: 46135 | G40: Senior Auto Test Engineer | J40: FHM CMS | K40: HCM | L40: FHM | M40: FHM CMS | P40: Manual Test | Q40: Senior | R40: Allocated | W40: ATES04 | X40: Allocated | Y40: Allocated | Z40: Allocated | AA40: 1 | AB40: 1 | AC40: 1 | AD40: 1 | AE40: 100 | AF40: FR | AG40: FSO.HCM.FHM.CMS | AH40: FRDLO | AI40: External | AJ40: 40 | AK40: 40 | AL40: 40 | AM40: 40 | AN40: 40 | AO40: 40
A41: 40 | B41: Phan Văn Đại | C41: DaiPV14 | D41: SBR_Buhin26 | E41: OFF | F41: 46180 | G41: Associate Software Engineer | J41: FHM CMS | K41: HCM | L41: FHM | M41: FHM CMS | P41: Java Framework | Q41: Junior | R41: Allocated | W41: DEVE01 | X41: Allocated | Y41: Allocated | Z41: Allocated | AA41: 1 | AB41: 1 | AC41: 1 | AD41: 1 | AE41: 100 | AF41: SBR | AG41: FSO.HCM.FHM.CMS | AH41: SBR_Buhin26 | AI41: External | AJ41: 40 | AK41: 40 | AL41: 40 | AM41: 40 | AN41: 40 | AO41: 40
A42: 41 | B42: Lý Công Đăng | C42: DangLC1 | D42: SBR_Buhin26 | E42: OFF | F42: 46189 | G42: Associate Software Engineer | J42: FHM CMS | K42: HCM | L42: FHM | M42: FHM CMS | P42: Java Framework | Q42: Junior | R42: Allocated | S42: Nghỉ phép: 18-Aug-2026 ~ 18-Aug-2026 Nghỉ phép: 04-Aug-2026 ~ 04-Aug-2026 | W42: DEVE01 | X42: Allocated | Y42: Allocated | Z42: Allocated | AA42: 1 | AB42: 1 | AC42: 1 | AD42: 1 | AE42: 100 | AF42: SBR | AG42: FSO.HCM.FHM.CMS | AH42: SBR_Buhin26 | AI42: External | AJ42: 40 | AK42: 40 | AL42: 40 | AM42: 40 | AN42: 40 | AO42: 40
A43: 42 | B43: Nguyễn Hoàng Hải Đăng | C43: DangNHH | D43: C99.I5.VS 2026 | E43: OFF | F43: 43617 | G43: Principal Software Engineer | H43: 710 | I43: EnglishScore;FSOFT Foreign Language Proficiency Test - TOEIC Test;Advanced Designer Certificate;Core Designer Certificate;Google Cloud Certified - Associate Cloud Engineer;AWS Certified Solutions Architect - Associate;Google Cloud Certified Generative AI Leader;Microsoft Certified: Azure Fundamentals;Oracle Certified Associate, Java SE 8 Programmer;Microsoft Certified: Azure Data Fundamentals | J43: FHM CMS | K43: HCM | L43: FHM | M43: FHM CMS | N43: Java Framework | O43: Senior | P43: Artificial Intelligence (AI) | Q43: Senior | R43: Allocated | W43: DEVE05 | X43: Allocated | Y43: Allocated | Z43: Allocated | AA43: 1 | AB43: 1 | AC43: 1 | AD43: 0.75 | AE43: 100 | AF43: SBR | AG43: FSO.HCM.FHM.CMS | AH43: SBR_Buhin26 | AI43: External | AJ43: 40 | AK43: 40 | AL43: 40 | AM43: 40 | AN43: 40 | AO43: 40
A44: 43 | B44: Phan Hải Đăng | C44: DangPH3 | D44: FVD2025 | E44: OFF | F44: 42354 | G44: Senior Software Engineer | H44: 665 | I44: FSOFT Foreign Language Proficiency Test - TOEIC Test;Certified HIPAA Privacy Associate (CHPA);SQL;EnglishScore;Predix Certified Developer;GitHub Copilot;PROFESSIONAL SCRUM MASTER™ I;Enrich skills to succeed - .NET Technology;Enrich skills to succeed - Ruby Platform;Google Analytics Certification;SI Associate Certification Program;SQL (Intermediate);SQL (Basic);SQL (Advanced);Mendix Rapid Developer;Oracle Cloud Data Management 2023 Certified Foundations Associate;Oracle Cloud Infrastructure 2023 Certified Foundations Associate;NVIDIA Getting Started with AI on Jetson Nano;Core Designer Certificate;Advanced Designer Certificate;AWS Certified Cloud Practitioner | J44: FHM CMS | K44: HCM | L44: FHM | M44: FHM CMS | N44: C/C++ | O44: Senior | P44: Python Platform | Q44: Senior | R44: Allocated | S44: Nghỉ mát: 03-Sep-2026 ~ 07-Sep-2026 | W44: DEVE04 | X44: Allocated | Y44: Allocated | Z44: Allocated | AA44: 1 | AB44: 1 | AC44: 1 | AD44: 1 | AE44: 100 | AF44: COX-AM | AG44: FSO.HCM.FHM.AKAT | AH44: C99.I5.VS 2026 | AI44: External | AJ44: 40 | AK44: 40 | AL44: 40 | AM44: 40 | AN44: 40 | AO44: 40
A45: 44 | B45: Nguyễn Đức Danh | C45: DanhND5 | D45: C99.I5.LOG 2026 | E45: OFF | F45: 45931 | G45: Senior Software Tester | J45: FHM CMS | K45: HCM | L45: FHM | M45: FHM CMS | P45: Manual Test | Q45: Middle | R45: Allocated | W45: TEST03 | X45: Allocated | Y45: Allocated | Z45: Allocated | AA45: 1 | AB45: 1 | AC45: 1 | AD45: 1 | AE45: 100 | AF45: FR | AG45: FSO.HCM.FHM.CMS | AH45: FVD2025 | AI45: External | AJ45: 40 | AK45: 40 | AL45: 40 | AM45: 40 | AN45: 40 | AO45: 40
A46: 45 | B46: Chou Tùng Đạt | C46: DatCT1 | D46: FHM.One | E46: OFF | F46: 43102 | G46: Senior Software Engineer | H46: 955 | I46: Developing ASP.NET MVC Web Applications;C# Fundamentals;Microsoft Certified: Azure DevOps Engineer Expert;FSOFT Foreign Language Proficiency Test - TOEIC Test;TOEIC (Internal);EnglishScore;Cloud DevOps Engineer;Microsoft Certified: Azure Architect Technologies;Microsoft Specialist: Programming in C#;Associate Traditional Web Developer O11;Microsoft Certified: Azure Developer Associate;GitHub Copilot | J46: FHM CMS | K46: HCM | L46: FHM | M46: FHM CMS | N46: Azure Cloud | P46: Azure Cloud | Q46: Senior | R46: Allocated | W46: DEVE04 | X46: Allocated | Y46: Allocated | Z46: Allocated | AA46: 1 | AB46: 1 | AC46: 1 | AD46: 1 | AE46: 100 | AF46: COX-AM | AG46: FSO.HCM.FHM.AKAT | AH46: C99.I5.LOG 2026 | AI46: External | AJ46: 40 | AK46: 40 | AL46: 40 | AM46: 40 | AN46: 40 | AO46: 40
A47: 46 | B47: Hoàng Cao Đạt | C47: DatHC5 | D47: FRWMS2026 | E47: OFF | F47: 45977 | G47: Senior Business Analyst | I47: TOEIC Listening & Reading;Japanese Language Proficiency Test N1 | J47: FHM JFL | K47: HCM | L47: FHM | M47: FHM JFL | P47: Project Management | Q47: Middle | R47: Allocated | W47: BANE03 | X47: Allocated | Y47: Allocated | Z47: Allocated | AA47: 1 | AB47: 1 | AC47: 1 | AD47: 1 | AE47: 100 | AF47: FSU-FHM | AG47: FSO.HCM.FHM.META | AH47: FHM.One | AI47: Internal | AJ47: 40 | AK47: 40 | AL47: 40 | AM47: 40 | AN47: 40 | AO47: 40
A48: 47 | B48: Lương Hồ Đắc Đạt | C48: DatLHD1 | D48: FRWMS2026 | E48: OFF | F48: 45130 | G48: Software Engineer | H48: 710 | I48: Advanced Designer Certificate;Core Designer Certificate;NVIDIA Getting Started with AI on Jetson Nano;GitHub Copilot;Oracle Cloud Infrastructure 2025 Certified Foundations Associate;Oracle Data Platform 2025 Certified Foundations Associate;AWS Certified Solutions Architect - Associate;Google Cloud Certified Generative AI Leader;Enrich skills to succeed - Low-Code;ML Practitioner Certificate;Developer Certificate;MLOps Practitioner Certificate;EnglishScore | J48: FHM CMS | K48: HCM | L48: FHM | M48: FHM CMS | N48: Fullstack QE/QC | P48: Java Framework | Q48: Middle | R48: Allocated | W48: DEVE02 | X48: Allocated | Y48: Allocated | Z48: Not-yet-Planned | AA48: 1 | AB48: 1 | AC48: 1 | AD48: 0 | AE48: 100 | AF48: FR | AG48: FSO.HCM.FHM.CMS | AH48: FRWMS2026 | AI48: External | AJ48: 40 | AK48: 40 | AL48: 40 | AM48: 40 | AN48: 40 | AO48: 40
A49: 48 | B49: Nguyễn Duy Đạt | C49: DatND8 | D49: MetalAlpha | E49: OFF | F49: 43822 | G49: Senior Software Engineer | H49: 710 | I49: FSOFT Foreign Language Proficiency Test - TOEIC Test;SQL;EnglishScore;Design for Performance and Scalability;Introduction to SQL;GitHub Copilot;AWS Cloud Architect;Cloud Developer;Design for Availability, Reliability, and Resiliency;Design for Security;Java Web Developer;Cloud DevOps Engineer;Java Programming;Advanced Designer Certificate;Core Designer Certificate;Oracle Cloud Infrastructure for Sunbird Ed Specialty;Digital Transformation for Business Leaders | J49: FHM CMS | K49: HCM | L49: FHM | M49: FHM CMS | N49: Java Framework | O49: Middle | P49: Java Framework | Q49: Senior | R49: Allocated | W49: DEVE03 | X49: Allocated | Y49: Allocated | Z49: Not-yet-Planned | AA49: 1 | AB49: 1 | AC49: 1 | AD49: 0 | AE49: 100 | AF49: FR | AG49: FSO.HCM.FHM.CMS | AH49: FRWMS2026 | AI49: External | AJ49: 40 | AK49: 40 | AL49: 40 | AM49: 40 | AN49: 40 | AO49: 40
A50: 49 | B50: Nguyễn Lê Thành Đạt | C50: DatNLT1 | D50: JOCAR_Replace | E50: OFF | F50: 46023 | G50: Associate Business Analyst | I50: GitHub Copilot | J50: FHM CMS | K50: HCM | L50: FHM | M50: FHM CMS | P50: BA | Q50: Junior | R50: Allocated | W50: BANE01 | X50: Allocated | Y50: Allocated | Z50: Allocated | AA50: 1 | AB50: 1 | AC50: 1 | AD50: 1 | AE50: 100 | AF50: MOC | AG50: FSO.HCM.FHM.CMS | AH50: MetalAlpha | AI50: External | AJ50: 40 | AK50: 40 | AL50: 40 | AM50: 40 | AN50: 40 | AO50: 40
A51: 50 | B51: Phạm Thành Đạt | C51: DatPT102 | D51: OPNEXT88 | E51: OFF | F51: 45398 | G51: Senior Software Tester | H51: 710 | I51: EnglishScore;ISTQB Certified Tester Advanced Level - Test Analyst | J51: FHM CMS | K51: HCM | L51: FHM | M51: FHM CMS | P51: Manual Test | Q51: Middle | R51: Allocated | W51: TEST03 | X51: Allocated | Y51: Allocated | Z51: Allocated | AA51: 1 | AB51: 1 | AC51: 1 | AD51: 1 | AE51: 100 | AF51: JJCM | AG51: FSO.HCM.FHM.CMS | AH51: JOCAR_Replace | AI51: External | AJ51: 40 | AK51: 40 | AL51: 40 | AM51: 40 | AN51: 40 | AO51: 40
